{
  "type": "Feature",
  "properties": {
    "gn:admin1_code":"N",
    "gn:admin2_code":"21",
    "gn:asciiname":"Fokodoumandou",
    "gn:country_code":"GN",
    "gn:dem":536,
    "gn:feature_class":"P",
    "gn:feature_code":"PPL",
    "gn:name":"Fokodoumandou",
    "gn:population":0,
    "gn:timezone":"Africa/Conakry",
    "iso:country":"GN",
    "wof:name":"Fokodoumandou",
    "wof:placetype":"locality"
},
  "geometry": {"coordinates":[-9.47361,8.52889],"type":"Point"}
}