{
  "type": "Feature",
  "properties": {
    "gn:admin1_code":"N",
    "gn:admin2_code":"38",
    "gn:asciiname":"Kelema",
    "gn:country_code":"GN",
    "gn:dem":484,
    "gn:feature_class":"P",
    "gn:feature_code":"PPL",
    "gn:name":"K\u00e9l\u00e9ma",
    "gn:population":0,
    "gn:timezone":"Africa/Conakry",
    "iso:country":"GN",
    "name:und_x_variant":[
        "K\u00e9r\u00e9na",
        "K\u00e9r\u00e9ma",
        "K\u00e9l\u00e9ma"
    ],
    "wof:name":"Kelema",
    "wof:placetype":"locality"
},
  "geometry": {"coordinates":[-8.91222,7.70806],"type":"Point"}
}