{
  "type": "Feature",
  "properties": {
    "gn:admin1_code":"B",
    "gn:admin2_code":"02",
    "gn:asciiname":"Tamalan",
    "gn:country_code":"GN",
    "gn:dem":56,
    "gn:feature_class":"P",
    "gn:feature_code":"PPL",
    "gn:name":"Tamalan",
    "gn:population":0,
    "gn:timezone":"Africa/Conakry",
    "iso:country":"GN",
    "wof:name":"Tamalan",
    "wof:placetype":"locality"
},
  "geometry": {"coordinates":[-13.91667,10.36667],"type":"Point"}
}