{
  "type": "Feature",
  "properties": {
    "gn:admin1_code":"B",
    "gn:admin2_code":"02",
    "gn:asciiname":"Duera",
    "gn:cc2":"GN",
    "gn:country_code":"GN",
    "gn:dem":0,
    "gn:feature_class":"P",
    "gn:feature_code":"PPL",
    "gn:name":"Du\u00e9ra",
    "gn:population":0,
    "gn:timezone":"Africa/Conakry",
    "iso:country":"GN",
    "name:und_x_variant":[
        "Diurera",
        "Disira",
        "Diourera",
        "Du\u00e9ra"
    ],
    "wof:name":"Duera",
    "wof:placetype":"locality"
},
  "geometry": {"coordinates":[-13.93333,10.01667],"type":"Point"}
}