{
  "type": "Feature",
  "properties": {
    "gn:admin1_code":"N",
    "gn:admin2_code":"17",
    "gn:asciiname":"Sobadou",
    "gn:country_code":"GN",
    "gn:dem":456,
    "gn:feature_class":"P",
    "gn:feature_code":"PPL",
    "gn:name":"Sobadou",
    "gn:population":0,
    "gn:timezone":"Africa/Conakry",
    "iso:country":"GN",
    "wof:name":"Sobadou",
    "wof:placetype":"locality"
},
  "geometry": {"coordinates":[-10.39722,8.97833],"type":"Point"}
}