{
  "type": "Feature",
  "properties": {
    "gn:admin1_code":"L",
    "gn:admin2_code":"22",
    "gn:asciiname":"Diaoia",
    "gn:country_code":"GN",
    "gn:dem":462,
    "gn:feature_class":"P",
    "gn:feature_code":"PPL",
    "gn:name":"Diao\u00efa",
    "gn:population":0,
    "gn:timezone":"Africa/Conakry",
    "iso:country":"GN",
    "wof:name":"Diaoia",
    "wof:placetype":"locality"
},
  "geometry": {"coordinates":[-12.349,12.1225],"type":"Point"}
}