{
  "type": "Feature",
  "properties": {
    "gn:admin1_code":"N",
    "gn:admin2_code":"01",
    "gn:asciiname":"Domanidougou",
    "gn:country_code":"GN",
    "gn:dem":647,
    "gn:feature_class":"P",
    "gn:feature_code":"PPL",
    "gn:name":"Domanidougou",
    "gn:population":0,
    "gn:timezone":"Africa/Conakry",
    "iso:country":"GN",
    "wof:name":"Domanidougou",
    "wof:placetype":"locality"
},
  "geometry": {"coordinates":[-8.76667,8.45],"type":"Point"}
}