{
  "type": "Feature",
  "properties": {
    "gn:admin1_code":"N",
    "gn:admin2_code":"13",
    "gn:asciiname":"Konian",
    "gn:country_code":"GN",
    "gn:dem":533,
    "gn:feature_class":"P",
    "gn:feature_code":"PPL",
    "gn:name":"Konian",
    "gn:population":0,
    "gn:timezone":"Africa/Conakry",
    "iso:country":"GN",
    "wof:name":"Konian",
    "wof:placetype":"locality"
},
  "geometry": {"coordinates":[-10.10972,8.91528],"type":"Point"}
}