{
  "type": "Feature",
  "properties": {
    "gn:admin1_code":"D",
    "gn:admin2_code":"27",
    "gn:asciiname":"Denda",
    "gn:country_code":"GN",
    "gn:dem":221,
    "gn:feature_class":"P",
    "gn:feature_code":"PPL",
    "gn:name":"Denda",
    "gn:population":0,
    "gn:timezone":"Africa/Conakry",
    "iso:country":"GN",
    "wof:name":"Denda",
    "wof:placetype":"locality"
},
  "geometry": {"coordinates":[-13.18333,11.05],"type":"Point"}
}