{
  "type": "Feature",
  "properties": {
    "gn:admin1_code":"K",
    "gn:admin2_code":"39",
    "gn:asciiname":"Ouandan",
    "gn:country_code":"GN",
    "gn:dem":352,
    "gn:feature_class":"P",
    "gn:feature_code":"PPL",
    "gn:name":"Ouandan",
    "gn:population":0,
    "gn:timezone":"Africa/Conakry",
    "iso:country":"GN",
    "wof:name":"Ouandan",
    "wof:placetype":"locality"
},
  "geometry": {"coordinates":[-8.93333,11.41667],"type":"Point"}
}