{
  "type": "Feature",
  "properties": {
    "gn:admin1_code":"F",
    "gn:admin2_code":"17",
    "gn:asciiname":"Koma",
    "gn:country_code":"GN",
    "gn:dem":549,
    "gn:feature_class":"P",
    "gn:feature_code":"PPL",
    "gn:name":"Koma",
    "gn:population":0,
    "gn:timezone":"Africa/Conakry",
    "iso:country":"GN",
    "name:ara_x_preferred":[
        "\u063a\u064a\u0628\u0648\u0628\u0629"
    ],
    "name:ceb_x_preferred":[
        "Koma"
    ],
    "name:ces_x_preferred":[
        "Koma"
    ],
    "name:dan_x_preferred":[
        "Koma"
    ],
    "name:deu_x_preferred":[
        "Koma"
    ],
    "name:eus_x_preferred":[
        "Koma"
    ],
    "name:fra_x_preferred":[
        "Koma"
    ],
    "name:hrv_x_preferred":[
        "Koma"
    ],
    "name:ind_x_preferred":[
        "Koma"
    ],
    "name:nds_x_preferred":[
        "Koma"
    ],
    "name:nno_x_preferred":[
        "Koma"
    ],
    "name:pol_x_preferred":[
        "Koma"
    ],
    "name:slk_x_preferred":[
        "Koma"
    ],
    "name:swe_x_preferred":[
        "Koma"
    ],
    "wof:name":"Koma",
    "wof:placetype":"locality"
},
  "geometry": {"coordinates":[-10.16667,9.03333],"type":"Point"}
}