{
  "type": "Feature",
  "properties": {
    "gn:admin1_code":"B",
    "gn:admin2_code":"18",
    "gn:asciiname":"Sanka",
    "gn:country_code":"GN",
    "gn:dem":68,
    "gn:feature_class":"P",
    "gn:feature_code":"PPL",
    "gn:name":"Sanka",
    "gn:population":0,
    "gn:timezone":"Africa/Conakry",
    "iso:country":"GN",
    "wof:name":"Sanka",
    "wof:placetype":"locality"
},
  "geometry": {"coordinates":[-13.55,12.38333],"type":"Point"}
}