{
  "type": "Feature",
  "properties": {
    "gn:admin1_code":"K",
    "gn:admin2_code":"39",
    "gn:asciiname":"Bodala",
    "gn:country_code":"GN",
    "gn:dem":337,
    "gn:feature_class":"P",
    "gn:feature_code":"PPL",
    "gn:name":"Bodala",
    "gn:population":0,
    "gn:timezone":"Africa/Conakry",
    "iso:country":"GN",
    "name:und_x_variant":[
        "Badala",
        "Bodala"
    ],
    "wof:name":"Bodala",
    "wof:placetype":"locality"
},
  "geometry": {"coordinates":[-9.36667,12.08333],"type":"Point"}
}