{
  "type": "Feature",
  "properties": {
    "gn:admin1_code":"D",
    "gn:admin2_code":"10",
    "gn:asciiname":"Silemanya",
    "gn:country_code":"GN",
    "gn:dem":24,
    "gn:feature_class":"P",
    "gn:feature_code":"PPL",
    "gn:name":"Sil\u00e9manya",
    "gn:population":0,
    "gn:timezone":"Africa/Conakry",
    "iso:country":"GN",
    "wof:name":"Silemanya",
    "wof:placetype":"locality"
},
  "geometry": {"coordinates":[-13.12944,9.51611],"type":"Point"}
}