{
  "type": "Feature",
  "properties": {
    "gn:admin1_code":"K",
    "gn:admin2_code":"39",
    "gn:asciiname":"Kouroubala",
    "gn:country_code":"GN",
    "gn:dem":332,
    "gn:feature_class":"P",
    "gn:feature_code":"PPL",
    "gn:name":"Kouroubala",
    "gn:population":0,
    "gn:timezone":"Africa/Conakry",
    "iso:country":"GN",
    "wof:name":"Kouroubala",
    "wof:placetype":"locality"
},
  "geometry": {"coordinates":[-9.18333,12.01667],"type":"Point"}
}