{
  "type": "Feature",
  "properties": {
    "gn:admin1_code":"K",
    "gn:admin2_code":"39",
    "gn:asciiname":"Banankoro",
    "gn:country_code":"GN",
    "gn:dem":402,
    "gn:feature_class":"P",
    "gn:feature_code":"PPL",
    "gn:name":"Banankoro",
    "gn:population":0,
    "gn:timezone":"Africa/Conakry",
    "iso:country":"GN",
    "name:ceb_x_preferred":[
        "Banankoro"
    ],
    "name:swe_x_preferred":[
        "Banankoro"
    ],
    "wof:name":"Banankoro",
    "wof:placetype":"locality"
},
  "geometry": {"coordinates":[-8.98333,11.81667],"type":"Point"}
}