{
  "type": "Feature",
  "properties": {
    "gn:admin1_code":"K",
    "gn:admin2_code":"39",
    "gn:asciiname":"Kounadibala",
    "gn:country_code":"GN",
    "gn:dem":361,
    "gn:feature_class":"P",
    "gn:feature_code":"PPL",
    "gn:name":"Kounadibala",
    "gn:population":0,
    "gn:timezone":"Africa/Conakry",
    "iso:country":"GN",
    "wof:name":"Kounadibala",
    "wof:placetype":"locality"
},
  "geometry": {"coordinates":[-8.81667,11.46667],"type":"Point"}
}