{
  "type": "Feature",
  "properties": {
    "gn:admin1_code":"D",
    "gn:admin2_code":"10",
    "gn:asciiname":"Sarrea",
    "gn:cc2":"GN",
    "gn:country_code":"GN",
    "gn:dem":39,
    "gn:feature_class":"P",
    "gn:feature_code":"PPL",
    "gn:name":"Sarr\u00e9a",
    "gn:population":0,
    "gn:timezone":"Africa/Conakry",
    "iso:country":"GN",
    "name:und_x_variant":[
        "Sariea",
        "Sarr\u00e9a"
    ],
    "wof:name":"Sarrea",
    "wof:placetype":"locality"
},
  "geometry": {"coordinates":[-13.0125,9.18389],"type":"Point"}
}