{
  "type": "Feature",
  "properties": {
    "gn:admin1_code":"N",
    "gn:admin2_code":"21",
    "gn:asciiname":"Bokoni",
    "gn:cc2":"GN",
    "gn:country_code":"GN",
    "gn:dem":559,
    "gn:feature_class":"P",
    "gn:feature_code":"PPL",
    "gn:name":"Bokoni",
    "gn:population":0,
    "gn:timezone":"Africa/Conakry",
    "iso:country":"GN",
    "name:azb_x_preferred":[
        "\u0628\u06a9\u0646\u06cc"
    ],
    "name:fas_x_preferred":[
        "\u0628\u06a9\u0646\u06cc"
    ],
    "name:und_x_variant":[
        "Bokouni",
        "Bokoni"
    ],
    "wof:name":"Bokoni",
    "wof:placetype":"locality"
},
  "geometry": {"coordinates":[-9.49667,8.44139],"type":"Point"}
}