{
  "type": "Feature",
  "properties": {
    "gn:admin1_code":"D",
    "gn:admin2_code":"16",
    "gn:asciiname":"Borea",
    "gn:country_code":"GN",
    "gn:dem":244,
    "gn:feature_class":"P",
    "gn:feature_code":"PPL",
    "gn:name":"Borea",
    "gn:population":0,
    "gn:timezone":"Africa/Conakry",
    "iso:country":"GN",
    "name:deu_x_preferred":[
        "Borea"
    ],
    "name:ita_x_preferred":[
        "Borea"
    ],
    "name:pol_x_preferred":[
        "Borea"
    ],
    "wof:name":"Borea",
    "wof:placetype":"locality"
},
  "geometry": {"coordinates":[-12.81667,9.96667],"type":"Point"}
}