{
  "type": "Feature",
  "properties": {
    "gn:admin1_code":"M",
    "gn:admin2_code":"23",
    "gn:asciiname":"Mali",
    "gn:country_code":"GN",
    "gn:dem":758,
    "gn:feature_class":"P",
    "gn:feature_code":"PPL",
    "gn:name":"Mali",
    "gn:population":0,
    "gn:timezone":"Africa/Conakry",
    "iso:country":"GN",
    "wof:name":"Mali",
    "wof:placetype":"locality"
},
  "geometry": {"coordinates":[-11.71667,10.78333],"type":"Point"}
}