{
  "type": "Feature",
  "properties": {
    "gn:admin1_code":"D",
    "gn:admin2_code":"31",
    "gn:asciiname":"Simbaya",
    "gn:country_code":"GN",
    "gn:dem":325,
    "gn:feature_class":"P",
    "gn:feature_code":"PPL",
    "gn:name":"Simbaya",
    "gn:population":0,
    "gn:timezone":"Africa/Conakry",
    "iso:country":"GN",
    "name:und_x_variant":[
        "Sambaya",
        "Simbaya"
    ],
    "wof:name":"Simbaya",
    "wof:placetype":"locality"
},
  "geometry": {"coordinates":[-13.28333,10.31667],"type":"Point"}
}