{
  "type": "Feature",
  "properties": {
    "gn:admin1_code":"K",
    "gn:admin2_code":"17",
    "gn:asciiname":"Damanguebedou",
    "gn:country_code":"GN",
    "gn:dem":809,
    "gn:feature_class":"P",
    "gn:feature_code":"PPL",
    "gn:name":"Damangueb\u00e8dou",
    "gn:population":0,
    "gn:timezone":"Africa/Conakry",
    "iso:country":"GN",
    "name:und_x_variant":[
        "Damangu\u00e9dou",
        "Damangueb\u00e8dou"
    ],
    "wof:name":"Damanguebedou",
    "wof:placetype":"locality"
},
  "geometry": {"coordinates":[-9.3575,8.97917],"type":"Point"}
}