{
  "type": "Feature",
  "properties": {
    "gn:admin1_code":"F",
    "gn:admin2_code":"09",
    "gn:asciiname":"Youroukouria",
    "gn:country_code":"GN",
    "gn:dem":609,
    "gn:feature_class":"P",
    "gn:feature_code":"PPL",
    "gn:name":"Youroukouria",
    "gn:population":0,
    "gn:timezone":"Africa/Conakry",
    "iso:country":"GN",
    "wof:name":"Youroukouria",
    "wof:placetype":"locality"
},
  "geometry": {"coordinates":[-10.65,9.23333],"type":"Point"}
}