{
  "type": "Feature",
  "properties": {
    "gn:admin1_code":"N",
    "gn:admin2_code":"13",
    "gn:asciiname":"Tinguedou",
    "gn:country_code":"GN",
    "gn:dem":437,
    "gn:feature_class":"P",
    "gn:feature_code":"PPL",
    "gn:name":"Tingu\u00e8dou",
    "gn:population":0,
    "gn:timezone":"Africa/Conakry",
    "iso:country":"GN",
    "wof:name":"Tinguedou",
    "wof:placetype":"locality"
},
  "geometry": {"coordinates":[-10.3175,8.87889],"type":"Point"}
}