{
  "type": "Feature",
  "properties": {
    "gn:admin1_code":"D",
    "gn:admin2_code":"31",
    "gn:asciiname":"Kereba",
    "gn:country_code":"GN",
    "gn:dem":2,
    "gn:feature_class":"P",
    "gn:feature_code":"PPL",
    "gn:name":"K\u00e9r\u00e9ba",
    "gn:population":0,
    "gn:timezone":"Africa/Conakry",
    "iso:country":"GN",
    "wof:name":"Kereba",
    "wof:placetype":"locality"
},
  "geometry": {"coordinates":[-13.59444,9.74528],"type":"Point"}
}