{
  "type": "Feature",
  "properties": {
    "iso:country":"GN",
    "qs:gn_pop":0,
    "qs:name":"Kindia-Centre",
    "qs:name_adm0":"Guin\u00e9e",
    "qs:name_adm1":"Kindia",
    "qs:photos":3,
    "qs:photos_1k":1,
    "qs:photos_9k":1,
    "qs:photos_9r":1,
    "qs:photos_all":8,
    "qs:photos_sr":1,
    "qs:placetype":"LocalAdmin",
    "qs:pop_sr":"0",
    "qs:woe_adm0":23424835,
    "wof:name":"Kindia-Centre",
    "wof:placetype":"localadmin"
},
  "geometry": {"coordinates":[-12.870483,10.058107],"type":"Point"}
}