{
  "type": "Feature",
  "properties": {
    "gn:admin1_code":"F",
    "gn:admin2_code":"07",
    "gn:asciiname":"Dibaya",
    "gn:country_code":"GN",
    "gn:dem":643,
    "gn:feature_class":"P",
    "gn:feature_code":"PPL",
    "gn:name":"Dibaya",
    "gn:population":0,
    "gn:timezone":"Africa/Conakry",
    "iso:country":"GN",
    "wof:name":"Dibaya",
    "wof:placetype":"locality"
},
  "geometry": {"coordinates":[-10.96667,11.25],"type":"Point"}
}