{
  "type": "Feature",
  "properties": {
    "gn:admin1_code":"F",
    "gn:admin2_code":"07",
    "gn:asciiname":"Dibaya",
    "gn:country_code":"GN",
    "gn:dem":643,
    "gn:feature_class":"P",
    "gn:feature_code":"PPL",
    "gn:name":"Dibaya",
    "gn:population":0,
    "gn:timezone":"Africa/Conakry",
    "iso:country":"GN",
    "name:ara_x_preferred":[
        "\u062f\u0628\u0627\u064a\u0629"
    ],
    "name:ben_x_preferred":[
        "\u09a6\u09bf\u09ac\u09be\u09df\u09be"
    ],
    "name:deu_x_preferred":[
        "Dibaya"
    ],
    "name:ell_x_preferred":[
        "\u039d\u03c4\u03b9\u03bc\u03c0\u03ac\u03b3\u03b9\u03b1"
    ],
    "name:fas_x_preferred":[
        "\u062f\u06cc\u0628\u0627\u06cc\u0627"
    ],
    "name:fra_x_preferred":[
        "Dibaya"
    ],
    "name:heb_x_preferred":[
        "\u05d3\u05d9\u05d1\u05d9\u05d9\u05d4"
    ],
    "name:hin_x_preferred":[
        "\u0921\u093f\u092c\u093e\u092f\u093e"
    ],
    "name:hun_x_preferred":[
        "Dibaya"
    ],
    "name:ind_x_preferred":[
        "Dibaya"
    ],
    "name:ita_x_preferred":[
        "Dibaya"
    ],
    "name:kor_x_preferred":[
        "\ub514\ubc14\uc57c"
    ],
    "name:pol_x_preferred":[
        "Dibaya"
    ],
    "name:por_x_preferred":[
        "Dibaya"
    ],
    "name:ron_x_preferred":[
        "Dibaya"
    ],
    "name:rus_x_preferred":[
        "\u0414\u0438\u0431\u0435\u0439\u044f"
    ],
    "name:spa_x_preferred":[
        "Dibaya"
    ],
    "name:swe_x_preferred":[
        "Dibaya"
    ],
    "name:tur_x_preferred":[
        "Dibaya"
    ],
    "name:ukr_x_preferred":[
        "\u0414\u0456\u0431\u0435\u0439\u044f"
    ],
    "name:urd_x_preferred":[
        "\u062f\u06cc\u0628\u0627\u06cc\u0627"
    ],
    "name:vie_x_preferred":[
        "Dibaya"
    ],
    "wof:name":"Dibaya",
    "wof:placetype":"locality"
},
  "geometry": {"coordinates":[-10.96667,11.25],"type":"Point"}
}