{
  "type": "Feature",
  "properties": {
    "gn:admin1_code":"K",
    "gn:admin2_code":"32",
    "gn:asciiname":"Kobala",
    "gn:country_code":"GN",
    "gn:dem":470,
    "gn:feature_class":"P",
    "gn:feature_code":"PPL",
    "gn:name":"Kobala",
    "gn:population":0,
    "gn:timezone":"Africa/Conakry",
    "iso:country":"GN",
    "wof:name":"Kobala",
    "wof:placetype":"locality"
},
  "geometry": {"coordinates":[-9.08333,10.11667],"type":"Point"}
}