{
  "type": "Feature",
  "properties": {
    "gn:admin1_code":"K",
    "gn:admin2_code":"15",
    "gn:asciiname":"Koniani",
    "gn:country_code":"GN",
    "gn:dem":638,
    "gn:feature_class":"P",
    "gn:feature_code":"PPL",
    "gn:name":"Koniani",
    "gn:population":0,
    "gn:timezone":"Africa/Conakry",
    "iso:country":"GN",
    "wof:name":"Koniani",
    "wof:placetype":"locality"
},
  "geometry": {"coordinates":[-8.73333,9.23333],"type":"Point"}
}