{
  "type": "Feature",
  "properties": {
    "gn:admin1_code":"L",
    "gn:admin2_code":"22",
    "gn:asciiname":"Godiolire",
    "gn:country_code":"GN",
    "gn:dem":566,
    "gn:feature_class":"P",
    "gn:feature_code":"PPL",
    "gn:name":"Godiolir\u00e9",
    "gn:population":0,
    "gn:timezone":"Africa/Conakry",
    "iso:country":"GN",
    "wof:name":"Godiolire",
    "wof:placetype":"locality"
},
  "geometry": {"coordinates":[-12.6925,12.0779],"type":"Point"}
}