{
  "type": "Feature",
  "properties": {
    "gn:admin1_code":"F",
    "gn:admin2_code":"07",
    "gn:asciiname":"Lountou",
    "gn:country_code":"GN",
    "gn:dem":550,
    "gn:feature_class":"P",
    "gn:feature_code":"PPL",
    "gn:name":"Lountou",
    "gn:population":0,
    "gn:timezone":"Africa/Conakry",
    "iso:country":"GN",
    "wof:name":"Lountou",
    "wof:placetype":"locality"
},
  "geometry": {"coordinates":[-10.81667,11.55],"type":"Point"}
}