{
  "type": "Feature",
  "properties": {
    "gn:admin1_code":"K",
    "gn:admin2_code":"15",
    "gn:asciiname":"Sirimoroudougou",
    "gn:country_code":"GN",
    "gn:dem":543,
    "gn:feature_class":"P",
    "gn:feature_code":"PPL",
    "gn:name":"Sirimoroudougou",
    "gn:population":0,
    "gn:timezone":"Africa/Conakry",
    "iso:country":"GN",
    "name:und_x_variant":[
        "Siromoridougou",
        "Siromaridougou",
        "Sirimoroudougou"
    ],
    "wof:name":"Sirimoroudougou",
    "wof:placetype":"locality"
},
  "geometry": {"coordinates":[-9.06667,9.53333],"type":"Point"}
}