{
  "type": "Feature",
  "properties": {
    "gn:admin1_code":"B",
    "gn:admin2_code":"18",
    "gn:asciiname":"Pouniar",
    "gn:country_code":"GN",
    "gn:dem":162,
    "gn:feature_class":"P",
    "gn:feature_code":"PPL",
    "gn:name":"Pouniar",
    "gn:population":0,
    "gn:timezone":"Africa/Conakry",
    "iso:country":"GN",
    "wof:name":"Pouniar",
    "wof:placetype":"locality"
},
  "geometry": {"coordinates":[-12.923,12.2447],"type":"Point"}
}