{
  "type": "Feature",
  "properties": {
    "gn:admin1_code":"B",
    "gn:admin2_code":"18",
    "gn:asciiname":"Soukoutou Foulbe",
    "gn:country_code":"GN",
    "gn:dem":58,
    "gn:feature_class":"P",
    "gn:feature_code":"PPL",
    "gn:name":"Soukoutou Foulb\u00e9",
    "gn:population":0,
    "gn:timezone":"Africa/Conakry",
    "iso:country":"GN",
    "wof:name":"Soukoutou Foulbe",
    "wof:placetype":"locality"
},
  "geometry": {"coordinates":[-13.56667,12.53333],"type":"Point"}
}