{
  "type": "Feature",
  "properties": {
    "gn:admin1_code":"F",
    "gn:admin2_code":"09",
    "gn:asciiname":"Sokourala",
    "gn:country_code":"GN",
    "gn:dem":445,
    "gn:feature_class":"P",
    "gn:feature_code":"PPL",
    "gn:name":"Sokourala",
    "gn:population":0,
    "gn:timezone":"Africa/Conakry",
    "iso:country":"GN",
    "wof:name":"Sokourala",
    "wof:placetype":"locality"
},
  "geometry": {"coordinates":[-10.66667,10.05],"type":"Point"}
}