{
  "type": "Feature",
  "properties": {
    "gn:admin1_code":"N",
    "gn:admin2_code":"13",
    "gn:asciiname":"Yefoula",
    "gn:country_code":"GN",
    "gn:dem":367,
    "gn:feature_class":"P",
    "gn:feature_code":"PPL",
    "gn:name":"Y\u00e9foula",
    "gn:population":0,
    "gn:timezone":"Africa/Conakry",
    "iso:country":"GN",
    "name:eng_x_preferred":[
        "Y\u00e9foula"
    ],
    "wof:name":"Yefoula",
    "wof:placetype":"locality"
},
  "geometry": {"coordinates":[-10.56667,8.81667],"type":"Point"}
}