{
  "type": "Feature",
  "properties": {
    "gn:admin1_code":"D",
    "gn:admin2_code":"31",
    "gn:asciiname":"Sanhia",
    "gn:country_code":"GN",
    "gn:dem":28,
    "gn:feature_class":"P",
    "gn:feature_code":"PPL",
    "gn:name":"Sanhia",
    "gn:population":0,
    "gn:timezone":"Africa/Conakry",
    "iso:country":"GN",
    "wof:name":"Sanhia",
    "wof:placetype":"locality"
},
  "geometry": {"coordinates":[-13.46417,9.9125],"type":"Point"}
}