{
  "type": "Feature",
  "properties": {
    "gn:admin1_code":"N",
    "gn:admin2_code":"01",
    "gn:asciiname":"Boumoukoro",
    "gn:country_code":"GN",
    "gn:dem":657,
    "gn:feature_class":"P",
    "gn:feature_code":"PPL",
    "gn:name":"Boumoukoro",
    "gn:population":0,
    "gn:timezone":"Africa/Conakry",
    "iso:country":"GN",
    "wof:name":"Boumoukoro",
    "wof:placetype":"locality"
},
  "geometry": {"coordinates":[-8.73333,8.41667],"type":"Point"}
}