{
  "type": "Feature",
  "properties": {
    "gn:admin1_code":"K",
    "gn:admin2_code":"01",
    "gn:asciiname":"Bofodougou",
    "gn:country_code":"GN",
    "gn:dem":676,
    "gn:feature_class":"P",
    "gn:feature_code":"PPL",
    "gn:name":"Bofodougou",
    "gn:population":0,
    "gn:timezone":"Africa/Conakry",
    "iso:country":"GN",
    "wof:name":"Bofodougou",
    "wof:placetype":"locality"
},
  "geometry": {"coordinates":[-8.98333,8.86667],"type":"Point"}
}