{
  "type": "Feature",
  "properties": {
    "gn:admin1_code":"N",
    "gn:admin2_code":"01",
    "gn:asciiname":"Guigbadougou",
    "gn:country_code":"GN",
    "gn:dem":682,
    "gn:feature_class":"P",
    "gn:feature_code":"PPL",
    "gn:name":"Guigbadougou",
    "gn:population":0,
    "gn:timezone":"Africa/Conakry",
    "iso:country":"GN",
    "wof:name":"Guigbadougou",
    "wof:placetype":"locality"
},
  "geometry": {"coordinates":[-8.36667,8.98333],"type":"Point"}
}