{
  "type": "Feature",
  "properties": {
    "gn:admin1_code":"L",
    "gn:admin2_code":"22",
    "gn:asciiname":"Wediawarou",
    "gn:country_code":"GN",
    "gn:dem":233,
    "gn:feature_class":"P",
    "gn:feature_code":"PPL",
    "gn:name":"W\u00e9diawarou",
    "gn:population":0,
    "gn:timezone":"Africa/Conakry",
    "iso:country":"GN",
    "wof:name":"Wediawarou",
    "wof:placetype":"locality"
},
  "geometry": {"coordinates":[-12.1831,12.1962],"type":"Point"}
}