{
  "type": "Feature",
  "properties": {
    "gn:admin1_code":"L",
    "gn:admin2_code":"28",
    "gn:asciiname":"Soumpoura",
    "gn:country_code":"GN",
    "gn:dem":746,
    "gn:feature_class":"P",
    "gn:feature_code":"PPL",
    "gn:name":"Soumpoura",
    "gn:population":0,
    "gn:timezone":"Africa/Conakry",
    "iso:country":"GN",
    "wof:name":"Soumpoura",
    "wof:placetype":"locality"
},
  "geometry": {"coordinates":[-11.71667,11.41667],"type":"Point"}
}