{
  "type": "Feature",
  "properties": {
    "gn:admin1_code":"B",
    "gn:admin2_code":"02",
    "gn:asciiname":"Boufou",
    "gn:country_code":"GN",
    "gn:dem":25,
    "gn:feature_class":"P",
    "gn:feature_code":"PPL",
    "gn:name":"Boufou",
    "gn:population":0,
    "gn:timezone":"Africa/Conakry",
    "iso:country":"GN",
    "wof:name":"Boufou",
    "wof:placetype":"locality"
},
  "geometry": {"coordinates":[-13.8625,9.99306],"type":"Point"}
}