{
  "type": "Feature",
  "properties": {
    "gn:admin1_code":"F",
    "gn:admin2_code":"07",
    "gn:asciiname":"Ndantari",
    "gn:country_code":"GN",
    "gn:dem":564,
    "gn:feature_class":"P",
    "gn:feature_code":"PPL",
    "gn:name":"Ndantari",
    "gn:population":0,
    "gn:timezone":"Africa/Conakry",
    "iso:country":"GN",
    "wof:name":"Ndantari",
    "wof:placetype":"locality"
},
  "geometry": {"coordinates":[-10.81667,12.08333],"type":"Point"}
}