{
  "type": "Feature",
  "properties": {
    "gn:admin1_code":"N",
    "gn:admin2_code":"01",
    "gn:asciiname":"Bonodou",
    "gn:cc2":"GN",
    "gn:country_code":"GN",
    "gn:dem":532,
    "gn:feature_class":"P",
    "gn:feature_code":"PPL",
    "gn:name":"Bonodou",
    "gn:population":0,
    "gn:timezone":"Africa/Conakry",
    "iso:country":"GN",
    "name:und_x_variant":[
        "Bohodou",
        "Bonodou"
    ],
    "wof:name":"Bonodou",
    "wof:placetype":"locality"
},
  "geometry": {"coordinates":[-8.33333,9.33333],"type":"Point"}
}