{
  "type": "Feature",
  "properties": {
    "gn:admin1_code":"N",
    "gn:admin2_code":"38",
    "gn:asciiname":"Gala",
    "gn:country_code":"GN",
    "gn:dem":497,
    "gn:feature_class":"P",
    "gn:feature_code":"PPL",
    "gn:name":"Gala",
    "gn:population":0,
    "gn:timezone":"Africa/Conakry",
    "iso:country":"GN",
    "name:und_x_variant":[
        "Galai",
        "Gala"
    ],
    "wof:name":"Gala",
    "wof:placetype":"locality"
},
  "geometry": {"coordinates":[-8.77028,7.77417],"type":"Point"}
}