{
  "type": "Feature",
  "properties": {
    "gn:admin1_code":"K",
    "gn:admin2_code":"37",
    "gn:asciiname":"Gouri",
    "gn:country_code":"GN",
    "gn:dem":368,
    "gn:feature_class":"P",
    "gn:feature_code":"PPL",
    "gn:name":"Gouri",
    "gn:population":0,
    "gn:timezone":"Africa/Conakry",
    "iso:country":"GN",
    "wof:name":"Gouri",
    "wof:placetype":"locality"
},
  "geometry": {"coordinates":[-8.66667,11.48333],"type":"Point"}
}