{
  "type": "Feature",
  "properties": {
    "gn:admin1_code":"D",
    "gn:admin2_code":"16",
    "gn:asciiname":"Sieroumba",
    "gn:country_code":"GN",
    "gn:dem":137,
    "gn:feature_class":"P",
    "gn:feature_code":"PPL",
    "gn:name":"Si\u00e9roumba",
    "gn:population":0,
    "gn:timezone":"Africa/Conakry",
    "iso:country":"GN",
    "wof:name":"Sieroumba",
    "wof:placetype":"locality"
},
  "geometry": {"coordinates":[-12.18333,9.95],"type":"Point"}
}