{
  "type": "Feature",
  "properties": {
    "gn:admin1_code":"D",
    "gn:admin2_code":"10",
    "gn:asciiname":"Tadi",
    "gn:country_code":"GN",
    "gn:dem":35,
    "gn:feature_class":"P",
    "gn:feature_code":"PPL",
    "gn:name":"T\u00e2di",
    "gn:population":0,
    "gn:timezone":"Africa/Conakry",
    "iso:country":"GN",
    "wof:name":"Tadi",
    "wof:placetype":"locality"
},
  "geometry": {"coordinates":[-13.04917,9.41917],"type":"Point"}
}