{
  "type": "Feature",
  "properties": {
    "gn:admin1_code":"F",
    "gn:admin2_code":"07",
    "gn:asciiname":"Fouga",
    "gn:country_code":"GN",
    "gn:dem":411,
    "gn:feature_class":"P",
    "gn:feature_code":"PPL",
    "gn:name":"Fouga",
    "gn:population":0,
    "gn:timezone":"Africa/Conakry",
    "iso:country":"GN",
    "name:fra_x_preferred":[
        "Fouga"
    ],
    "name:heb_x_preferred":[
        "\u05d0\u05d9\u05d9\u05e8 \u05e4\u05d5\u05d2\u05d4"
    ],
    "name:jpn_x_preferred":[
        "\u30d5\u30fc\u30ac"
    ],
    "wof:name":"Fouga",
    "wof:placetype":"locality"
},
  "geometry": {"coordinates":[-10.86667,11.25],"type":"Point"}
}