{
  "type": "Feature",
  "properties": {
    "gn:admin1_code":"B",
    "gn:admin2_code":"18",
    "gn:asciiname":"Parakanta",
    "gn:country_code":"GN",
    "gn:dem":142,
    "gn:feature_class":"P",
    "gn:feature_code":"PPL",
    "gn:name":"Parakanta",
    "gn:population":0,
    "gn:timezone":"Africa/Conakry",
    "iso:country":"GN",
    "wof:name":"Parakanta",
    "wof:placetype":"locality"
},
  "geometry": {"coordinates":[-12.916,12.407],"type":"Point"}
}