{
  "type": "Feature",
  "properties": {
    "gn:admin1_code":"L",
    "gn:admin2_code":"22",
    "gn:asciiname":"Dougoulin",
    "gn:country_code":"GN",
    "gn:dem":593,
    "gn:feature_class":"P",
    "gn:feature_code":"PPL",
    "gn:name":"Dougoulin",
    "gn:population":0,
    "gn:timezone":"Africa/Conakry",
    "iso:country":"GN",
    "name:und_x_variant":[
        "Dougouli",
        "Dougoulin"
    ],
    "wof:name":"Dougoulin",
    "wof:placetype":"locality"
},
  "geometry": {"coordinates":[-11.96667,11.73333],"type":"Point"}
}