{
  "type": "Feature",
  "properties": {
    "gn:admin1_code":"K",
    "gn:admin2_code":"39",
    "gn:asciiname":"Bouida",
    "gn:country_code":"GN",
    "gn:dem":318,
    "gn:feature_class":"P",
    "gn:feature_code":"PPL",
    "gn:name":"Bou\u00efda",
    "gn:population":0,
    "gn:timezone":"Africa/Conakry",
    "iso:country":"GN",
    "wof:name":"Bouida",
    "wof:placetype":"locality"
},
  "geometry": {"coordinates":[-9.05,12.13333],"type":"Point"}
}