{
  "type": "Feature",
  "properties": {
    "gn:admin1_code":"D",
    "gn:admin2_code":"27",
    "gn:asciiname":"Kama",
    "gn:country_code":"GN",
    "gn:dem":426,
    "gn:feature_class":"P",
    "gn:feature_code":"PPL",
    "gn:name":"Kama",
    "gn:population":0,
    "gn:timezone":"Africa/Conakry",
    "iso:country":"GN",
    "wof:name":"Kama",
    "wof:placetype":"locality"
},
  "geometry": {"coordinates":[-13.63333,11.16667],"type":"Point"}
}