{
  "type": "Feature",
  "properties": {
    "gn:admin1_code":"D",
    "gn:admin2_code":"16",
    "gn:asciiname":"Yalaga",
    "gn:cc2":"GN",
    "gn:country_code":"GN",
    "gn:dem":128,
    "gn:feature_class":"P",
    "gn:feature_code":"PPL",
    "gn:name":"Yalaga",
    "gn:population":0,
    "gn:timezone":"Africa/Conakry",
    "iso:country":"GN",
    "name:und_x_variant":[
        "Yataga",
        "Yat\u00e8a",
        "Yataya",
        "Yalaga"
    ],
    "wof:name":"Yalaga",
    "wof:placetype":"locality"
},
  "geometry": {"coordinates":[-13.26667,10.05],"type":"Point"}
}