{
  "type": "Feature",
  "properties": {
    "gn:admin1_code":"F",
    "gn:admin2_code":"17",
    "gn:asciiname":"Yaonadou",
    "gn:country_code":"GN",
    "gn:dem":549,
    "gn:feature_class":"P",
    "gn:feature_code":"PPL",
    "gn:name":"Yaonadou",
    "gn:population":0,
    "gn:timezone":"Africa/Conakry",
    "iso:country":"GN",
    "wof:name":"Yaonadou",
    "wof:placetype":"locality"
},
  "geometry": {"coordinates":[-10.18333,9.08333],"type":"Point"}
}