{
  "type": "Feature",
  "properties": {
    "gn:admin1_code":"N",
    "gn:admin2_code":"36",
    "gn:asciiname":"Blayegouma",
    "gn:country_code":"GN",
    "gn:dem":464,
    "gn:feature_class":"P",
    "gn:feature_code":"PPL",
    "gn:name":"Blay\u00e9gouma",
    "gn:population":0,
    "gn:timezone":"Africa/Conakry",
    "iso:country":"GN",
    "name:und_x_variant":[
        "Bl\u00e8egouma",
        "Blay\u00e9gouma"
    ],
    "wof:name":"Blayegouma",
    "wof:placetype":"locality"
},
  "geometry": {"coordinates":[-8.36278,7.74889],"type":"Point"}
}