{
  "type": "Feature",
  "properties": {
    "gn:admin1_code":"D",
    "gn:admin2_code":"31",
    "gn:asciiname":"Wawa",
    "gn:country_code":"GN",
    "gn:dem":10,
    "gn:feature_class":"P",
    "gn:feature_code":"PPL",
    "gn:name":"Wawa",
    "gn:population":0,
    "gn:timezone":"Africa/Conakry",
    "iso:country":"GN",
    "name:ceb_x_preferred":[
        "Wawa"
    ],
    "name:deu_x_preferred":[
        "Wawa"
    ],
    "name:fin_x_preferred":[
        "Wawa"
    ],
    "name:fra_x_preferred":[
        "Wawa"
    ],
    "name:hye_x_preferred":[
        "\u054e\u0561\u057e\u0561"
    ],
    "name:ita_x_preferred":[
        "Wawa"
    ],
    "name:pol_x_preferred":[
        "Wawa"
    ],
    "name:rus_x_preferred":[
        "\u0412\u0430\u0432\u0430"
    ],
    "name:swe_x_preferred":[
        "Wawa"
    ],
    "name:ukr_x_preferred":[
        "\u0412\u0430\u0432\u0430"
    ],
    "wof:name":"Wawa",
    "wof:placetype":"locality"
},
  "geometry": {"coordinates":[-13.69778,9.97333],"type":"Point"}
}