{
  "type": "Feature",
  "properties": {
    "gn:admin1_code":"D",
    "gn:admin2_code":"31",
    "gn:asciiname":"Wawa",
    "gn:country_code":"GN",
    "gn:dem":10,
    "gn:feature_class":"P",
    "gn:feature_code":"PPL",
    "gn:name":"Wawa",
    "gn:population":0,
    "gn:timezone":"Africa/Conakry",
    "iso:country":"GN",
    "name:ben_x_preferred":[
        "\u0993\u09df\u09be\u0993\u09df\u09be"
    ],
    "name:ceb_x_preferred":[
        "Wawa"
    ],
    "name:deu_x_preferred":[
        "Wawa"
    ],
    "name:fas_x_preferred":[
        "\u0648\u0627\u0648\u0627"
    ],
    "name:fin_x_preferred":[
        "Wawa"
    ],
    "name:fra_x_preferred":[
        "Wawa"
    ],
    "name:heb_x_preferred":[
        "\u05d5\u05d5\u05dc\u05d5\u05d5\u05d4"
    ],
    "name:hin_x_preferred":[
        "\u0935\u093e\u0935\u093e"
    ],
    "name:hun_x_preferred":[
        "Wawa"
    ],
    "name:hye_x_preferred":[
        "\u054e\u0561\u057e\u0561"
    ],
    "name:ita_x_preferred":[
        "Wawa"
    ],
    "name:kor_x_preferred":[
        "\uc640\uc640"
    ],
    "name:pol_x_preferred":[
        "Wawa"
    ],
    "name:rus_x_preferred":[
        "\u0412\u0430\u0432\u0430"
    ],
    "name:swe_x_preferred":[
        "Wawa"
    ],
    "name:tur_x_preferred":[
        "Wawa"
    ],
    "name:ukr_x_preferred":[
        "\u0412\u0430\u0432\u0430"
    ],
    "name:urd_x_preferred":[
        "\u0648\u0627\u0648\u0627"
    ],
    "name:vie_x_preferred":[
        "Wawa"
    ],
    "wof:name":"Wawa",
    "wof:placetype":"locality"
},
  "geometry": {"coordinates":[-13.69778,9.97333],"type":"Point"}
}