{
  "type": "Feature",
  "properties": {
    "gn:admin1_code":"D",
    "gn:admin2_code":"16",
    "gn:asciiname":"Koumbaya",
    "gn:country_code":"GN",
    "gn:dem":239,
    "gn:feature_class":"P",
    "gn:feature_code":"PPL",
    "gn:name":"Koumbaya",
    "gn:population":0,
    "gn:timezone":"Africa/Conakry",
    "iso:country":"GN",
    "wof:name":"Koumbaya",
    "wof:placetype":"locality"
},
  "geometry": {"coordinates":[-12.88333,10.16667],"type":"Point"}
}