{
  "type": "Feature",
  "properties": {
    "gn:admin1_code":"N",
    "gn:admin2_code":"13",
    "gn:asciiname":"Boboueloua",
    "gn:country_code":"GN",
    "gn:dem":626,
    "gn:feature_class":"P",
    "gn:feature_code":"PPL",
    "gn:name":"Bobou\u00e9loua",
    "gn:population":0,
    "gn:timezone":"Africa/Conakry",
    "iso:country":"GN",
    "wof:name":"Boboueloua",
    "wof:placetype":"locality"
},
  "geometry": {"coordinates":[-9.93056,8.5375],"type":"Point"}
}