{
  "type": "Feature",
  "properties": {
    "gn:admin1_code":"04",
    "gn:asciiname":"Lembagui",
    "gn:country_code":"GN",
    "gn:dem":16,
    "gn:feature_class":"P",
    "gn:feature_code":"PPL",
    "gn:name":"Lembagui",
    "gn:population":0,
    "gn:timezone":"Africa/Conakry",
    "iso:country":"GN",
    "wof:name":"Lembagui",
    "wof:placetype":"locality"
},
  "geometry": {"coordinates":[-13.62111,9.63639],"type":"Point"}
}