{
  "type": "Feature",
  "properties": {
    "gn:admin1_code":"N",
    "gn:admin2_code":"38",
    "gn:asciiname":"Orata",
    "gn:country_code":"GN",
    "gn:dem":639,
    "gn:feature_class":"P",
    "gn:feature_code":"PPL",
    "gn:name":"Orata",
    "gn:population":0,
    "gn:timezone":"Africa/Conakry",
    "iso:country":"GN",
    "name:und_x_variant":[
        "Ouraso",
        "Orata"
    ],
    "wof:name":"Orata",
    "wof:placetype":"locality"
},
  "geometry": {"coordinates":[-8.66667,8.31667],"type":"Point"}
}