{
  "type": "Feature",
  "properties": {
    "gn:admin1_code":"B",
    "gn:admin2_code":"03",
    "gn:asciiname":"Kanfarande",
    "gn:cc2":"GN",
    "gn:country_code":"GN",
    "gn:dem":1,
    "gn:feature_class":"P",
    "gn:feature_code":"PPL",
    "gn:name":"Kanfarand\u00e9",
    "gn:population":0,
    "gn:timezone":"Africa/Conakry",
    "iso:country":"GN",
    "name:fra_x_preferred":[
        "Kanfarand\u00e9"
    ],
    "name:ita_x_preferred":[
        "Kanfarand\u00e9"
    ],
    "name:msa_x_preferred":[
        "Kanfarand\u00e9"
    ],
    "name:por_x_preferred":[
        "Kanfarand\u00e9"
    ],
    "name:spa_x_preferred":[
        "Kanfarand\u00e9"
    ],
    "name:und_x_variant":[
        "Victoria",
        "Saint Eugenie",
        "Kanfarand\u00e9"
    ],
    "wof:name":"Kanfarande",
    "wof:placetype":"locality"
},
  "geometry": {"coordinates":[-14.55,10.83333],"type":"Point"}
}