{
  "type": "Feature",
  "properties": {
    "gn:admin1_code":"F",
    "gn:admin2_code":"05",
    "gn:asciiname":"Bissikrima",
    "gn:cc2":"GN",
    "gn:country_code":"GN",
    "gn:dem":409,
    "gn:feature_class":"P",
    "gn:feature_code":"PPL",
    "gn:name":"Bissikrima",
    "gn:population":0,
    "gn:timezone":"Africa/Conakry",
    "iso:country":"GN",
    "name:und_x_variant":[
        "Bissikrinia",
        "Bissikrima"
    ],
    "wof:name":"Bissikrima",
    "wof:placetype":"locality"
},
  "geometry": {"coordinates":[-10.93333,10.85],"type":"Point"}
}