{
  "type": "Feature",
  "properties": {
    "gn:admin1_code":"F",
    "gn:admin2_code":"09",
    "gn:asciiname":"Dar es Saleme",
    "gn:country_code":"GN",
    "gn:dem":433,
    "gn:feature_class":"P",
    "gn:feature_code":"PPL",
    "gn:name":"Dar es Sal\u00e8me",
    "gn:population":0,
    "gn:timezone":"Africa/Conakry",
    "iso:country":"GN",
    "wof:name":"Dar es Saleme",
    "wof:placetype":"locality"
},
  "geometry": {"coordinates":[-10.88333,10.66667],"type":"Point"}
}