{
  "type": "Feature",
  "properties": {
    "gn:admin1_code":"K",
    "gn:admin2_code":"39",
    "gn:asciiname":"Mankono",
    "gn:country_code":"GN",
    "gn:dem":520,
    "gn:feature_class":"P",
    "gn:feature_code":"PPL",
    "gn:name":"Mankono",
    "gn:population":0,
    "gn:timezone":"Africa/Conakry",
    "iso:country":"GN",
    "name:ita_x_preferred":[
        "Mankono"
    ],
    "name:jpn_x_preferred":[
        "\u30de\u30f3\u30b3\u30ce"
    ],
    "name:urd_x_preferred":[
        "\u0645\u0627\u0646\u06a9\u0648\u0646\u0648"
    ],
    "wof:name":"Mankono",
    "wof:placetype":"locality"
},
  "geometry": {"coordinates":[-9.51667,12.11667],"type":"Point"}
}