{
  "type": "Feature",
  "properties": {
    "gn:admin1_code":"B",
    "gn:admin2_code":"18",
    "gn:asciiname":"Termesse",
    "gn:country_code":"GN",
    "gn:dem":190,
    "gn:feature_class":"P",
    "gn:feature_code":"PPL",
    "gn:name":"Termess\u00e9",
    "gn:population":0,
    "gn:timezone":"Africa/Conakry",
    "iso:country":"GN",
    "name:ceb_x_preferred":[
        "Termess\u00e9"
    ],
    "name:ita_x_preferred":[
        "Termesse"
    ],
    "name:msa_x_preferred":[
        "Termesse"
    ],
    "name:spa_x_preferred":[
        "Termesse"
    ],
    "name:swe_x_preferred":[
        "Termess\u00e9"
    ],
    "name:und_x_variant":[
        "Termess\u00e9"
    ],
    "wof:name":"Termesse",
    "wof:placetype":"locality"
},
  "geometry": {"coordinates":[-12.7843,12.3152],"type":"Point"}
}