{
  "type": "Feature",
  "properties": {
    "gn:admin1_code":"K",
    "gn:admin2_code":"15",
    "gn:asciiname":"Nialemoridougou",
    "gn:country_code":"GN",
    "gn:dem":525,
    "gn:feature_class":"P",
    "gn:feature_code":"PPL",
    "gn:name":"Nial\u00e9moridougou",
    "gn:population":0,
    "gn:timezone":"Africa/Conakry",
    "iso:country":"GN",
    "wof:name":"Nialemoridougou",
    "wof:placetype":"locality"
},
  "geometry": {"coordinates":[-8.98333,9.56667],"type":"Point"}
}