{
  "type": "Feature",
  "properties": {
    "gn:admin1_code":"N",
    "gn:admin2_code":"29",
    "gn:asciiname":"Nzerekoele",
    "gn:cc2":"GN",
    "gn:country_code":"GN",
    "gn:dem":453,
    "gn:feature_class":"P",
    "gn:feature_code":"PPL",
    "gn:name":"Nz\u00e9r\u00e9ko\u00e9l\u00e9",
    "gn:population":0,
    "gn:timezone":"Africa/Conakry",
    "iso:country":"GN",
    "name:und_x_variant":[
        "N \u2019 Z\u00e9r\u00e9ko\u00e9l\u00e9",
        "Nz\u00e9r\u00e9ko\u00e9l\u00e9"
    ],
    "wof:name":"Nzerekoele",
    "wof:placetype":"locality"
},
  "geometry": {"coordinates":[-9.15389,7.83694],"type":"Point"}
}