{
  "type": "Feature",
  "properties": {
    "gn:admin1_code":"K",
    "gn:admin2_code":"32",
    "gn:asciiname":"Diamona",
    "gn:country_code":"GN",
    "gn:dem":472,
    "gn:feature_class":"P",
    "gn:feature_code":"PPL",
    "gn:name":"Diamona",
    "gn:population":0,
    "gn:timezone":"Africa/Conakry",
    "iso:country":"GN",
    "wof:name":"Diamona",
    "wof:placetype":"locality"
},
  "geometry": {"coordinates":[-9.03333,10.13333],"type":"Point"}
}