{
  "type": "Feature",
  "properties": {
    "gn:admin1_code":"N",
    "gn:admin2_code":"01",
    "gn:asciiname":"Silasabadougou",
    "gn:country_code":"GN",
    "gn:dem":592,
    "gn:feature_class":"P",
    "gn:feature_code":"PPL",
    "gn:name":"Silasabadougou",
    "gn:population":0,
    "gn:timezone":"Africa/Conakry",
    "iso:country":"GN",
    "wof:name":"Silasabadougou",
    "wof:placetype":"locality"
},
  "geometry": {"coordinates":[-8.21667,8.66667],"type":"Point"}
}