{
  "type": "Feature",
  "properties": {
    "gn:admin1_code":"B",
    "gn:admin2_code":"18",
    "gn:asciiname":"Koubia",
    "gn:country_code":"GN",
    "gn:dem":279,
    "gn:feature_class":"P",
    "gn:feature_code":"PPL",
    "gn:name":"Koubia",
    "gn:population":0,
    "gn:timezone":"Africa/Conakry",
    "iso:country":"GN",
    "name:bul_x_preferred":[
        "\u041a\u0443\u0431\u0438\u044f"
    ],
    "name:ceb_x_preferred":[
        "Koubia"
    ],
    "name:fin_x_preferred":[
        "Koubia"
    ],
    "name:fra_x_preferred":[
        "Koubia"
    ],
    "name:ita_x_preferred":[
        "Koubia"
    ],
    "name:msa_x_preferred":[
        "Koubia"
    ],
    "name:pol_x_preferred":[
        "Koubia"
    ],
    "name:spa_x_preferred":[
        "Koubia"
    ],
    "name:swe_x_preferred":[
        "Koubia"
    ],
    "wof:name":"Koubia",
    "wof:placetype":"locality"
},
  "geometry": {"coordinates":[-12.8144,12.2349],"type":"Point"}
}