{
  "type": "Feature",
  "properties": {
    "gn:admin1_code":"L",
    "gn:admin2_code":"22",
    "gn:asciiname":"Bounaougobi",
    "gn:country_code":"GN",
    "gn:dem":1194,
    "gn:feature_class":"P",
    "gn:feature_code":"PPL",
    "gn:name":"Bounaougobi",
    "gn:population":0,
    "gn:timezone":"Africa/Conakry",
    "iso:country":"GN",
    "wof:name":"Bounaougobi",
    "wof:placetype":"locality"
},
  "geometry": {"coordinates":[-12.2486,12.0474],"type":"Point"}
}