{
  "type": "Feature",
  "properties": {
    "gn:admin1_code":"F",
    "gn:admin2_code":"09",
    "gn:asciiname":"Serekoro",
    "gn:country_code":"GN",
    "gn:dem":485,
    "gn:feature_class":"P",
    "gn:feature_code":"PPL",
    "gn:name":"S\u00e9r\u00e9koro",
    "gn:population":0,
    "gn:timezone":"Africa/Conakry",
    "iso:country":"GN",
    "wof:name":"Serekoro",
    "wof:placetype":"locality"
},
  "geometry": {"coordinates":[-10.43333,10.13333],"type":"Point"}
}