{
  "type": "Feature",
  "properties": {
    "gn:admin1_code":"N",
    "gn:admin2_code":"01",
    "gn:asciiname":"Kamorodougou",
    "gn:country_code":"GN",
    "gn:dem":612,
    "gn:feature_class":"P",
    "gn:feature_code":"PPL",
    "gn:name":"Kamorodougou",
    "gn:population":0,
    "gn:timezone":"Africa/Conakry",
    "iso:country":"GN",
    "wof:name":"Kamorodougou",
    "wof:placetype":"locality"
},
  "geometry": {"coordinates":[-8.13333,8.93333],"type":"Point"}
}