{
  "type": "Feature",
  "properties": {
    "gn:admin1_code":"B",
    "gn:admin2_code":"02",
    "gn:asciiname":"Yamaya",
    "gn:cc2":"GN",
    "gn:country_code":"GN",
    "gn:dem":1,
    "gn:feature_class":"P",
    "gn:feature_code":"PPL",
    "gn:name":"Yamaya",
    "gn:population":0,
    "gn:timezone":"Africa/Conakry",
    "iso:country":"GN",
    "name:und_x_variant":[
        "Yamia",
        "Yamaia",
        "Yamaya"
    ],
    "wof:name":"Yamaya",
    "wof:placetype":"locality"
},
  "geometry": {"coordinates":[-14.01667,10.18333],"type":"Point"}
}