{
  "type": "Feature",
  "properties": {
    "gn:admin1_code":"F",
    "gn:admin2_code":"07",
    "gn:asciiname":"Baelea",
    "gn:country_code":"GN",
    "gn:dem":396,
    "gn:feature_class":"P",
    "gn:feature_code":"PPL",
    "gn:name":"Ba\u00e9l\u00e9a",
    "gn:population":0,
    "gn:timezone":"Africa/Conakry",
    "iso:country":"GN",
    "wof:name":"Baelea",
    "wof:placetype":"locality"
},
  "geometry": {"coordinates":[-10.78333,11.46667],"type":"Point"}
}