{
  "type": "Feature",
  "properties": {
    "gn:admin1_code":"N",
    "gn:admin2_code":"29",
    "gn:asciiname":"Zogotta",
    "gn:country_code":"GN",
    "gn:dem":485,
    "gn:feature_class":"P",
    "gn:feature_code":"PPL",
    "gn:name":"Zogotta",
    "gn:population":0,
    "gn:timezone":"Africa/Conakry",
    "iso:country":"GN",
    "wof:name":"Zogotta",
    "wof:placetype":"locality"
},
  "geometry": {"coordinates":[-9.13167,7.93],"type":"Point"}
}