{
  "type": "Feature",
  "properties": {
    "gn:admin1_code":"N",
    "gn:admin2_code":"13",
    "gn:asciiname":"Bilimba",
    "gn:country_code":"GN",
    "gn:dem":555,
    "gn:feature_class":"P",
    "gn:feature_code":"PPL",
    "gn:name":"Bilimba",
    "gn:population":0,
    "gn:timezone":"Africa/Conakry",
    "iso:country":"GN",
    "name:eng_x_preferred":[
        "Bilimba"
    ],
    "wof:name":"Bilimba",
    "wof:placetype":"locality"
},
  "geometry": {"coordinates":[-10.56667,8.93333],"type":"Point"}
}