{
  "type": "Feature",
  "properties": {
    "gn:admin1_code":"F",
    "gn:admin2_code":"09",
    "gn:asciiname":"Seremessadou",
    "gn:country_code":"GN",
    "gn:dem":717,
    "gn:feature_class":"P",
    "gn:feature_code":"PPL",
    "gn:name":"Ser\u00e9m\u00e9ssadou",
    "gn:population":0,
    "gn:timezone":"Africa/Conakry",
    "iso:country":"GN",
    "wof:name":"Seremessadou",
    "wof:placetype":"locality"
},
  "geometry": {"coordinates":[-10.55,9.25],"type":"Point"}
}