{
  "type": "Feature",
  "properties": {
    "gn:admin1_code":"F",
    "gn:admin2_code":"07",
    "gn:asciiname":"Kemaya",
    "gn:country_code":"GN",
    "gn:dem":543,
    "gn:feature_class":"P",
    "gn:feature_code":"PPL",
    "gn:name":"Kemaya",
    "gn:population":0,
    "gn:timezone":"Africa/Conakry",
    "iso:country":"GN",
    "wof:name":"Kemaya",
    "wof:placetype":"locality"
},
  "geometry": {"coordinates":[-10.31667,12.08333],"type":"Point"}
}