{
  "type": "Feature",
  "properties": {
    "gn:admin1_code":"F",
    "gn:admin2_code":"07",
    "gn:asciiname":"Dantare",
    "gn:country_code":"GN",
    "gn:dem":538,
    "gn:feature_class":"P",
    "gn:feature_code":"PPL",
    "gn:name":"Dantar\u00e9",
    "gn:population":0,
    "gn:timezone":"Africa/Conakry",
    "iso:country":"GN",
    "wof:name":"Dantare",
    "wof:placetype":"locality"
},
  "geometry": {"coordinates":[-10.91667,11.66667],"type":"Point"}
}