{
  "type": "Feature",
  "properties": {
    "gn:admin1_code":"L",
    "gn:admin2_code":"22",
    "gn:asciiname":"Foton",
    "gn:country_code":"GN",
    "gn:dem":260,
    "gn:feature_class":"P",
    "gn:feature_code":"PPL",
    "gn:name":"Foton",
    "gn:population":0,
    "gn:timezone":"Africa/Conakry",
    "iso:country":"GN",
    "name:fra_x_preferred":[
        "Foton"
    ],
    "name:pol_x_preferred":[
        "Foton"
    ],
    "wof:name":"Foton",
    "wof:placetype":"locality"
},
  "geometry": {"coordinates":[-11.79118,12.24848],"type":"Point"}
}