{
  "type": "Feature",
  "properties": {
    "gn:admin1_code":"N",
    "gn:admin2_code":"01",
    "gn:asciiname":"Ouanino",
    "gn:country_code":"GN",
    "gn:dem":656,
    "gn:feature_class":"P",
    "gn:feature_code":"PPL",
    "gn:name":"Ouanino",
    "gn:population":0,
    "gn:timezone":"Africa/Conakry",
    "iso:country":"GN",
    "wof:name":"Ouanino",
    "wof:placetype":"locality"
},
  "geometry": {"coordinates":[-8.55,8.78333],"type":"Point"}
}