{
  "type": "Feature",
  "properties": {
    "gn:admin1_code":"F",
    "gn:admin2_code":"17",
    "gn:asciiname":"Douadou",
    "gn:country_code":"GN",
    "gn:dem":592,
    "gn:feature_class":"P",
    "gn:feature_code":"PPL",
    "gn:name":"Douadou",
    "gn:population":0,
    "gn:timezone":"Africa/Conakry",
    "iso:country":"GN",
    "wof:name":"Douadou",
    "wof:placetype":"locality"
},
  "geometry": {"coordinates":[-10.19056,8.99139],"type":"Point"}
}