{
  "type": "Feature",
  "properties": {
    "gn:admin1_code":"L",
    "gn:admin2_code":"22",
    "gn:asciiname":"Ore Vindou",
    "gn:country_code":"GN",
    "gn:dem":399,
    "gn:feature_class":"P",
    "gn:feature_code":"PPL",
    "gn:name":"Ore Vindou",
    "gn:population":0,
    "gn:timezone":"Africa/Conakry",
    "iso:country":"GN",
    "name:und_x_variant":[
        "Moporo",
        "Ore Vindou"
    ],
    "wof:name":"Ore Vindou",
    "wof:placetype":"locality"
},
  "geometry": {"coordinates":[-12.5023,12.2548],"type":"Point"}
}