{
  "type": "Feature",
  "properties": {
    "gn:admin1_code":"F",
    "gn:admin2_code":"07",
    "gn:asciiname":"Linguere",
    "gn:country_code":"GN",
    "gn:dem":609,
    "gn:feature_class":"P",
    "gn:feature_code":"PPL",
    "gn:name":"Lingu\u00e9r\u00e9",
    "gn:population":0,
    "gn:timezone":"Africa/Conakry",
    "iso:country":"GN",
    "wof:name":"Linguere",
    "wof:placetype":"locality"
},
  "geometry": {"coordinates":[-10.61667,11.55],"type":"Point"}
}