{
  "type": "Feature",
  "properties": {
    "gn:admin1_code":"B",
    "gn:admin2_code":"02",
    "gn:asciiname":"Mayounde",
    "gn:cc2":"GN",
    "gn:country_code":"GN",
    "gn:dem":92,
    "gn:feature_class":"P",
    "gn:feature_code":"PPL",
    "gn:name":"Mayound\u00e9",
    "gn:population":0,
    "gn:timezone":"Africa/Conakry",
    "iso:country":"GN",
    "name:und_x_variant":[
        "Mauende",
        "Mahound\u00e9",
        "Mayande",
        "Maouend\u00e9",
        "Mayound\u00e9"
    ],
    "wof:name":"Mayounde",
    "wof:placetype":"locality"
},
  "geometry": {"coordinates":[-13.98333,10.11667],"type":"Point"}
}