{
  "type": "Feature",
  "properties": {
    "gn:admin1_code":"K",
    "gn:admin2_code":"21",
    "gn:asciiname":"Diomandou",
    "gn:country_code":"GN",
    "gn:dem":713,
    "gn:feature_class":"P",
    "gn:feature_code":"PPL",
    "gn:name":"Diomandou",
    "gn:population":0,
    "gn:timezone":"Africa/Conakry",
    "iso:country":"GN",
    "wof:name":"Diomandou",
    "wof:placetype":"locality"
},
  "geometry": {"coordinates":[-9.12222,8.83083],"type":"Point"}
}