{
  "type": "Feature",
  "properties": {
    "gn:admin1_code":"K",
    "gn:admin2_code":"39",
    "gn:asciiname":"Tiedala",
    "gn:country_code":"GN",
    "gn:dem":336,
    "gn:feature_class":"P",
    "gn:feature_code":"PPL",
    "gn:name":"Ti\u00e9dala",
    "gn:population":0,
    "gn:timezone":"Africa/Conakry",
    "iso:country":"GN",
    "name:und_x_variant":[
        "Ti\u00e9dal\u00e9",
        "Ti\u00e9dala"
    ],
    "wof:name":"Tiedala",
    "wof:placetype":"locality"
},
  "geometry": {"coordinates":[-9.25,11.88333],"type":"Point"}
}