{
  "type": "Feature",
  "properties": {
    "gn:admin1_code":"N",
    "gn:admin2_code":"13",
    "gn:asciiname":"Bassialo",
    "gn:country_code":"GN",
    "gn:dem":496,
    "gn:feature_class":"P",
    "gn:feature_code":"PPL",
    "gn:name":"Bassialo",
    "gn:population":0,
    "gn:timezone":"Africa/Conakry",
    "iso:country":"GN",
    "wof:name":"Bassialo",
    "wof:placetype":"locality"
},
  "geometry": {"coordinates":[-10.02722,8.54444],"type":"Point"}
}