{
  "type": "Feature",
  "properties": {
    "gn:admin1_code":"F",
    "gn:admin2_code":"05",
    "gn:asciiname":"Fissonia",
    "gn:cc2":"GN",
    "gn:country_code":"GN",
    "gn:dem":773,
    "gn:feature_class":"P",
    "gn:feature_code":"PPL",
    "gn:name":"Fissonia",
    "gn:population":0,
    "gn:timezone":"Africa/Conakry",
    "iso:country":"GN",
    "name:und_x_variant":[
        "Fissiona",
        "Fissonia"
    ],
    "wof:name":"Fissonia",
    "wof:placetype":"locality"
},
  "geometry": {"coordinates":[-11.21667,10.38333],"type":"Point"}
}