{
  "type": "Feature",
  "properties": {
    "gn:admin1_code":"F",
    "gn:admin2_code":"05",
    "gn:asciiname":"Fadama",
    "gn:country_code":"GN",
    "gn:dem":774,
    "gn:feature_class":"P",
    "gn:feature_code":"PPL",
    "gn:name":"Fadama",
    "gn:population":0,
    "gn:timezone":"Africa/Conakry",
    "iso:country":"GN",
    "wof:name":"Fadama",
    "wof:placetype":"locality"
},
  "geometry": {"coordinates":[-11.35,10.88333],"type":"Point"}
}