{
  "type": "Feature",
  "properties": {
    "gn:admin1_code":"L",
    "gn:admin2_code":"33",
    "gn:asciiname":"Kolibade",
    "gn:country_code":"GN",
    "gn:dem":330,
    "gn:feature_class":"P",
    "gn:feature_code":"PPL",
    "gn:name":"Kolibad\u00e9",
    "gn:population":0,
    "gn:timezone":"Africa/Conakry",
    "iso:country":"GN",
    "wof:name":"Kolibade",
    "wof:placetype":"locality"
},
  "geometry": {"coordinates":[-11.49622,12.1869],"type":"Point"}
}