{
  "type": "Feature",
  "properties": {
    "gn:admin1_code":"D",
    "gn:admin2_code":"30",
    "gn:asciiname":"Toumaniya",
    "gn:country_code":"GN",
    "gn:dem":17,
    "gn:feature_class":"P",
    "gn:feature_code":"PPL",
    "gn:name":"Toumaniya",
    "gn:population":0,
    "gn:timezone":"Africa/Conakry",
    "iso:country":"GN",
    "name:und_x_variant":[
        "Toumania",
        "Toumaniya"
    ],
    "wof:name":"Toumaniya",
    "wof:placetype":"locality"
},
  "geometry": {"coordinates":[-13.38333,9.63333],"type":"Point"}
}