{
  "type": "Feature",
  "properties": {
    "gn:admin1_code":"K",
    "gn:admin2_code":"39",
    "gn:asciiname":"Manakoro",
    "gn:country_code":"GN",
    "gn:dem":341,
    "gn:feature_class":"P",
    "gn:feature_code":"PPL",
    "gn:name":"Manakoro",
    "gn:population":0,
    "gn:timezone":"Africa/Conakry",
    "iso:country":"GN",
    "wof:name":"Manakoro",
    "wof:placetype":"locality"
},
  "geometry": {"coordinates":[-9.11667,11.41667],"type":"Point"}
}