{
  "type": "Feature",
  "properties": {
    "gn:admin1_code":"N",
    "gn:admin2_code":"21",
    "gn:asciiname":"Tenambadou",
    "gn:cc2":"GN",
    "gn:country_code":"GN",
    "gn:dem":747,
    "gn:feature_class":"P",
    "gn:feature_code":"PPL",
    "gn:name":"T\u00e9nambadou",
    "gn:population":0,
    "gn:timezone":"Africa/Conakry",
    "iso:country":"GN",
    "name:und_x_variant":[
        "T\u00e9nemba",
        "T\u00e9nembadou",
        "T\u00e9nambadou"
    ],
    "wof:name":"Tenambadou",
    "wof:placetype":"locality"
},
  "geometry": {"coordinates":[-9.13722,8.77222],"type":"Point"}
}