{
  "type": "Feature",
  "properties": {
    "gn:admin1_code":"N",
    "gn:admin2_code":"21",
    "gn:asciiname":"Kouzezou",
    "gn:country_code":"GN",
    "gn:dem":651,
    "gn:feature_class":"P",
    "gn:feature_code":"PPL",
    "gn:name":"Kouzezou",
    "gn:population":0,
    "gn:timezone":"Africa/Conakry",
    "iso:country":"GN",
    "wof:name":"Kouzezou",
    "wof:placetype":"locality"
},
  "geometry": {"coordinates":[-9.74472,8.79306],"type":"Point"}
}