{
  "type": "Feature",
  "properties": {
    "gn:admin1_code":"F",
    "gn:admin2_code":"09",
    "gn:asciiname":"Bindou",
    "gn:country_code":"GN",
    "gn:dem":547,
    "gn:feature_class":"P",
    "gn:feature_code":"PPL",
    "gn:name":"Bindou",
    "gn:population":0,
    "gn:timezone":"Africa/Conakry",
    "iso:country":"GN",
    "wof:name":"Bindou",
    "wof:placetype":"locality"
},
  "geometry": {"coordinates":[-10.63333,9.21667],"type":"Point"}
}