{
  "type": "Feature",
  "properties": {
    "gn:admin1_code":"F",
    "gn:admin2_code":"07",
    "gn:asciiname":"Nouhouya",
    "gn:country_code":"GN",
    "gn:dem":254,
    "gn:feature_class":"P",
    "gn:feature_code":"PPL",
    "gn:name":"Nouhouya",
    "gn:population":0,
    "gn:timezone":"Africa/Conakry",
    "iso:country":"GN",
    "wof:name":"Nouhouya",
    "wof:placetype":"locality"
},
  "geometry": {"coordinates":[-11.03464,12.0567],"type":"Point"}
}