{
  "type": "Feature",
  "properties": {
    "gn:admin1_code":"K",
    "gn:admin2_code":"39",
    "gn:asciiname":"Dialakoro",
    "gn:country_code":"GN",
    "gn:dem":339,
    "gn:feature_class":"P",
    "gn:feature_code":"PPL",
    "gn:name":"Dialakoro",
    "gn:population":0,
    "gn:timezone":"Africa/Conakry",
    "iso:country":"GN",
    "name:ita_x_preferred":[
        "Dialakoro"
    ],
    "name:msa_x_preferred":[
        "Dialakoro"
    ],
    "name:spa_x_preferred":[
        "Dialakoro"
    ],
    "wof:name":"Dialakoro",
    "wof:placetype":"locality"
},
  "geometry": {"coordinates":[-8.88333,11.45],"type":"Point"}
}