{
  "type": "Feature",
  "properties": {
    "gn:admin1_code":"L",
    "gn:admin2_code":"22",
    "gn:asciiname":"Sinntiou",
    "gn:country_code":"GN",
    "gn:dem":348,
    "gn:feature_class":"P",
    "gn:feature_code":"PPL",
    "gn:name":"Sinntiou",
    "gn:population":0,
    "gn:timezone":"Africa/Conakry",
    "iso:country":"GN",
    "name:und_x_variant":[
        "Sintiou",
        "Sinntiou"
    ],
    "wof:name":"Sinntiou",
    "wof:placetype":"locality"
},
  "geometry": {"coordinates":[-12.2602,12.2081],"type":"Point"}
}