{
  "type": "Feature",
  "properties": {
    "gn:admin1_code":"K",
    "gn:admin2_code":"19",
    "gn:asciiname":"Tamiko",
    "gn:country_code":"GN",
    "gn:dem":396,
    "gn:feature_class":"P",
    "gn:feature_code":"PPL",
    "gn:name":"Tamiko",
    "gn:population":0,
    "gn:timezone":"Africa/Conakry",
    "iso:country":"GN",
    "name:ceb_x_preferred":[
        "Tamiko"
    ],
    "name:swe_x_preferred":[
        "Tamiko"
    ],
    "wof:name":"Tamiko",
    "wof:placetype":"locality"
},
  "geometry": {"coordinates":[-9.38333,10.85],"type":"Point"}
}