{
  "type": "Feature",
  "properties": {
    "gn:admin1_code":"N",
    "gn:admin2_code":"13",
    "gn:asciiname":"Sandia",
    "gn:country_code":"GN",
    "gn:dem":509,
    "gn:feature_class":"P",
    "gn:feature_code":"PPL",
    "gn:name":"Sandia",
    "gn:population":0,
    "gn:timezone":"Africa/Conakry",
    "iso:country":"GN",
    "name:ceb_x_preferred":[
        "Sandia"
    ],
    "name:deu_x_preferred":[
        "Sandia"
    ],
    "name:hrv_x_preferred":[
        "Sandia"
    ],
    "name:nld_x_preferred":[
        "Sandia"
    ],
    "name:pol_x_preferred":[
        "Sandia"
    ],
    "name:por_x_preferred":[
        "Sandia"
    ],
    "name:spa_x_preferred":[
        "Sandia"
    ],
    "name:swe_x_preferred":[
        "Sandia"
    ],
    "wof:name":"Sandia",
    "wof:placetype":"locality"
},
  "geometry": {"coordinates":[-10.17306,8.76],"type":"Point"}
}