{
  "type": "Feature",
  "properties": {
    "gn:admin1_code":"K",
    "gn:admin2_code":"01",
    "gn:asciiname":"Fenedougou",
    "gn:country_code":"GN",
    "gn:dem":610,
    "gn:feature_class":"P",
    "gn:feature_code":"PPL",
    "gn:name":"F\u00e9n\u00e9dougou",
    "gn:population":0,
    "gn:timezone":"Africa/Conakry",
    "iso:country":"GN",
    "name:und_x_variant":[
        "Fandougou",
        "F\u00e9n\u00e9dougou"
    ],
    "wof:name":"Fenedougou",
    "wof:placetype":"locality"
},
  "geometry": {"coordinates":[-8.76667,9.15],"type":"Point"}
}