{
  "type": "Feature",
  "properties": {
    "gn:admin1_code":"L",
    "gn:admin2_code":"02",
    "gn:asciiname":"Kriffi",
    "gn:country_code":"GN",
    "gn:dem":863,
    "gn:feature_class":"P",
    "gn:feature_code":"PPL",
    "gn:name":"Kriffi",
    "gn:population":0,
    "gn:timezone":"Africa/Conakry",
    "iso:country":"GN",
    "name:und_x_variant":[
        "Kirfi",
        "Kriffi"
    ],
    "wof:name":"Kriffi",
    "wof:placetype":"locality"
},
  "geometry": {"coordinates":[-11.51667,11.46667],"type":"Point"}
}