{
  "type": "Feature",
  "properties": {
    "gn:admin1_code":"B",
    "gn:admin2_code":"18",
    "gn:asciiname":"Bowal-Ila",
    "gn:country_code":"GN",
    "gn:dem":159,
    "gn:feature_class":"P",
    "gn:feature_code":"PPL",
    "gn:name":"Bowal-Ila",
    "gn:population":0,
    "gn:timezone":"Africa/Conakry",
    "iso:country":"GN",
    "wof:name":"Bowal-Ila",
    "wof:placetype":"locality"
},
  "geometry": {"coordinates":[-12.8959,12.2295],"type":"Point"}
}