{
  "type": "Feature",
  "properties": {
    "gn:admin1_code":"F",
    "gn:admin2_code":"17",
    "gn:asciiname":"Broadou",
    "gn:cc2":"GN",
    "gn:country_code":"GN",
    "gn:dem":547,
    "gn:feature_class":"P",
    "gn:feature_code":"PPL",
    "gn:name":"Broadou",
    "gn:population":0,
    "gn:timezone":"Africa/Conakry",
    "iso:country":"GN",
    "name:und_x_variant":[
        "Brouadou",
        "Broadou"
    ],
    "wof:name":"Broadou",
    "wof:placetype":"locality"
},
  "geometry": {"coordinates":[-10.06667,9.13333],"type":"Point"}
}