{
  "type": "Feature",
  "properties": {
    "gn:admin1_code":"K",
    "gn:admin2_code":"21",
    "gn:asciiname":"Niamadou",
    "gn:country_code":"GN",
    "gn:dem":641,
    "gn:feature_class":"P",
    "gn:feature_code":"PPL",
    "gn:name":"Niamadou",
    "gn:population":0,
    "gn:timezone":"Africa/Conakry",
    "iso:country":"GN",
    "wof:name":"Niamadou",
    "wof:placetype":"locality"
},
  "geometry": {"coordinates":[-9.00167,8.81389],"type":"Point"}
}