{
  "type": "Feature",
  "properties": {
    "gn:admin1_code":"L",
    "gn:admin2_code":"22",
    "gn:asciiname":"Balaya",
    "gn:country_code":"GN",
    "gn:dem":296,
    "gn:feature_class":"P",
    "gn:feature_code":"PPL",
    "gn:name":"Balaya",
    "gn:population":0,
    "gn:timezone":"Africa/Conakry",
    "iso:country":"GN",
    "name:ita_x_preferred":[
        "Balaya"
    ],
    "name:msa_x_preferred":[
        "Balaya"
    ],
    "name:spa_x_preferred":[
        "Balaya"
    ],
    "wof:name":"Balaya",
    "wof:placetype":"locality"
},
  "geometry": {"coordinates":[-11.68309,12.15101],"type":"Point"}
}