{
  "type": "Feature",
  "properties": {
    "gn:admin1_code":"F",
    "gn:admin2_code":"07",
    "gn:asciiname":"Seria",
    "gn:country_code":"GN",
    "gn:dem":412,
    "gn:feature_class":"P",
    "gn:feature_code":"PPL",
    "gn:name":"S\u00e9ria",
    "gn:population":0,
    "gn:timezone":"Africa/Conakry",
    "iso:country":"GN",
    "wof:name":"Seria",
    "wof:placetype":"locality"
},
  "geometry": {"coordinates":[-10.45,11.58333],"type":"Point"}
}