{
  "type": "Feature",
  "properties": {
    "gn:admin1_code":"F",
    "gn:admin2_code":"07",
    "gn:asciiname":"Seria",
    "gn:country_code":"GN",
    "gn:dem":412,
    "gn:feature_class":"P",
    "gn:feature_code":"PPL",
    "gn:name":"S\u00e9ria",
    "gn:population":0,
    "gn:timezone":"Africa/Conakry",
    "iso:country":"GN",
    "name:ceb_x_preferred":[
        "Seria"
    ],
    "name:fin_x_preferred":[
        "Seria"
    ],
    "name:fra_x_preferred":[
        "Seria"
    ],
    "name:ind_x_preferred":[
        "Seria"
    ],
    "name:ita_x_preferred":[
        "Seria"
    ],
    "name:jpn_x_preferred":[
        "\u30bb\u30ea\u30a2"
    ],
    "name:kor_x_preferred":[
        "\uc138\ub9ac\uc544"
    ],
    "name:lit_x_preferred":[
        "Serija"
    ],
    "name:msa_x_preferred":[
        "Seria"
    ],
    "name:nld_x_preferred":[
        "Seria"
    ],
    "name:pol_x_preferred":[
        "Seria"
    ],
    "name:rus_x_preferred":[
        "\u0421\u0435\u0440\u0438\u0430"
    ],
    "name:spa_x_preferred":[
        "Seria"
    ],
    "name:swe_x_preferred":[
        "Seria"
    ],
    "name:tha_x_preferred":[
        "\u0e40\u0e0b\u0e2d\u0e40\u0e23\u0e35\u0e22"
    ],
    "name:tur_x_preferred":[
        "Seria"
    ],
    "name:ukr_x_preferred":[
        "\u0421\u0435\u0440\u0456\u0430"
    ],
    "wof:name":"Seria",
    "wof:placetype":"locality"
},
  "geometry": {"coordinates":[-10.45,11.58333],"type":"Point"}
}