{
  "type": "Feature",
  "properties": {
    "gn:admin1_code":"D",
    "gn:admin2_code":"27",
    "gn:asciiname":"Sourdissa",
    "gn:country_code":"GN",
    "gn:dem":449,
    "gn:feature_class":"P",
    "gn:feature_code":"PPL",
    "gn:name":"Sourdissa",
    "gn:population":0,
    "gn:timezone":"Africa/Conakry",
    "iso:country":"GN",
    "wof:name":"Sourdissa",
    "wof:placetype":"locality"
},
  "geometry": {"coordinates":[-13.63333,10.83333],"type":"Point"}
}