{
  "type": "Feature",
  "properties": {
    "gn:admin1_code":"04",
    "gn:asciiname":"Kouromandja",
    "gn:cc2":"GN",
    "gn:country_code":"GN",
    "gn:dem":102,
    "gn:feature_class":"P",
    "gn:feature_code":"PPL",
    "gn:name":"Kouromandja",
    "gn:population":0,
    "gn:timezone":"Africa/Conakry",
    "iso:country":"GN",
    "name:und_x_variant":[
        "Coromania",
        "Kouromandya",
        "Kouromandja"
    ],
    "wof:name":"Kouromandja",
    "wof:placetype":"locality"
},
  "geometry": {"coordinates":[-13.74917,9.46083],"type":"Point"}
}