{
  "type": "Feature",
  "properties": {
    "gn:admin1_code":"B",
    "gn:admin2_code":"18",
    "gn:asciiname":"Tierno Kali",
    "gn:country_code":"GN",
    "gn:dem":68,
    "gn:feature_class":"P",
    "gn:feature_code":"PPL",
    "gn:name":"Ti\u00e9rno Kali",
    "gn:population":0,
    "gn:timezone":"Africa/Conakry",
    "iso:country":"GN",
    "wof:name":"Tierno Kali",
    "wof:placetype":"locality"
},
  "geometry": {"coordinates":[-13.35,12.35],"type":"Point"}
}