{
  "type": "Feature",
  "properties": {
    "gn:admin1_code":"N",
    "gn:admin2_code":"21",
    "gn:asciiname":"Missamoridou",
    "gn:country_code":"GN",
    "gn:dem":558,
    "gn:feature_class":"P",
    "gn:feature_code":"PPL",
    "gn:name":"Missamoridou",
    "gn:population":0,
    "gn:timezone":"Africa/Conakry",
    "iso:country":"GN",
    "wof:name":"Missamoridou",
    "wof:placetype":"locality"
},
  "geometry": {"coordinates":[-9.07611,8.67278],"type":"Point"}
}