{
  "type": "Feature",
  "properties": {
    "gn:admin1_code":"N",
    "gn:admin2_code":"21",
    "gn:asciiname":"Senebou",
    "gn:country_code":"GN",
    "gn:dem":638,
    "gn:feature_class":"P",
    "gn:feature_code":"PPL",
    "gn:name":"S\u00e9n\u00e9bou",
    "gn:population":0,
    "gn:timezone":"Africa/Conakry",
    "iso:country":"GN",
    "wof:name":"Senebou",
    "wof:placetype":"locality"
},
  "geometry": {"coordinates":[-9.53417,8.62111],"type":"Point"}
}