{
  "type": "Feature",
  "properties": {
    "gn:admin1_code":"F",
    "gn:admin2_code":"09",
    "gn:asciiname":"Yerewolia",
    "gn:country_code":"GN",
    "gn:dem":543,
    "gn:feature_class":"P",
    "gn:feature_code":"PPL",
    "gn:name":"Y\u00e9r\u00e9wolia",
    "gn:population":0,
    "gn:timezone":"Africa/Conakry",
    "iso:country":"GN",
    "wof:name":"Yerewolia",
    "wof:placetype":"locality"
},
  "geometry": {"coordinates":[-10.51667,9.21667],"type":"Point"}
}