{
  "type": "Feature",
  "properties": {
    "gn:admin1_code":"D",
    "gn:admin2_code":"31",
    "gn:asciiname":"Dogofon",
    "gn:country_code":"GN",
    "gn:dem":244,
    "gn:feature_class":"P",
    "gn:feature_code":"PPL",
    "gn:name":"Dogofon",
    "gn:population":0,
    "gn:timezone":"Africa/Conakry",
    "iso:country":"GN",
    "name:und_x_variant":[
        "Dogofo",
        "Dogofon"
    ],
    "wof:name":"Dogofon",
    "wof:placetype":"locality"
},
  "geometry": {"coordinates":[-13.58333,10.16667],"type":"Point"}
}