{
  "type": "Feature",
  "properties": {
    "gn:admin1_code":"F",
    "gn:admin2_code":"19",
    "gn:asciiname":"Dandakara",
    "gn:country_code":"GN",
    "gn:dem":417,
    "gn:feature_class":"P",
    "gn:feature_code":"PPL",
    "gn:name":"Dandakara",
    "gn:population":0,
    "gn:timezone":"Africa/Conakry",
    "iso:country":"GN",
    "wof:name":"Dandakara",
    "wof:placetype":"locality"
},
  "geometry": {"coordinates":[-10.78333,10.61667],"type":"Point"}
}