{
  "type": "Feature",
  "properties": {
    "gn:admin1_code":"N",
    "gn:admin2_code":"13",
    "gn:asciiname":"Bindou",
    "gn:country_code":"GN",
    "gn:dem":449,
    "gn:feature_class":"P",
    "gn:feature_code":"PPL",
    "gn:name":"Bindou",
    "gn:population":0,
    "gn:timezone":"Africa/Conakry",
    "iso:country":"GN",
    "wof:name":"Bindou",
    "wof:placetype":"locality"
},
  "geometry": {"coordinates":[-10.22667,8.68806],"type":"Point"}
}