{
  "type": "Feature",
  "properties": {
    "gn:admin1_code":"D",
    "gn:admin2_code":"16",
    "gn:asciiname":"Dantoumaya",
    "gn:country_code":"GN",
    "gn:dem":359,
    "gn:feature_class":"P",
    "gn:feature_code":"PPL",
    "gn:name":"Dantoumaya",
    "gn:population":0,
    "gn:timezone":"Africa/Conakry",
    "iso:country":"GN",
    "wof:name":"Dantoumaya",
    "wof:placetype":"locality"
},
  "geometry": {"coordinates":[-13.02361,9.96583],"type":"Point"}
}