{
  "type": "Feature",
  "properties": {
    "gn:admin1_code":"N",
    "gn:admin2_code":"13",
    "gn:asciiname":"Maa",
    "gn:country_code":"GN",
    "gn:dem":283,
    "gn:feature_class":"P",
    "gn:feature_code":"PPL",
    "gn:name":"Maa",
    "gn:population":0,
    "gn:timezone":"Africa/Conakry",
    "iso:country":"GN",
    "name:ben_x_preferred":[
        "\u09ae\u09be"
    ],
    "name:ceb_x_preferred":[
        "Maa"
    ],
    "name:est_x_preferred":[
        "Maa"
    ],
    "name:fin_x_preferred":[
        "Maa"
    ],
    "name:fra_x_preferred":[
        "Maa"
    ],
    "name:ind_x_preferred":[
        "Maa"
    ],
    "name:ori_x_preferred":[
        "\u0b2e\u0b3e"
    ],
    "name:swe_x_preferred":[
        "Maa"
    ],
    "name:tur_x_preferred":[
        "Maa"
    ],
    "wof:name":"Maa",
    "wof:placetype":"locality"
},
  "geometry": {"coordinates":[-10.61667,8.51667],"type":"Point"}
}