{
  "type": "Feature",
  "properties": {
    "gn:admin1_code":"B",
    "gn:admin2_code":"18",
    "gn:asciiname":"Sare Kebe",
    "gn:country_code":"GN",
    "gn:dem":71,
    "gn:feature_class":"P",
    "gn:feature_code":"PPL",
    "gn:name":"Sar\u00e9 K\u00e9b\u00e9",
    "gn:population":0,
    "gn:timezone":"Africa/Conakry",
    "iso:country":"GN",
    "wof:name":"Sare Kebe",
    "wof:placetype":"locality"
},
  "geometry": {"coordinates":[-13.51667,12.33333],"type":"Point"}
}