{
  "type": "Feature",
  "properties": {
    "gn:admin1_code":"B",
    "gn:admin2_code":"03",
    "gn:asciiname":"Tatsouboumbi",
    "gn:country_code":"GN",
    "gn:dem":53,
    "gn:feature_class":"P",
    "gn:feature_code":"PPL",
    "gn:name":"Tatsouboumbi",
    "gn:population":0,
    "gn:timezone":"Africa/Conakry",
    "iso:country":"GN",
    "wof:name":"Tatsouboumbi",
    "wof:placetype":"locality"
},
  "geometry": {"coordinates":[-14.38333,11.11667],"type":"Point"}
}