{
  "type": "Feature",
  "properties": {
    "gn:admin1_code":"D",
    "gn:admin2_code":"16",
    "gn:asciiname":"Sonkia",
    "gn:country_code":"GN",
    "gn:dem":280,
    "gn:feature_class":"P",
    "gn:feature_code":"PPL",
    "gn:name":"Sonkia",
    "gn:population":0,
    "gn:timezone":"Africa/Conakry",
    "iso:country":"GN",
    "wof:name":"Sonkia",
    "wof:placetype":"locality"
},
  "geometry": {"coordinates":[-13.06667,10.25],"type":"Point"}
}