{
  "type": "Feature",
  "properties": {
    "gn:admin1_code":"L",
    "gn:admin2_code":"22",
    "gn:asciiname":"Diagara",
    "gn:country_code":"GN",
    "gn:dem":325,
    "gn:feature_class":"P",
    "gn:feature_code":"PPL",
    "gn:name":"Diagara",
    "gn:population":0,
    "gn:timezone":"Africa/Conakry",
    "iso:country":"GN",
    "wof:name":"Diagara",
    "wof:placetype":"locality"
},
  "geometry": {"coordinates":[-11.52859,12.32394],"type":"Point"}
}