{
  "type": "Feature",
  "properties": {
    "gn:admin1_code":"N",
    "gn:admin2_code":"21",
    "gn:asciiname":"Teguebeya",
    "gn:country_code":"GN",
    "gn:dem":669,
    "gn:feature_class":"P",
    "gn:feature_code":"PPL",
    "gn:name":"Teguebeya",
    "gn:population":0,
    "gn:timezone":"Africa/Conakry",
    "iso:country":"GN",
    "wof:name":"Teguebeya",
    "wof:placetype":"locality"
},
  "geometry": {"coordinates":[-9.76083,8.80167],"type":"Point"}
}