{
  "type": "Feature",
  "properties": {
    "gn:admin1_code":"M",
    "gn:admin2_code":"25",
    "gn:asciiname":"Kebale",
    "gn:country_code":"GN",
    "gn:dem":262,
    "gn:feature_class":"P",
    "gn:feature_code":"PPL",
    "gn:name":"K\u00e9bal\u00e9",
    "gn:population":0,
    "gn:timezone":"Africa/Conakry",
    "iso:country":"GN",
    "wof:name":"Kebale",
    "wof:placetype":"locality"
},
  "geometry": {"coordinates":[-12.78333,10.53333],"type":"Point"}
}