{
  "type": "Feature",
  "properties": {
    "gn:admin1_code":"N",
    "gn:admin2_code":"36",
    "gn:asciiname":"Pola",
    "gn:country_code":"GN",
    "gn:dem":416,
    "gn:feature_class":"P",
    "gn:feature_code":"PPL",
    "gn:name":"Pola",
    "gn:population":0,
    "gn:timezone":"Africa/Conakry",
    "iso:country":"GN",
    "name:bul_x_preferred":[
        "\u041f\u043e\u043b\u0430"
    ],
    "name:cat_x_preferred":[
        "Pola"
    ],
    "name:ceb_x_preferred":[
        "Pola"
    ],
    "name:ces_x_preferred":[
        "Pola"
    ],
    "name:deu_x_preferred":[
        "Pola"
    ],
    "name:fin_x_preferred":[
        "Pola"
    ],
    "name:fra_x_preferred":[
        "Pola"
    ],
    "name:glg_x_preferred":[
        "Pola"
    ],
    "name:hrv_x_preferred":[
        "Pola"
    ],
    "name:hun_x_preferred":[
        "Pola"
    ],
    "name:ita_x_preferred":[
        "Pola"
    ],
    "name:nld_x_preferred":[
        "Pola"
    ],
    "name:pol_x_preferred":[
        "Pola"
    ],
    "name:spa_x_preferred":[
        "Pola"
    ],
    "name:swe_x_preferred":[
        "Pola"
    ],
    "name:und_x_variant":[
        "Pora"
    ],
    "wof:name":"Pola",
    "wof:placetype":"locality"
},
  "geometry": {"coordinates":[-8.29389,7.70583],"type":"Point"}
}