{
  "type": "Feature",
  "properties": {
    "gn:admin1_code":"N",
    "gn:admin2_code":"36",
    "gn:asciiname":"Pola",
    "gn:country_code":"GN",
    "gn:dem":416,
    "gn:feature_class":"P",
    "gn:feature_code":"PPL",
    "gn:name":"Pola",
    "gn:population":0,
    "gn:timezone":"Africa/Conakry",
    "iso:country":"GN",
    "name:und_x_variant":[
        "Pora",
        "Pola"
    ],
    "wof:name":"Pola",
    "wof:placetype":"locality"
},
  "geometry": {"coordinates":[-8.29389,7.70583],"type":"Point"}
}