{
  "type": "Feature",
  "properties": {
    "gn:admin1_code":"K",
    "gn:admin2_code":"15",
    "gn:asciiname":"Manifadou",
    "gn:country_code":"GN",
    "gn:dem":532,
    "gn:feature_class":"P",
    "gn:feature_code":"PPL",
    "gn:name":"Manifadou",
    "gn:population":0,
    "gn:timezone":"Africa/Conakry",
    "iso:country":"GN",
    "wof:name":"Manifadou",
    "wof:placetype":"locality"
},
  "geometry": {"coordinates":[-9.08333,9.21667],"type":"Point"}
}