{
  "type": "Feature",
  "properties": {
    "gn:admin1_code":"F",
    "gn:admin2_code":"07",
    "gn:asciiname":"Daka Sountou",
    "gn:country_code":"GN",
    "gn:dem":530,
    "gn:feature_class":"P",
    "gn:feature_code":"PPL",
    "gn:name":"Daka Sountou",
    "gn:population":0,
    "gn:timezone":"Africa/Conakry",
    "iso:country":"GN",
    "wof:name":"Daka Sountou",
    "wof:placetype":"locality"
},
  "geometry": {"coordinates":[-10.71667,11.41667],"type":"Point"}
}