{
  "type": "Feature",
  "properties": {
    "gn:admin1_code":"N",
    "gn:admin2_code":"38",
    "gn:asciiname":"Konigpala",
    "gn:country_code":"GN",
    "gn:dem":423,
    "gn:feature_class":"P",
    "gn:feature_code":"PPL",
    "gn:name":"Konigpala",
    "gn:population":0,
    "gn:timezone":"Africa/Conakry",
    "iso:country":"GN",
    "wof:name":"Konigpala",
    "wof:placetype":"locality"
},
  "geometry": {"coordinates":[-9.045,7.85556],"type":"Point"}
}