{
  "type": "Feature",
  "properties": {
    "gn:admin1_code":"N",
    "gn:admin2_code":"38",
    "gn:asciiname":"Foudjou",
    "gn:country_code":"GN",
    "gn:dem":471,
    "gn:feature_class":"P",
    "gn:feature_code":"PPL",
    "gn:name":"Foudjou",
    "gn:population":0,
    "gn:timezone":"Africa/Conakry",
    "iso:country":"GN",
    "wof:name":"Foudjou",
    "wof:placetype":"locality"
},
  "geometry": {"coordinates":[-8.66667,8.16667],"type":"Point"}
}