{
  "type": "Feature",
  "properties": {
    "gn:admin1_code":"F",
    "gn:admin2_code":"09",
    "gn:asciiname":"Sanouya",
    "gn:country_code":"GN",
    "gn:dem":471,
    "gn:feature_class":"P",
    "gn:feature_code":"PPL",
    "gn:name":"Sanouya",
    "gn:population":0,
    "gn:timezone":"Africa/Conakry",
    "iso:country":"GN",
    "wof:name":"Sanouya",
    "wof:placetype":"locality"
},
  "geometry": {"coordinates":[-11.11667,10.06667],"type":"Point"}
}