{
  "type": "Feature",
  "properties": {
    "gn:admin1_code":"N",
    "gn:admin2_code":"21",
    "gn:asciiname":"Kalo",
    "gn:country_code":"GN",
    "gn:dem":550,
    "gn:feature_class":"P",
    "gn:feature_code":"PPL",
    "gn:name":"Kalo",
    "gn:population":0,
    "gn:timezone":"Africa/Conakry",
    "iso:country":"GN",
    "wof:name":"Kalo",
    "wof:placetype":"locality"
},
  "geometry": {"coordinates":[-9.55778,8.48806],"type":"Point"}
}