{
  "type": "Feature",
  "properties": {
    "gn:admin1_code":"F",
    "gn:admin2_code":"09",
    "gn:asciiname":"Morissiria",
    "gn:country_code":"GN",
    "gn:dem":486,
    "gn:feature_class":"P",
    "gn:feature_code":"PPL",
    "gn:name":"Morissiria",
    "gn:population":0,
    "gn:timezone":"Africa/Conakry",
    "iso:country":"GN",
    "wof:name":"Morissiria",
    "wof:placetype":"locality"
},
  "geometry": {"coordinates":[-10.46667,10.03333],"type":"Point"}
}