{
  "type": "Feature",
  "properties": {
    "gn:admin1_code":"D",
    "gn:admin2_code":"10",
    "gn:asciiname":"Yasasi",
    "gn:country_code":"GN",
    "gn:dem":4,
    "gn:feature_class":"P",
    "gn:feature_code":"PPL",
    "gn:name":"Yasasi",
    "gn:population":0,
    "gn:timezone":"Africa/Conakry",
    "iso:country":"GN",
    "wof:name":"Yasasi",
    "wof:placetype":"locality"
},
  "geometry": {"coordinates":[-13.40917,9.42222],"type":"Point"}
}