{
  "type": "Feature",
  "properties": {
    "gn:admin1_code":"N",
    "gn:admin2_code":"29",
    "gn:asciiname":"Koeta",
    "gn:cc2":"GN",
    "gn:country_code":"GN",
    "gn:dem":387,
    "gn:feature_class":"P",
    "gn:feature_code":"PPL",
    "gn:name":"Ko\u00e9ta",
    "gn:population":0,
    "gn:timezone":"Africa/Conakry",
    "iso:country":"GN",
    "name:und_x_variant":[
        "Ko\u00e9ta"
    ],
    "wof:name":"Koeta",
    "wof:placetype":"locality"
},
  "geometry": {"coordinates":[-9.22306,7.58778],"type":"Point"}
}