{
  "type": "Feature",
  "properties": {
    "gn:admin1_code":"N",
    "gn:admin2_code":"01",
    "gn:asciiname":"Kouroufe",
    "gn:cc2":"GN",
    "gn:country_code":"GN",
    "gn:dem":572,
    "gn:feature_class":"P",
    "gn:feature_code":"PPL",
    "gn:name":"Kourouf\u00e9",
    "gn:population":0,
    "gn:timezone":"Africa/Conakry",
    "iso:country":"GN",
    "name:und_x_variant":[
        "Kouroufi",
        "Kourouf\u00e9"
    ],
    "wof:name":"Kouroufe",
    "wof:placetype":"locality"
},
  "geometry": {"coordinates":[-8.03333,9.03333],"type":"Point"}
}