{
  "type": "Feature",
  "properties": {
    "gn:admin1_code":"F",
    "gn:admin2_code":"09",
    "gn:asciiname":"Bouraya",
    "gn:country_code":"GN",
    "gn:dem":649,
    "gn:feature_class":"P",
    "gn:feature_code":"PPL",
    "gn:name":"Bouraya",
    "gn:population":0,
    "gn:timezone":"Africa/Conakry",
    "iso:country":"GN",
    "wof:name":"Bouraya",
    "wof:placetype":"locality"
},
  "geometry": {"coordinates":[-10.63333,9.15],"type":"Point"}
}