{
  "type": "Feature",
  "properties": {
    "gn:admin1_code":"F",
    "gn:admin2_code":"19",
    "gn:asciiname":"Keniebo",
    "gn:country_code":"GN",
    "gn:dem":434,
    "gn:feature_class":"P",
    "gn:feature_code":"PPL",
    "gn:name":"K\u00e9ni\u00e9bo",
    "gn:population":0,
    "gn:timezone":"Africa/Conakry",
    "iso:country":"GN",
    "wof:name":"Keniebo",
    "wof:placetype":"locality"
},
  "geometry": {"coordinates":[-10.63333,10.63333],"type":"Point"}
}