{
  "type": "Feature",
  "properties": {
    "gn:country":"GN",
    "gn:fcode":"PPLA2",
    "gn:pop":2332,
    "iso:country":"GN",
    "name:ara_x_preferred":[
        "\u0628\u0648\u0641\u0627"
    ],
    "name:bul_x_preferred":[
        "\u0411\u043e\u0444\u0430"
    ],
    "name:cat_x_preferred":[
        "Boffa"
    ],
    "name:ceb_x_preferred":[
        "Boffa"
    ],
    "name:eng_x_preferred":[
        "Boffa"
    ],
    "name:fin_x_preferred":[
        "Boffa"
    ],
    "name:fra_x_preferred":[
        "Boffa"
    ],
    "name:frr_x_preferred":[
        "Boffa"
    ],
    "name:heb_x_preferred":[
        "\u05d1\u05d5\u05e4\u05d4"
    ],
    "name:ita_x_preferred":[
        "Boffa"
    ],
    "name:jpn_x_preferred":[
        "\u30dc\u30c3\u30d5\u30a1"
    ],
    "name:nld_x_preferred":[
        "Boffa"
    ],
    "name:pol_x_preferred":[
        "Boffa"
    ],
    "name:por_x_preferred":[
        "Boffa"
    ],
    "name:spa_x_preferred":[
        "Boffa"
    ],
    "name:swe_x_preferred":[
        "Boffa"
    ],
    "name:tur_x_preferred":[
        "Boffa"
    ],
    "name:unk_x_variant":[
        "Bomma"
    ],
    "ne:ADM0CAP":0.0,
    "ne:ADM0NAME":"Guinea",
    "ne:ADM0_A3":"GIN",
    "ne:ADM1NAME":"Boke",
    "ne:ADMIN1_COD":2,
    "ne:CAPALT":0,
    "ne:CHANGED":4,
    "ne:CHECKME":0,
    "ne:COMPARE":0,
    "ne:DIFFASCII":0,
    "ne:DIFFNOTE":"Added missing admin-1 capital. Population from GeoNames.",
    "ne:ELEVATION":0.0,
    "ne:FEATURECLA":"Admin-1 capital",
    "ne:FEATURE_CL":"P",
    "ne:FEATURE_CO":"PPLA",
    "ne:GEONAMEID":2422968,
    "ne:GEONAMESNO":"GeoNames match general.",
    "ne:GN_ASCII":"Boffa",
    "ne:GN_POP":2332,
    "ne:GTOPO30":63.0,
    "ne:ISO_A2":"GN",
    "ne:LABELRANK":8,
    "ne:LATITUDE":10.185003,
    "ne:LONGITUDE":-14.042996,
    "ne:LS_MATCH":0,
    "ne:MAX_AREAKM":0.0,
    "ne:MAX_AREAMI":0.0,
    "ne:MAX_BBXMAX":0.0,
    "ne:MAX_BBXMIN":0.0,
    "ne:MAX_BBYMAX":0.0,
    "ne:MAX_BBYMIN":0.0,
    "ne:MAX_NATSCA":0.0,
    "ne:MAX_PERKM":0.0,
    "ne:MAX_PERMI":0.0,
    "ne:MAX_POP10":0,
    "ne:MAX_POP20":0,
    "ne:MAX_POP300":0,
    "ne:MAX_POP310":0,
    "ne:MAX_POP50":0,
    "ne:MEAN_BBXC":0.0,
    "ne:MEAN_BBYC":0.0,
    "ne:MEGACITY":0,
    "ne:MIN_AREAKM":0.0,
    "ne:MIN_AREAMI":0.0,
    "ne:MIN_BBXMAX":0.0,
    "ne:MIN_BBXMIN":0.0,
    "ne:MIN_BBYMAX":0.0,
    "ne:MIN_BBYMIN":0.0,
    "ne:MIN_PERKM":0.0,
    "ne:MIN_PERMI":0.0,
    "ne:NAME":"Boffa",
    "ne:NAMEASCII":"Boffa",
    "ne:NAMEDIFF":1,
    "ne:NATSCALE":1,
    "ne:POP1950":0,
    "ne:POP1955":0,
    "ne:POP1960":0,
    "ne:POP1965":0,
    "ne:POP1970":0,
    "ne:POP1975":0,
    "ne:POP1980":0,
    "ne:POP1985":0,
    "ne:POP1990":0,
    "ne:POP1995":0,
    "ne:POP2000":0,
    "ne:POP2005":0,
    "ne:POP2010":0,
    "ne:POP2015":0,
    "ne:POP2020":0,
    "ne:POP2025":0,
    "ne:POP2050":0,
    "ne:POP_MAX":2332,
    "ne:POP_MIN":2332,
    "ne:POP_OTHER":0,
    "ne:RANK_MAX":4,
    "ne:RANK_MIN":4,
    "ne:SCALERANK":10,
    "ne:SOV0NAME":"Guinea",
    "ne:SOV_A3":"GIN",
    "ne:TIMEZONE":"Africa/Conakry",
    "ne:UN_FID":0,
    "ne:UN_LAT":0.0,
    "ne:UN_LONG":0.0,
    "ne:WORLDCITY":0,
    "qs:name":"Boffa",
    "qs:photos_9r":0,
    "qs:photos_sr":0,
    "qs:pop_sr":"4",
    "wd:wordcount":77,
    "wof:name":"Boffa",
    "wof:placetype":"locality",
    "wof:population":2332
},
  "geometry": {"coordinates":[-14.03333,10.16667],"type":"Point"}
}