{
  "type": "Feature",
  "properties": {
    "gn:admin1_code":"N",
    "gn:admin2_code":"21",
    "gn:asciiname":"Boule",
    "gn:cc2":"GN",
    "gn:country_code":"GN",
    "gn:dem":486,
    "gn:feature_class":"P",
    "gn:feature_code":"PPL",
    "gn:name":"Boul\u00e9",
    "gn:population":0,
    "gn:timezone":"Africa/Conakry",
    "iso:country":"GN",
    "name:ceb_x_preferred":[
        "Boule"
    ],
    "name:deu_x_preferred":[
        "Boule"
    ],
    "name:fra_x_preferred":[
        "Boule"
    ],
    "name:ita_x_preferred":[
        "Boule"
    ],
    "name:nld_x_preferred":[
        "Boule"
    ],
    "name:rus_x_preferred":[
        "\u0411\u0443\u043b\u0435"
    ],
    "name:spa_x_preferred":[
        "Boule"
    ],
    "name:swe_x_preferred":[
        "Boule"
    ],
    "name:und_x_variant":[
        "Boul\u00e9"
    ],
    "wof:name":"Boule",
    "wof:placetype":"locality"
},
  "geometry": {"coordinates":[-9.37472,7.95389],"type":"Point"}
}