{
  "type": "Feature",
  "properties": {
    "gn:admin1_code":"M",
    "gn:admin2_code":"06",
    "gn:asciiname":"Tielire",
    "gn:country_code":"GN",
    "gn:dem":824,
    "gn:feature_class":"P",
    "gn:feature_code":"PPL",
    "gn:name":"Ti\u00e9lir\u00e9",
    "gn:population":0,
    "gn:timezone":"Africa/Conakry",
    "iso:country":"GN",
    "wof:name":"Tielire",
    "wof:placetype":"locality"
},
  "geometry": {"coordinates":[-12.33333,10.96667],"type":"Point"}
}