{
  "type": "Feature",
  "properties": {
    "gn:admin1_code":"B",
    "gn:admin2_code":"03",
    "gn:asciiname":"Potopata",
    "gn:cc2":"GN",
    "gn:country_code":"GN",
    "gn:dem":22,
    "gn:feature_class":"P",
    "gn:feature_code":"PPL",
    "gn:name":"Potopata",
    "gn:population":0,
    "gn:timezone":"Africa/Conakry",
    "iso:country":"GN",
    "name:und_x_variant":[
        "Poutou Pata",
        "Potopata"
    ],
    "wof:name":"Potopata",
    "wof:placetype":"locality"
},
  "geometry": {"coordinates":[-14.76667,11.13333],"type":"Point"}
}