{
  "type": "Feature",
  "properties": {
    "gn:admin1_code":"K",
    "gn:admin2_code":"39",
    "gn:asciiname":"Konianfara",
    "gn:country_code":"GN",
    "gn:dem":383,
    "gn:feature_class":"P",
    "gn:feature_code":"PPL",
    "gn:name":"Konianfara",
    "gn:population":0,
    "gn:timezone":"Africa/Conakry",
    "iso:country":"GN",
    "wof:name":"Konianfara",
    "wof:placetype":"locality"
},
  "geometry": {"coordinates":[-8.98333,11.63333],"type":"Point"}
}