{
  "type": "Feature",
  "properties": {
    "gn:admin1_code":"D",
    "gn:admin2_code":"27",
    "gn:asciiname":"Nomo",
    "gn:country_code":"GN",
    "gn:dem":339,
    "gn:feature_class":"P",
    "gn:feature_code":"PPL",
    "gn:name":"Nomo",
    "gn:population":0,
    "gn:timezone":"Africa/Conakry",
    "iso:country":"GN",
    "name:ceb_x_preferred":[
        "Nomo"
    ],
    "name:deu_x_preferred":[
        "Nomo"
    ],
    "name:glg_x_preferred":[
        "Nomo"
    ],
    "name:ita_x_preferred":[
        "Nomo"
    ],
    "name:por_x_preferred":[
        "Nomo"
    ],
    "name:slk_x_preferred":[
        "Nomo"
    ],
    "name:swe_x_preferred":[
        "Nomo"
    ],
    "wof:name":"Nomo",
    "wof:placetype":"locality"
},
  "geometry": {"coordinates":[-13.38333,11.28333],"type":"Point"}
}