{
  "type": "Feature",
  "properties": {
    "gn:admin1_code":"D",
    "gn:admin2_code":"10",
    "gn:asciiname":"Kafou",
    "gn:country_code":"GN",
    "gn:dem":57,
    "gn:feature_class":"P",
    "gn:feature_code":"PPL",
    "gn:name":"Kafou",
    "gn:population":0,
    "gn:timezone":"Africa/Conakry",
    "iso:country":"GN",
    "wof:name":"Kafou",
    "wof:placetype":"locality"
},
  "geometry": {"coordinates":[-12.86667,9.33333],"type":"Point"}
}