{
  "type": "Feature",
  "properties": {
    "gn:admin1_code":"M",
    "gn:admin2_code":"23",
    "gn:asciiname":"Bagata",
    "gn:country_code":"GN",
    "gn:dem":636,
    "gn:feature_class":"P",
    "gn:feature_code":"PPL",
    "gn:name":"Bagata",
    "gn:population":0,
    "gn:timezone":"Africa/Conakry",
    "iso:country":"GN",
    "wof:name":"Bagata",
    "wof:placetype":"locality"
},
  "geometry": {"coordinates":[-11.66667,10.71667],"type":"Point"}
}