{
  "type": "Feature",
  "properties": {
    "gn:admin1_code":"N",
    "gn:admin2_code":"01",
    "gn:asciiname":"Solonfe",
    "gn:country_code":"GN",
    "gn:dem":561,
    "gn:feature_class":"P",
    "gn:feature_code":"PPL",
    "gn:name":"Solonf\u00e9",
    "gn:population":0,
    "gn:timezone":"Africa/Conakry",
    "iso:country":"GN",
    "wof:name":"Solonfe",
    "wof:placetype":"locality"
},
  "geometry": {"coordinates":[-8.36667,8.23333],"type":"Point"}
}