{
  "type": "Feature",
  "properties": {
    "gn:admin1_code":"F",
    "gn:admin2_code":"05",
    "gn:asciiname":"Kobilato",
    "gn:cc2":"GN",
    "gn:country_code":"GN",
    "gn:dem":716,
    "gn:feature_class":"P",
    "gn:feature_code":"PPL",
    "gn:name":"Kobilato",
    "gn:population":0,
    "gn:timezone":"Africa/Conakry",
    "iso:country":"GN",
    "name:und_x_variant":[
        "Kobilado",
        "Kobilato"
    ],
    "wof:name":"Kobilato",
    "wof:placetype":"locality"
},
  "geometry": {"coordinates":[-11.48333,10.58333],"type":"Point"}
}