{
  "type": "Feature",
  "properties": {
    "gn:admin1_code":"K",
    "gn:admin2_code":"37",
    "gn:asciiname":"Farasababe",
    "gn:country_code":"GN",
    "gn:dem":382,
    "gn:feature_class":"P",
    "gn:feature_code":"PPL",
    "gn:name":"Farasabab\u00e9",
    "gn:population":0,
    "gn:timezone":"Africa/Conakry",
    "iso:country":"GN",
    "wof:name":"Farasababe",
    "wof:placetype":"locality"
},
  "geometry": {"coordinates":[-8.83333,11.31667],"type":"Point"}
}