{
  "type": "Feature",
  "properties": {
    "gn:admin1_code":"N",
    "gn:admin2_code":"13",
    "gn:asciiname":"Kenema",
    "gn:country_code":"GN",
    "gn:dem":436,
    "gn:feature_class":"P",
    "gn:feature_code":"PPL",
    "gn:name":"Ken\u00e9ma",
    "gn:population":0,
    "gn:timezone":"Africa/Conakry",
    "iso:country":"GN",
    "wof:name":"Kenema",
    "wof:placetype":"locality"
},
  "geometry": {"coordinates":[-10.35278,8.67028],"type":"Point"}
}