{
  "type": "Feature",
  "properties": {
    "gn:admin1_code":"N",
    "gn:admin2_code":"13",
    "gn:asciiname":"Kenema",
    "gn:country_code":"GN",
    "gn:dem":436,
    "gn:feature_class":"P",
    "gn:feature_code":"PPL",
    "gn:name":"Ken\u00e9ma",
    "gn:population":0,
    "gn:timezone":"Africa/Conakry",
    "iso:country":"GN",
    "name:afr_x_preferred":[
        "Kenema"
    ],
    "name:ara_x_preferred":[
        "\u0643\u064a\u0646\u064a\u0645\u0627"
    ],
    "name:ben_x_preferred":[
        "\u0995\u09c7\u09a8\u09c7\u09ae\u09be"
    ],
    "name:bul_x_preferred":[
        "\u041a\u0435\u043d\u0435\u043c\u0430"
    ],
    "name:ceb_x_preferred":[
        "Kenema"
    ],
    "name:ces_x_preferred":[
        "Kenema"
    ],
    "name:dan_x_preferred":[
        "Kenema"
    ],
    "name:deu_x_preferred":[
        "Kenema"
    ],
    "name:ell_x_preferred":[
        "\u039a\u03b5\u03bd\u03ad\u03bc\u03b1"
    ],
    "name:epo_x_preferred":[
        "Kenema"
    ],
    "name:fin_x_preferred":[
        "Kenema"
    ],
    "name:fra_x_preferred":[
        "Kenema"
    ],
    "name:hrv_x_preferred":[
        "Kenema"
    ],
    "name:ind_x_preferred":[
        "Kenema"
    ],
    "name:ita_x_preferred":[
        "Kenema"
    ],
    "name:jpn_x_preferred":[
        "\u30b1\u30cd\u30de"
    ],
    "name:kor_x_preferred":[
        "\ucf00\ub124\ub9c8"
    ],
    "name:lit_x_preferred":[
        "Kenema"
    ],
    "name:nld_x_preferred":[
        "Kenema"
    ],
    "name:nor_x_preferred":[
        "Kenema"
    ],
    "name:pol_x_preferred":[
        "Kenema"
    ],
    "name:por_x_preferred":[
        "Kenema"
    ],
    "name:ron_x_preferred":[
        "Kenema"
    ],
    "name:rus_x_preferred":[
        "\u041a\u0435\u043d\u0435\u043c\u0430"
    ],
    "name:spa_x_preferred":[
        "Kenema"
    ],
    "name:swe_x_preferred":[
        "Kenema"
    ],
    "name:tur_x_preferred":[
        "Kenema"
    ],
    "name:urd_x_preferred":[
        "\u06a9\u06cc\u0646\u06cc\u0645\u0627"
    ],
    "name:uzb_x_preferred":[
        "Kenema"
    ],
    "name:zho_x_preferred":[
        "\u51ef\u5185\u9a6c"
    ],
    "wof:name":"Kenema",
    "wof:placetype":"locality"
},
  "geometry": {"coordinates":[-10.35278,8.67028],"type":"Point"}
}