{
  "type": "Feature",
  "properties": {
    "gn:admin1_code":"B",
    "gn:admin2_code":"02",
    "gn:asciiname":"Samansira",
    "gn:country_code":"GN",
    "gn:dem":65,
    "gn:feature_class":"P",
    "gn:feature_code":"PPL",
    "gn:name":"Samansira",
    "gn:population":0,
    "gn:timezone":"Africa/Conakry",
    "iso:country":"GN",
    "wof:name":"Samansira",
    "wof:placetype":"locality"
},
  "geometry": {"coordinates":[-14.28333,10.48333],"type":"Point"}
}