{
  "type": "Feature",
  "properties": {
    "gn:admin1_code":"K",
    "gn:admin2_code":"39",
    "gn:asciiname":"Tondo",
    "gn:country_code":"GN",
    "gn:dem":330,
    "gn:feature_class":"P",
    "gn:feature_code":"PPL",
    "gn:name":"Tondo",
    "gn:population":0,
    "gn:timezone":"Africa/Conakry",
    "iso:country":"GN",
    "name:ceb_x_preferred":[
        "Tondo"
    ],
    "name:deu_x_preferred":[
        "Tondo"
    ],
    "name:fra_x_preferred":[
        "Tondo"
    ],
    "name:ita_x_preferred":[
        "Tondo"
    ],
    "name:nld_x_preferred":[
        "Tondo"
    ],
    "name:nor_x_preferred":[
        "Tondo"
    ],
    "name:rus_x_preferred":[
        "\u0422\u043e\u043d\u0434\u043e"
    ],
    "name:sco_x_preferred":[
        "Tondo"
    ],
    "name:spa_x_preferred":[
        "Tondo"
    ],
    "name:swe_x_preferred":[
        "Tondo"
    ],
    "name:tgl_x_preferred":[
        "Tondo"
    ],
    "wof:name":"Tondo",
    "wof:placetype":"locality"
},
  "geometry": {"coordinates":[-9.15,11.98333],"type":"Point"}
}