{
  "type": "Feature",
  "properties": {
    "gn:admin1_code":"B",
    "gn:admin2_code":"12",
    "gn:asciiname":"Illime",
    "gn:country_code":"GN",
    "gn:dem":488,
    "gn:feature_class":"P",
    "gn:feature_code":"PPL",
    "gn:name":"Illim\u00e9",
    "gn:population":0,
    "gn:timezone":"Africa/Conakry",
    "iso:country":"GN",
    "wof:name":"Illime",
    "wof:placetype":"locality"
},
  "geometry": {"coordinates":[-12.93333,11.53333],"type":"Point"}
}