{
  "type": "Feature",
  "properties": {
    "gn:admin1_code":"B",
    "gn:admin2_code":"18",
    "gn:asciiname":"Koubia",
    "gn:country_code":"GN",
    "gn:dem":144,
    "gn:feature_class":"P",
    "gn:feature_code":"PPL",
    "gn:name":"Koubia",
    "gn:population":0,
    "gn:timezone":"Africa/Conakry",
    "iso:country":"GN",
    "wof:name":"Koubia",
    "wof:placetype":"locality"
},
  "geometry": {"coordinates":[-12.5937,12.3529],"type":"Point"}
}