{
  "type": "Feature",
  "properties": {
    "gn:admin1_code":"B",
    "gn:admin2_code":"18",
    "gn:asciiname":"Koubia",
    "gn:country_code":"GN",
    "gn:dem":144,
    "gn:feature_class":"P",
    "gn:feature_code":"PPL",
    "gn:name":"Koubia",
    "gn:population":0,
    "gn:timezone":"Africa/Conakry",
    "iso:country":"GN",
    "name:bul_x_preferred":[
        "\u041a\u0443\u0431\u0438\u044f"
    ],
    "name:ceb_x_preferred":[
        "Koubia"
    ],
    "name:fas_x_preferred":[
        "\u06a9\u0648\u0628\u06cc\u0627"
    ],
    "name:fin_x_preferred":[
        "Koubia"
    ],
    "name:fra_x_preferred":[
        "Koubia"
    ],
    "name:heb_x_preferred":[
        "\u05e7\u05d5\u05d1\u05d9\u05d4"
    ],
    "name:hun_x_preferred":[
        "Koubia"
    ],
    "name:ita_x_preferred":[
        "Koubia"
    ],
    "name:msa_x_preferred":[
        "Koubia"
    ],
    "name:pol_x_preferred":[
        "Koubia"
    ],
    "name:spa_x_preferred":[
        "Koubia"
    ],
    "name:swe_x_preferred":[
        "Koubia"
    ],
    "wof:name":"Koubia",
    "wof:placetype":"locality"
},
  "geometry": {"coordinates":[-12.5937,12.3529],"type":"Point"}
}