{
  "type": "Feature",
  "properties": {
    "gn:admin1_code":"N",
    "gn:admin2_code":"13",
    "gn:asciiname":"Kolifa",
    "gn:country_code":"GN",
    "gn:dem":378,
    "gn:feature_class":"P",
    "gn:feature_code":"PPL",
    "gn:name":"Kolifa",
    "gn:population":0,
    "gn:timezone":"Africa/Conakry",
    "iso:country":"GN",
    "wof:name":"Kolifa",
    "wof:placetype":"locality"
},
  "geometry": {"coordinates":[-10.45222,8.69944],"type":"Point"}
}