{
  "type": "Feature",
  "properties": {
    "gn:admin1_code":"N",
    "gn:admin2_code":"29",
    "gn:asciiname":"Telikoele",
    "gn:cc2":"GN",
    "gn:country_code":"GN",
    "gn:dem":395,
    "gn:feature_class":"P",
    "gn:feature_code":"PPL",
    "gn:name":"T\u00e9liko\u00e9l\u00e9",
    "gn:population":0,
    "gn:timezone":"Africa/Conakry",
    "iso:country":"GN",
    "name:und_x_variant":[
        "Teliko\u00e9l\u00e9",
        "T\u00e9liko\u00e9l\u00e9"
    ],
    "wof:name":"Telikoele",
    "wof:placetype":"locality"
},
  "geometry": {"coordinates":[-9.22944,7.48556],"type":"Point"}
}