{
  "type": "Feature",
  "properties": {
    "gn:admin1_code":"F",
    "gn:admin2_code":"07",
    "gn:asciiname":"Fougoumba",
    "gn:country_code":"GN",
    "gn:dem":388,
    "gn:feature_class":"P",
    "gn:feature_code":"PPL",
    "gn:name":"Fougoumba",
    "gn:population":0,
    "gn:timezone":"Africa/Conakry",
    "iso:country":"GN",
    "wof:name":"Fougoumba",
    "wof:placetype":"locality"
},
  "geometry": {"coordinates":[-10.83333,11.51667],"type":"Point"}
}