{
  "type": "Feature",
  "properties": {
    "gn:admin1_code":"B",
    "gn:admin2_code":"12",
    "gn:asciiname":"Seriba",
    "gn:country_code":"GN",
    "gn:dem":122,
    "gn:feature_class":"P",
    "gn:feature_code":"PPL",
    "gn:name":"S\u00e9riba",
    "gn:population":0,
    "gn:timezone":"Africa/Conakry",
    "iso:country":"GN",
    "wof:name":"Seriba",
    "wof:placetype":"locality"
},
  "geometry": {"coordinates":[-13.06667,11.76667],"type":"Point"}
}