{
  "type": "Feature",
  "properties": {
    "gn:admin1_code":"B",
    "gn:admin2_code":"02",
    "gn:asciiname":"Tanene",
    "gn:country_code":"GN",
    "gn:dem":27,
    "gn:feature_class":"P",
    "gn:feature_code":"PPL",
    "gn:name":"Tan\u00e9n\u00e9",
    "gn:population":0,
    "gn:timezone":"Africa/Conakry",
    "iso:country":"GN",
    "wof:name":"Tanene",
    "wof:placetype":"locality"
},
  "geometry": {"coordinates":[-13.86278,9.94139],"type":"Point"}
}