{
  "type": "Feature",
  "properties": {
    "gn:admin1_code":"F",
    "gn:admin2_code":"09",
    "gn:asciiname":"Dansokoya",
    "gn:cc2":"GN",
    "gn:country_code":"GN",
    "gn:dem":447,
    "gn:feature_class":"P",
    "gn:feature_code":"PPL",
    "gn:name":"Dansokoya",
    "gn:population":0,
    "gn:timezone":"Africa/Conakry",
    "iso:country":"GN",
    "name:und_x_variant":[
        "Dansogoya",
        "Dansokoya"
    ],
    "wof:name":"Dansokoya",
    "wof:placetype":"locality"
},
  "geometry": {"coordinates":[-10.81667,10.36667],"type":"Point"}
}