{
  "type": "Feature",
  "properties": {
    "gn:admin1_code":"N",
    "gn:admin2_code":"38",
    "gn:asciiname":"Lomou",
    "gn:country_code":"GN",
    "gn:dem":564,
    "gn:feature_class":"P",
    "gn:feature_code":"PPL",
    "gn:name":"Lomou",
    "gn:population":0,
    "gn:timezone":"Africa/Conakry",
    "iso:country":"GN",
    "wof:name":"Lomou",
    "wof:placetype":"locality"
},
  "geometry": {"coordinates":[-8.81667,8.23333],"type":"Point"}
}