{
  "type": "Feature",
  "properties": {
    "gn:admin1_code":"F",
    "gn:admin2_code":"09",
    "gn:asciiname":"Foroconia",
    "gn:cc2":"GN",
    "gn:country_code":"GN",
    "gn:dem":595,
    "gn:feature_class":"P",
    "gn:feature_code":"PPL",
    "gn:name":"Foroconia",
    "gn:population":0,
    "gn:timezone":"Africa/Conakry",
    "iso:country":"GN",
    "name:und_x_variant":[
        "Fourkonia",
        "Foroconia"
    ],
    "wof:name":"Foroconia",
    "wof:placetype":"locality"
},
  "geometry": {"coordinates":[-10.66667,9.13333],"type":"Point"}
}