{
  "type": "Feature",
  "properties": {
    "gn:admin1_code":"B",
    "gn:admin2_code":"18",
    "gn:asciiname":"Unntiti",
    "gn:country_code":"GN",
    "gn:dem":77,
    "gn:feature_class":"P",
    "gn:feature_code":"PPL",
    "gn:name":"Unntiti",
    "gn:population":0,
    "gn:timezone":"Africa/Conakry",
    "iso:country":"GN",
    "wof:name":"Unntiti",
    "wof:placetype":"locality"
},
  "geometry": {"coordinates":[-13.15,12.51667],"type":"Point"}
}