{
  "type": "Feature",
  "properties": {
    "gn:admin1_code":"B",
    "gn:admin2_code":"18",
    "gn:asciiname":"Simde",
    "gn:country_code":"GN",
    "gn:dem":60,
    "gn:feature_class":"P",
    "gn:feature_code":"PPL",
    "gn:name":"Simd\u00e9",
    "gn:population":0,
    "gn:timezone":"Africa/Conakry",
    "iso:country":"GN",
    "wof:name":"Simde",
    "wof:placetype":"locality"
},
  "geometry": {"coordinates":[-13.46667,12.35],"type":"Point"}
}