{
  "type": "Feature",
  "properties": {
    "gn:admin1_code":"N",
    "gn:admin2_code":"38",
    "gn:asciiname":"Koola",
    "gn:cc2":"GN",
    "gn:country_code":"GN",
    "gn:dem":470,
    "gn:feature_class":"P",
    "gn:feature_code":"PPL",
    "gn:name":"Koola",
    "gn:population":0,
    "gn:timezone":"Africa/Conakry",
    "iso:country":"GN",
    "name:bul_x_preferred":[
        "\u041a\u043e\u0431\u0435\u043b\u0430"
    ],
    "name:fra_x_preferred":[
        "Kob\u00e9la"
    ],
    "name:ita_x_preferred":[
        "Kob\u00e9la"
    ],
    "name:msa_x_preferred":[
        "Kob\u00e9la"
    ],
    "name:spa_x_preferred":[
        "Kob\u00e9la"
    ],
    "name:und_x_variant":[
        "Kobela",
        "Koola"
    ],
    "wof:name":"Koola",
    "wof:placetype":"locality"
},
  "geometry": {"coordinates":[-9.02333,7.88611],"type":"Point"}
}