{
  "type": "Feature",
  "properties": {
    "gn:admin1_code":"N",
    "gn:admin2_code":"13",
    "gn:asciiname":"Odoulon",
    "gn:country_code":"GN",
    "gn:dem":503,
    "gn:feature_class":"P",
    "gn:feature_code":"PPL",
    "gn:name":"Odoulon",
    "gn:population":0,
    "gn:timezone":"Africa/Conakry",
    "iso:country":"GN",
    "wof:name":"Odoulon",
    "wof:placetype":"locality"
},
  "geometry": {"coordinates":[-10.05333,8.45167],"type":"Point"}
}