{
  "type": "Feature",
  "properties": {
    "gn:admin1_code":"N",
    "gn:admin2_code":"21",
    "gn:asciiname":"Lampo",
    "gn:country_code":"GN",
    "gn:dem":690,
    "gn:feature_class":"P",
    "gn:feature_code":"PPL",
    "gn:name":"Lampo",
    "gn:population":0,
    "gn:timezone":"Africa/Conakry",
    "iso:country":"GN",
    "wof:name":"Lampo",
    "wof:placetype":"locality"
},
  "geometry": {"coordinates":[-9.35333,8.56028],"type":"Point"}
}