{
  "type": "Feature",
  "properties": {
    "gn:admin1_code":"F",
    "gn:admin2_code":"09",
    "gn:asciiname":"Sekorea",
    "gn:country_code":"GN",
    "gn:dem":445,
    "gn:feature_class":"P",
    "gn:feature_code":"PPL",
    "gn:name":"S\u00e9kor\u00e9a",
    "gn:population":0,
    "gn:timezone":"Africa/Conakry",
    "iso:country":"GN",
    "wof:name":"Sekorea",
    "wof:placetype":"locality"
},
  "geometry": {"coordinates":[-10.88333,10.08333],"type":"Point"}
}