{
  "type": "Feature",
  "properties": {
    "gn:admin1_code":"N",
    "gn:admin2_code":"13",
    "gn:asciiname":"Segbedou",
    "gn:country_code":"GN",
    "gn:dem":472,
    "gn:feature_class":"P",
    "gn:feature_code":"PPL",
    "gn:name":"Segb\u00e9dou",
    "gn:population":0,
    "gn:timezone":"Africa/Conakry",
    "iso:country":"GN",
    "wof:name":"Segbedou",
    "wof:placetype":"locality"
},
  "geometry": {"coordinates":[-10.23806,8.6675],"type":"Point"}
}