{
  "type": "Feature",
  "properties": {
    "gn:admin1_code":"F",
    "gn:admin2_code":"07",
    "gn:asciiname":"Hafia",
    "gn:country_code":"GN",
    "gn:dem":363,
    "gn:feature_class":"P",
    "gn:feature_code":"PPL",
    "gn:name":"Hafia",
    "gn:population":0,
    "gn:timezone":"Africa/Conakry",
    "iso:country":"GN",
    "wof:name":"Hafia",
    "wof:placetype":"locality"
},
  "geometry": {"coordinates":[-10.36667,11.85],"type":"Point"}
}