{
  "type": "Feature",
  "properties": {
    "gn:admin1_code":"K",
    "gn:admin2_code":"37",
    "gn:asciiname":"Koundianakoura",
    "gn:country_code":"GN",
    "gn:dem":361,
    "gn:feature_class":"P",
    "gn:feature_code":"PPL",
    "gn:name":"Koundianakoura",
    "gn:population":0,
    "gn:timezone":"Africa/Conakry",
    "iso:country":"GN",
    "wof:name":"Koundianakoura",
    "wof:placetype":"locality"
},
  "geometry": {"coordinates":[-8.71667,11.25],"type":"Point"}
}