{
  "type": "Feature",
  "properties": {
    "gn:admin1_code":"D",
    "gn:admin2_code":"16",
    "gn:asciiname":"Kouyeya",
    "gn:country_code":"GN",
    "gn:dem":89,
    "gn:feature_class":"P",
    "gn:feature_code":"PPL",
    "gn:name":"Kouy\u00e9ya",
    "gn:population":0,
    "gn:timezone":"Africa/Conakry",
    "iso:country":"GN",
    "name:und_x_variant":[
        "Kouy\u00e9ya"
    ],
    "wof:name":"Kouyeya",
    "wof:placetype":"locality"
},
  "geometry": {"coordinates":[-12.68333,10.08333],"type":"Point"}
}