{
  "type": "Feature",
  "properties": {
    "gn:admin1_code":"K",
    "gn:admin2_code":"01",
    "gn:asciiname":"Foundougou",
    "gn:country_code":"GN",
    "gn:dem":730,
    "gn:feature_class":"P",
    "gn:feature_code":"PPL",
    "gn:name":"Foundougou",
    "gn:population":0,
    "gn:timezone":"Africa/Conakry",
    "iso:country":"GN",
    "name:und_x_variant":[
        "Fondougou",
        "Foudougou",
        "Foundougou"
    ],
    "wof:name":"Foundougou",
    "wof:placetype":"locality"
},
  "geometry": {"coordinates":[-8.88333,8.93333],"type":"Point"}
}