{
  "type": "Feature",
  "properties": {
    "gn:admin1_code":"L",
    "gn:admin2_code":"28",
    "gn:asciiname":"Koulifakara",
    "gn:cc2":"GN",
    "gn:country_code":"GN",
    "gn:dem":787,
    "gn:feature_class":"P",
    "gn:feature_code":"PPL",
    "gn:name":"Koulifakara",
    "gn:population":0,
    "gn:timezone":"Africa/Conakry",
    "iso:country":"GN",
    "name:und_x_variant":[
        "Kouilifakara",
        "Koulifakara"
    ],
    "wof:name":"Koulifakara",
    "wof:placetype":"locality"
},
  "geometry": {"coordinates":[-11.28333,11.61667],"type":"Point"}
}