{
  "type": "Feature",
  "properties": {
    "gn:admin1_code":"K",
    "gn:admin2_code":"32",
    "gn:asciiname":"Fissankoro",
    "gn:country_code":"GN",
    "gn:dem":514,
    "gn:feature_class":"P",
    "gn:feature_code":"PPL",
    "gn:name":"Fissankoro",
    "gn:population":0,
    "gn:timezone":"Africa/Conakry",
    "iso:country":"GN",
    "wof:name":"Fissankoro",
    "wof:placetype":"locality"
},
  "geometry": {"coordinates":[-9.68333,9.58333],"type":"Point"}
}