{
  "type": "Feature",
  "properties": {
    "gn:admin1_code":"F",
    "gn:admin2_code":"17",
    "gn:asciiname":"Kero",
    "gn:country_code":"GN",
    "gn:dem":714,
    "gn:feature_class":"P",
    "gn:feature_code":"PPL",
    "gn:name":"K\u00e9ro",
    "gn:population":0,
    "gn:timezone":"Africa/Conakry",
    "iso:country":"GN",
    "wof:name":"Kero",
    "wof:placetype":"locality"
},
  "geometry": {"coordinates":[-9.79472,8.97583],"type":"Point"}
}