{
  "type": "Feature",
  "properties": {
    "gn:admin1_code":"B",
    "gn:admin2_code":"03",
    "gn:asciiname":"Hore Kouloye",
    "gn:cc2":"GN",
    "gn:country_code":"GN",
    "gn:dem":212,
    "gn:feature_class":"P",
    "gn:feature_code":"PPL",
    "gn:name":"Hor\u00e9 Kouloye",
    "gn:population":0,
    "gn:timezone":"Africa/Conakry",
    "iso:country":"GN",
    "name:und_x_variant":[
        "Kouloye",
        "Hor\u00e9 Kouloye"
    ],
    "wof:name":"Hore Kouloye",
    "wof:placetype":"locality"
},
  "geometry": {"coordinates":[-14.13333,11.33333],"type":"Point"}
}