{
  "type": "Feature",
  "properties": {
    "gn:admin1_code":"K",
    "gn:admin2_code":"19",
    "gn:asciiname":"Koumana",
    "gn:country_code":"GN",
    "gn:dem":361,
    "gn:feature_class":"P",
    "gn:feature_code":"PPL",
    "gn:name":"Koumana",
    "gn:population":0,
    "gn:timezone":"Africa/Conakry",
    "iso:country":"GN",
    "wof:name":"Koumana",
    "wof:placetype":"locality"
},
  "geometry": {"coordinates":[-9.66667,10.68333],"type":"Point"}
}