{
  "type": "Feature",
  "properties": {
    "gn:admin1_code":"D",
    "gn:admin2_code":"16",
    "gn:asciiname":"Sougeta",
    "gn:cc2":"GN",
    "gn:country_code":"GN",
    "gn:dem":301,
    "gn:feature_class":"P",
    "gn:feature_code":"PPL",
    "gn:name":"Soug\u00e9ta",
    "gn:population":0,
    "gn:timezone":"Africa/Conakry",
    "iso:country":"GN",
    "name:und_x_variant":[
        "Sougu\u00e9ta",
        "Soug\u00e9ta"
    ],
    "wof:name":"Sougeta",
    "wof:placetype":"locality"
},
  "geometry": {"coordinates":[-12.53333,10.15],"type":"Point"}
}