{
  "type": "Feature",
  "properties": {
    "gn:admin1_code":"N",
    "gn:admin2_code":"21",
    "gn:asciiname":"Sobaou",
    "gn:cc2":"GN",
    "gn:country_code":"GN",
    "gn:dem":548,
    "gn:feature_class":"P",
    "gn:feature_code":"PPL",
    "gn:name":"Sobaou",
    "gn:population":0,
    "gn:timezone":"Africa/Conakry",
    "iso:country":"GN",
    "name:und_x_variant":[
        "Sabaou",
        "Sobaou"
    ],
    "wof:name":"Sobaou",
    "wof:placetype":"locality"
},
  "geometry": {"coordinates":[-9.75833,8.6175],"type":"Point"}
}