{
  "type": "Feature",
  "properties": {
    "gn:admin1_code":"N",
    "gn:admin2_code":"13",
    "gn:asciiname":"Songbo",
    "gn:country_code":"GN",
    "gn:dem":678,
    "gn:feature_class":"P",
    "gn:feature_code":"PPL",
    "gn:name":"Songbo",
    "gn:population":0,
    "gn:timezone":"Africa/Conakry",
    "iso:country":"GN",
    "wof:name":"Songbo",
    "wof:placetype":"locality"
},
  "geometry": {"coordinates":[-10.35,8.86667],"type":"Point"}
}