{
  "type": "Feature",
  "properties": {
    "gn:admin1_code":"B",
    "gn:admin2_code":"31",
    "gn:asciiname":"Khonibombo",
    "gn:country_code":"GN",
    "gn:dem":2,
    "gn:feature_class":"P",
    "gn:feature_code":"PPL",
    "gn:name":"Khonibombo",
    "gn:population":0,
    "gn:timezone":"Africa/Conakry",
    "iso:country":"GN",
    "wof:name":"Khonibombo",
    "wof:placetype":"locality"
},
  "geometry": {"coordinates":[-13.76778,9.81167],"type":"Point"}
}