{
  "type": "Feature",
  "properties": {
    "gn:admin1_code":"K",
    "gn:admin2_code":"39",
    "gn:asciiname":"Kofoulani",
    "gn:country_code":"GN",
    "gn:dem":350,
    "gn:feature_class":"P",
    "gn:feature_code":"PPL",
    "gn:name":"Kofoulani",
    "gn:population":0,
    "gn:timezone":"Africa/Conakry",
    "iso:country":"GN",
    "name:und_x_variant":[
        "Kofoula",
        "Kofoulani"
    ],
    "wof:name":"Kofoulani",
    "wof:placetype":"locality"
},
  "geometry": {"coordinates":[-9.25,11.85],"type":"Point"}
}