{
  "type": "Feature",
  "properties": {
    "gn:admin1_code":"N",
    "gn:admin2_code":"38",
    "gn:asciiname":"Oueya",
    "gn:country_code":"GN",
    "gn:dem":428,
    "gn:feature_class":"P",
    "gn:feature_code":"PPL",
    "gn:name":"Oueya",
    "gn:population":0,
    "gn:timezone":"Africa/Conakry",
    "iso:country":"GN",
    "name:und_x_variant":[
        "Ouy\u00e9a",
        "Oueya"
    ],
    "wof:name":"Oueya",
    "wof:placetype":"locality"
},
  "geometry": {"coordinates":[-8.85778,7.90417],"type":"Point"}
}