{
  "type": "Feature",
  "properties": {
    "gn:admin1_code":"D",
    "gn:admin2_code":"27",
    "gn:asciiname":"Kinkin",
    "gn:cc2":"GN",
    "gn:country_code":"GN",
    "gn:dem":440,
    "gn:feature_class":"P",
    "gn:feature_code":"PPL",
    "gn:name":"Kinkin",
    "gn:population":0,
    "gn:timezone":"Africa/Conakry",
    "iso:country":"GN",
    "name:fra_x_preferred":[
        "Kinkin"
    ],
    "name:und_x_variant":[
        "Kinnki"
    ],
    "wof:name":"Kinkin",
    "wof:placetype":"locality"
},
  "geometry": {"coordinates":[-13.58333,11.05],"type":"Point"}
}