{
  "type": "Feature",
  "properties": {
    "gn:admin1_code":"B",
    "gn:admin2_code":"02",
    "gn:asciiname":"Kiribamba",
    "gn:country_code":"GN",
    "gn:dem":66,
    "gn:feature_class":"P",
    "gn:feature_code":"PPL",
    "gn:name":"Kiribamba",
    "gn:population":0,
    "gn:timezone":"Africa/Conakry",
    "iso:country":"GN",
    "wof:name":"Kiribamba",
    "wof:placetype":"locality"
},
  "geometry": {"coordinates":[-14.05,10.46667],"type":"Point"}
}