{
  "type": "Feature",
  "properties": {
    "gn:admin1_code":"B",
    "gn:admin2_code":"12",
    "gn:asciiname":"Kourevel",
    "gn:country_code":"GN",
    "gn:dem":149,
    "gn:feature_class":"P",
    "gn:feature_code":"PPL",
    "gn:name":"Kour\u00e9vel",
    "gn:population":0,
    "gn:timezone":"Africa/Conakry",
    "iso:country":"GN",
    "wof:name":"Kourevel",
    "wof:placetype":"locality"
},
  "geometry": {"coordinates":[-12.8571,12.0158],"type":"Point"}
}