{
  "type": "Feature",
  "properties": {
    "gn:admin1_code":"F",
    "gn:admin2_code":"17",
    "gn:asciiname":"Nonguokoro",
    "gn:cc2":"GN",
    "gn:country_code":"GN",
    "gn:dem":599,
    "gn:feature_class":"P",
    "gn:feature_code":"PPL",
    "gn:name":"Nonguokoro",
    "gn:population":0,
    "gn:timezone":"Africa/Conakry",
    "iso:country":"GN",
    "name:und_x_variant":[
        "Nongouaro",
        "Nonguokoro"
    ],
    "wof:name":"Nonguokoro",
    "wof:placetype":"locality"
},
  "geometry": {"coordinates":[-10.26667,9.16667],"type":"Point"}
}