{
  "type": "Feature",
  "properties": {
    "gn:admin1_code":"K",
    "gn:admin2_code":"37",
    "gn:asciiname":"Kodiaraninda",
    "gn:country_code":"GN",
    "gn:dem":367,
    "gn:feature_class":"P",
    "gn:feature_code":"PPL",
    "gn:name":"Kodiaraninda",
    "gn:population":0,
    "gn:timezone":"Africa/Conakry",
    "iso:country":"GN",
    "wof:name":"Kodiaraninda",
    "wof:placetype":"locality"
},
  "geometry": {"coordinates":[-8.85,11.15],"type":"Point"}
}