{
  "type": "Feature",
  "properties": {
    "gn:admin1_code":"F",
    "gn:admin2_code":"07",
    "gn:asciiname":"Hamdoullaye",
    "gn:country_code":"GN",
    "gn:dem":434,
    "gn:feature_class":"P",
    "gn:feature_code":"PPL",
    "gn:name":"Hamdoullaye",
    "gn:population":0,
    "gn:timezone":"Africa/Conakry",
    "iso:country":"GN",
    "wof:name":"Hamdoullaye",
    "wof:placetype":"locality"
},
  "geometry": {"coordinates":[-10.98333,11.16667],"type":"Point"}
}