{
  "type": "Feature",
  "properties": {
    "gn:admin1_code":"N",
    "gn:admin2_code":"38",
    "gn:asciiname":"Guela",
    "gn:country_code":"GN",
    "gn:dem":459,
    "gn:feature_class":"P",
    "gn:feature_code":"PPL",
    "gn:name":"Guela",
    "gn:population":0,
    "gn:timezone":"Africa/Conakry",
    "iso:country":"GN",
    "name:ceb_x_preferred":[
        "Guela"
    ],
    "name:swe_x_preferred":[
        "Guela"
    ],
    "wof:name":"Guela",
    "wof:placetype":"locality"
},
  "geometry": {"coordinates":[-8.9075,7.80083],"type":"Point"}
}