{
  "type": "Feature",
  "properties": {
    "gn:admin1_code":"N",
    "gn:admin2_code":"38",
    "gn:asciiname":"Gbote",
    "gn:country_code":"GN",
    "gn:dem":492,
    "gn:feature_class":"P",
    "gn:feature_code":"PPL",
    "gn:name":"Gbot\u00e9",
    "gn:population":0,
    "gn:timezone":"Africa/Conakry",
    "iso:country":"GN",
    "wof:name":"Gbote",
    "wof:placetype":"locality"
},
  "geometry": {"coordinates":[-8.73444,7.78639],"type":"Point"}
}