{
  "type": "Feature",
  "properties": {
    "gn:admin1_code":"F",
    "gn:admin2_code":"07",
    "gn:asciiname":"Sourou",
    "gn:country_code":"GN",
    "gn:dem":636,
    "gn:feature_class":"P",
    "gn:feature_code":"PPL",
    "gn:name":"Sourou",
    "gn:population":0,
    "gn:timezone":"Africa/Conakry",
    "iso:country":"GN",
    "name:ceb_x_preferred":[
        "Sourou"
    ],
    "name:deu_x_preferred":[
        "Sourou"
    ],
    "name:fra_x_preferred":[
        "Sourou"
    ],
    "name:swe_x_preferred":[
        "Sourou"
    ],
    "wof:name":"Sourou",
    "wof:placetype":"locality"
},
  "geometry": {"coordinates":[-10.86667,11.75],"type":"Point"}
}