{
  "type": "Feature",
  "properties": {
    "gn:admin1_code":"K",
    "gn:admin2_code":"39",
    "gn:asciiname":"Tombani",
    "gn:country_code":"GN",
    "gn:dem":428,
    "gn:feature_class":"P",
    "gn:feature_code":"PPL",
    "gn:name":"Tombani",
    "gn:population":0,
    "gn:timezone":"Africa/Conakry",
    "iso:country":"GN",
    "wof:name":"Tombani",
    "wof:placetype":"locality"
},
  "geometry": {"coordinates":[-10.13333,11.76667],"type":"Point"}
}