{
  "type": "Feature",
  "properties": {
    "gn:admin1_code":"K",
    "gn:admin2_code":"39",
    "gn:asciiname":"Gueregue",
    "gn:country_code":"GN",
    "gn:dem":422,
    "gn:feature_class":"P",
    "gn:feature_code":"PPL",
    "gn:name":"Gu\u00e9r\u00e9gu\u00e9",
    "gn:population":0,
    "gn:timezone":"Africa/Conakry",
    "iso:country":"GN",
    "wof:name":"Gueregue",
    "wof:placetype":"locality"
},
  "geometry": {"coordinates":[-9.53333,11.15],"type":"Point"}
}