{
  "type": "Feature",
  "properties": {
    "gn:admin1_code":"K",
    "gn:admin2_code":"32",
    "gn:asciiname":"Tere",
    "gn:country_code":"GN",
    "gn:dem":398,
    "gn:feature_class":"P",
    "gn:feature_code":"PPL",
    "gn:name":"T\u00e9r\u00e9",
    "gn:population":0,
    "gn:timezone":"Africa/Conakry",
    "iso:country":"GN",
    "wof:name":"Tere",
    "wof:placetype":"locality"
},
  "geometry": {"coordinates":[-8.86667,9.88333],"type":"Point"}
}