{
  "type": "Feature",
  "properties": {
    "gn:admin1_code":"F",
    "gn:admin2_code":"17",
    "gn:asciiname":"Mansoundou",
    "gn:cc2":"GN",
    "gn:country_code":"GN",
    "gn:dem":572,
    "gn:feature_class":"P",
    "gn:feature_code":"PPL",
    "gn:name":"Mansoundou",
    "gn:population":0,
    "gn:timezone":"Africa/Conakry",
    "iso:country":"GN",
    "name:und_x_variant":[
        "Mansandou",
        "Mansoundou"
    ],
    "wof:name":"Mansoundou",
    "wof:placetype":"locality"
},
  "geometry": {"coordinates":[-10.41667,9.18333],"type":"Point"}
}