{
  "type": "Feature",
  "properties": {
    "gn:admin1_code":"N",
    "gn:admin2_code":"13",
    "gn:asciiname":"Fongolo",
    "gn:country_code":"GN",
    "gn:dem":451,
    "gn:feature_class":"P",
    "gn:feature_code":"PPL",
    "gn:name":"Fongolo",
    "gn:population":0,
    "gn:timezone":"Africa/Conakry",
    "iso:country":"GN",
    "wof:name":"Fongolo",
    "wof:placetype":"locality"
},
  "geometry": {"coordinates":[-10.39556,8.75611],"type":"Point"}
}