{
  "type": "Feature",
  "properties": {
    "gn:admin1_code":"L",
    "gn:admin2_code":"28",
    "gn:asciiname":"Ndire",
    "gn:country_code":"GN",
    "gn:dem":807,
    "gn:feature_class":"P",
    "gn:feature_code":"PPL",
    "gn:name":"Ndir\u00e9",
    "gn:population":0,
    "gn:timezone":"Africa/Conakry",
    "iso:country":"GN",
    "wof:name":"Ndire",
    "wof:placetype":"locality"
},
  "geometry": {"coordinates":[-11.73333,11.05],"type":"Point"}
}