{
  "type": "Feature",
  "properties": {
    "gn:admin1_code":"F",
    "gn:admin2_code":"07",
    "gn:asciiname":"Aynde",
    "gn:country_code":"GN",
    "gn:dem":419,
    "gn:feature_class":"P",
    "gn:feature_code":"PPL",
    "gn:name":"Aynd\u00e9",
    "gn:population":0,
    "gn:timezone":"Africa/Conakry",
    "iso:country":"GN",
    "wof:name":"Aynde",
    "wof:placetype":"locality"
},
  "geometry": {"coordinates":[-10.41667,11.83333],"type":"Point"}
}