{
  "type": "Feature",
  "properties": {
    "gn:admin1_code":"M",
    "gn:admin2_code":"06",
    "gn:asciiname":"Ore Dioli",
    "gn:country_code":"GN",
    "gn:dem":1100,
    "gn:feature_class":"P",
    "gn:feature_code":"PPL",
    "gn:name":"Or\u00e9 Dioli",
    "gn:population":0,
    "gn:timezone":"Africa/Conakry",
    "iso:country":"GN",
    "wof:name":"Ore Dioli",
    "wof:placetype":"locality"
},
  "geometry": {"coordinates":[-12.33333,10.65],"type":"Point"}
}