{
  "type": "Feature",
  "properties": {
    "gn:admin1_code":"B",
    "gn:admin2_code":"02",
    "gn:asciiname":"Koliya",
    "gn:cc2":"GN",
    "gn:country_code":"GN",
    "gn:dem":96,
    "gn:feature_class":"P",
    "gn:feature_code":"PPL",
    "gn:name":"Koliya",
    "gn:population":0,
    "gn:timezone":"Africa/Conakry",
    "iso:country":"GN",
    "name:hin_x_preferred":[
        "\u0915\u094b\u0932\u0940\u092f"
    ],
    "name:hun_x_preferred":[
        "K\u00f3lij\u00e1k"
    ],
    "name:tam_x_preferred":[
        "\u0b95\u0bcb\u0bb2\u0bbf\u0baf\u0bb0\u0bcd"
    ],
    "name:und_x_variant":[
        "Kolia"
    ],
    "name:vie_x_preferred":[
        "Koliya"
    ],
    "wof:name":"Koliya",
    "wof:placetype":"locality"
},
  "geometry": {"coordinates":[-14.06667,10.41667],"type":"Point"}
}