{
  "type": "Feature",
  "properties": {
    "gn:admin1_code":"B",
    "gn:admin2_code":"02",
    "gn:asciiname":"Koliya",
    "gn:cc2":"GN",
    "gn:country_code":"GN",
    "gn:dem":96,
    "gn:feature_class":"P",
    "gn:feature_code":"PPL",
    "gn:name":"Koliya",
    "gn:population":0,
    "gn:timezone":"Africa/Conakry",
    "iso:country":"GN",
    "name:und_x_variant":[
        "Kolia",
        "Koliya"
    ],
    "wof:name":"Koliya",
    "wof:placetype":"locality"
},
  "geometry": {"coordinates":[-14.06667,10.41667],"type":"Point"}
}