{
  "type": "Feature",
  "properties": {
    "gn:admin1_code":"N",
    "gn:admin2_code":"01",
    "gn:asciiname":"Fouama",
    "gn:country_code":"GN",
    "gn:dem":575,
    "gn:feature_class":"P",
    "gn:feature_code":"PPL",
    "gn:name":"Fouama",
    "gn:population":0,
    "gn:timezone":"Africa/Conakry",
    "iso:country":"GN",
    "wof:name":"Fouama",
    "wof:placetype":"locality"
},
  "geometry": {"coordinates":[-8.83333,8.35],"type":"Point"}
}