{
  "type": "Feature",
  "properties": {
    "gn:admin1_code":"D",
    "gn:admin2_code":"16",
    "gn:asciiname":"Komoya",
    "gn:country_code":"GN",
    "gn:dem":398,
    "gn:feature_class":"P",
    "gn:feature_code":"PPL",
    "gn:name":"Komoya",
    "gn:population":0,
    "gn:timezone":"Africa/Conakry",
    "iso:country":"GN",
    "wof:name":"Komoya",
    "wof:placetype":"locality"
},
  "geometry": {"coordinates":[-13.03333,10.05],"type":"Point"}
}