{
  "type": "Feature",
  "properties": {
    "gn:admin1_code":"K",
    "gn:admin2_code":"39",
    "gn:asciiname":"Doubaya",
    "gn:country_code":"GN",
    "gn:dem":383,
    "gn:feature_class":"P",
    "gn:feature_code":"PPL",
    "gn:name":"Doubaya",
    "gn:population":0,
    "gn:timezone":"Africa/Conakry",
    "iso:country":"GN",
    "wof:name":"Doubaya",
    "wof:placetype":"locality"
},
  "geometry": {"coordinates":[-9.78333,11.73333],"type":"Point"}
}