{
  "type": "Feature",
  "properties": {
    "gn:admin1_code":"F",
    "gn:admin2_code":"17",
    "gn:asciiname":"Mansonian",
    "gn:country_code":"GN",
    "gn:dem":587,
    "gn:feature_class":"P",
    "gn:feature_code":"PPL",
    "gn:name":"Mansonian",
    "gn:population":0,
    "gn:timezone":"Africa/Conakry",
    "iso:country":"GN",
    "wof:name":"Mansonian",
    "wof:placetype":"locality"
},
  "geometry": {"coordinates":[-10.38333,9.21667],"type":"Point"}
}