{
  "type": "Feature",
  "properties": {
    "gn:admin1_code":"F",
    "gn:admin2_code":"07",
    "gn:asciiname":"Kerela",
    "gn:country_code":"GN",
    "gn:dem":411,
    "gn:feature_class":"P",
    "gn:feature_code":"PPL",
    "gn:name":"K\u00e9r\u00e9la",
    "gn:population":0,
    "gn:timezone":"Africa/Conakry",
    "iso:country":"GN",
    "wof:name":"Kerela",
    "wof:placetype":"locality"
},
  "geometry": {"coordinates":[-10.88333,11.36667],"type":"Point"}
}