{
  "type": "Feature",
  "properties": {
    "gn:admin1_code":"F",
    "gn:admin2_code":"17",
    "gn:asciiname":"Lingbirinkoro",
    "gn:country_code":"GN",
    "gn:dem":509,
    "gn:feature_class":"P",
    "gn:feature_code":"PPL",
    "gn:name":"Lingbirinkoro",
    "gn:population":0,
    "gn:timezone":"Africa/Conakry",
    "iso:country":"GN",
    "wof:name":"Lingbirinkoro",
    "wof:placetype":"locality"
},
  "geometry": {"coordinates":[-9.91667,9.41667],"type":"Point"}
}