{
  "type": "Feature",
  "properties": {
    "gn:admin1_code":"D",
    "gn:admin2_code":"16",
    "gn:asciiname":"Lansanya",
    "gn:cc2":"GN",
    "gn:country_code":"GN",
    "gn:dem":521,
    "gn:feature_class":"P",
    "gn:feature_code":"PPL",
    "gn:name":"Lansanya",
    "gn:population":0,
    "gn:timezone":"Africa/Conakry",
    "iso:country":"GN",
    "name:ita_x_preferred":[
        "Lansanya"
    ],
    "name:msa_x_preferred":[
        "Lansanya"
    ],
    "name:spa_x_preferred":[
        "Lansanya"
    ],
    "name:und_x_variant":[
        "Lans\u00e9nia",
        "Lansanya"
    ],
    "name:urd_x_preferred":[
        "\u0644\u0627\u0646\u0633\u0627\u0646\u06cc\u0627"
    ],
    "wof:name":"Lansanya",
    "wof:placetype":"locality"
},
  "geometry": {"coordinates":[-12.18333,10.08333],"type":"Point"}
}