{
  "type": "Feature",
  "properties": {
    "gn:admin1_code":"K",
    "gn:admin2_code":"39",
    "gn:asciiname":"Fadougou",
    "gn:country_code":"GN",
    "gn:dem":348,
    "gn:feature_class":"P",
    "gn:feature_code":"PPL",
    "gn:name":"Fadougou",
    "gn:population":0,
    "gn:timezone":"Africa/Conakry",
    "iso:country":"GN",
    "wof:name":"Fadougou",
    "wof:placetype":"locality"
},
  "geometry": {"coordinates":[-9.36667,11.73333],"type":"Point"}
}