{
  "type": "Feature",
  "properties": {
    "gn:admin1_code":"N",
    "gn:admin2_code":"13",
    "gn:asciiname":"Yomadou",
    "gn:country_code":"GN",
    "gn:dem":460,
    "gn:feature_class":"P",
    "gn:feature_code":"PPL",
    "gn:name":"Yomadou",
    "gn:population":0,
    "gn:timezone":"Africa/Conakry",
    "iso:country":"GN",
    "wof:name":"Yomadou",
    "wof:placetype":"locality"
},
  "geometry": {"coordinates":[-10.09083,8.62722],"type":"Point"}
}