{
  "type": "Feature",
  "properties": {
    "gn:admin1_code":"04",
    "gn:asciiname":"Sonike",
    "gn:country_code":"GN",
    "gn:dem":17,
    "gn:feature_class":"P",
    "gn:feature_code":"PPL",
    "gn:name":"Sonik\u00e9",
    "gn:population":0,
    "gn:timezone":"Africa/Conakry",
    "iso:country":"GN",
    "wof:name":"Sonike",
    "wof:placetype":"locality"
},
  "geometry": {"coordinates":[-13.60444,9.58556],"type":"Point"}
}