{
  "type": "Feature",
  "properties": {
    "gn:admin1_code":"K",
    "gn:admin2_code":"32",
    "gn:asciiname":"Ouloukoro",
    "gn:country_code":"GN",
    "gn:dem":488,
    "gn:feature_class":"P",
    "gn:feature_code":"PPL",
    "gn:name":"Ouloukoro",
    "gn:population":0,
    "gn:timezone":"Africa/Conakry",
    "iso:country":"GN",
    "name:und_x_variant":[
        "Oulicoro",
        "Oulikoro",
        "Ouloukoro"
    ],
    "wof:name":"Ouloukoro",
    "wof:placetype":"locality"
},
  "geometry": {"coordinates":[-9.41667,9.65],"type":"Point"}
}