{
  "type": "Feature",
  "properties": {
    "gn:admin1_code":"N",
    "gn:admin2_code":"13",
    "gn:asciiname":"Beressa",
    "gn:country_code":"GN",
    "gn:dem":385,
    "gn:feature_class":"P",
    "gn:feature_code":"PPL",
    "gn:name":"Beressa",
    "gn:population":0,
    "gn:timezone":"Africa/Conakry",
    "iso:country":"GN",
    "wof:name":"Beressa",
    "wof:placetype":"locality"
},
  "geometry": {"coordinates":[-10.39083,8.5725],"type":"Point"}
}