{
  "type": "Feature",
  "properties": {
    "gn:admin1_code":"N",
    "gn:admin2_code":"01",
    "gn:asciiname":"Fouala",
    "gn:cc2":"GN",
    "gn:country_code":"GN",
    "gn:dem":689,
    "gn:feature_class":"P",
    "gn:feature_code":"PPL",
    "gn:name":"Fouala",
    "gn:population":0,
    "gn:timezone":"Africa/Conakry",
    "iso:country":"GN",
    "name:ita_x_preferred":[
        "Fouala"
    ],
    "name:msa_x_preferred":[
        "Fouala"
    ],
    "name:spa_x_preferred":[
        "Fouala"
    ],
    "name:und_x_variant":[
        "Foukala"
    ],
    "wof:name":"Fouala",
    "wof:placetype":"locality"
},
  "geometry": {"coordinates":[-8.33333,8.98333],"type":"Point"}
}