{
  "type": "Feature",
  "properties": {
    "gn:admin1_code":"F",
    "gn:admin2_code":"19",
    "gn:asciiname":"Tarounda",
    "gn:country_code":"GN",
    "gn:dem":453,
    "gn:feature_class":"P",
    "gn:feature_code":"PPL",
    "gn:name":"Tarounda",
    "gn:population":0,
    "gn:timezone":"Africa/Conakry",
    "iso:country":"GN",
    "wof:name":"Tarounda",
    "wof:placetype":"locality"
},
  "geometry": {"coordinates":[-10.76667,10.71667],"type":"Point"}
}