{
  "type": "Feature",
  "properties": {
    "gn:admin1_code":"L",
    "gn:admin2_code":"22",
    "gn:asciiname":"Karevi",
    "gn:country_code":"GN",
    "gn:dem":742,
    "gn:feature_class":"P",
    "gn:feature_code":"PPL",
    "gn:name":"Kar\u00e9vi",
    "gn:population":0,
    "gn:timezone":"Africa/Conakry",
    "iso:country":"GN",
    "wof:name":"Karevi",
    "wof:placetype":"locality"
},
  "geometry": {"coordinates":[-12.5847,12.1137],"type":"Point"}
}