{
  "type": "Feature",
  "properties": {
    "gn:admin1_code":"F",
    "gn:admin2_code":"17",
    "gn:asciiname":"Malo",
    "gn:country_code":"GN",
    "gn:dem":483,
    "gn:feature_class":"P",
    "gn:feature_code":"PPL",
    "gn:name":"Malo",
    "gn:population":0,
    "gn:timezone":"Africa/Conakry",
    "iso:country":"GN",
    "name:bul_x_preferred":[
        "\u041c\u0430\u043b\u043e"
    ],
    "name:ceb_x_preferred":[
        "Malo"
    ],
    "name:deu_x_preferred":[
        "Malo"
    ],
    "name:epo_x_preferred":[
        "Malo"
    ],
    "name:eus_x_preferred":[
        "Malo"
    ],
    "name:fin_x_preferred":[
        "Malo"
    ],
    "name:fra_x_preferred":[
        "Malo"
    ],
    "name:glg_x_preferred":[
        "Malo"
    ],
    "name:ind_x_preferred":[
        "Malo"
    ],
    "name:ita_x_preferred":[
        "Malo"
    ],
    "name:nld_x_preferred":[
        "Malo"
    ],
    "name:ron_x_preferred":[
        "Malo"
    ],
    "name:rus_x_preferred":[
        "\u041c\u0430\u043b\u043e"
    ],
    "name:spa_x_preferred":[
        "Malo"
    ],
    "name:swe_x_preferred":[
        "Malo"
    ],
    "wof:name":"Malo",
    "wof:placetype":"locality"
},
  "geometry": {"coordinates":[-10.41667,9.03333],"type":"Point"}
}