{
  "type": "Feature",
  "properties": {
    "gn:admin1_code":"K",
    "gn:admin2_code":"39",
    "gn:asciiname":"Lefarani",
    "gn:country_code":"GN",
    "gn:dem":374,
    "gn:feature_class":"P",
    "gn:feature_code":"PPL",
    "gn:name":"L\u00e9farani",
    "gn:population":0,
    "gn:timezone":"Africa/Conakry",
    "iso:country":"GN",
    "wof:name":"Lefarani",
    "wof:placetype":"locality"
},
  "geometry": {"coordinates":[-8.96667,11.35],"type":"Point"}
}