{
  "type": "Feature",
  "properties": {
    "gn:admin1_code":"B",
    "gn:admin2_code":"02",
    "gn:asciiname":"Maleya",
    "gn:cc2":"GN",
    "gn:country_code":"GN",
    "gn:dem":119,
    "gn:feature_class":"P",
    "gn:feature_code":"PPL",
    "gn:name":"Mal\u00e9ya",
    "gn:population":0,
    "gn:timezone":"Africa/Conakry",
    "iso:country":"GN",
    "name:und_x_variant":[
        "Mal\u00e9a",
        "Mal\u00e9ya"
    ],
    "wof:name":"Maleya",
    "wof:placetype":"locality"
},
  "geometry": {"coordinates":[-14.11667,10.48333],"type":"Point"}
}