{
  "type": "Feature",
  "properties": {
    "gn:admin1_code":"K",
    "gn:admin2_code":"15",
    "gn:asciiname":"Boula Kouninka",
    "gn:country_code":"GN",
    "gn:dem":855,
    "gn:feature_class":"P",
    "gn:feature_code":"PPL",
    "gn:name":"Boula Kouninka",
    "gn:population":0,
    "gn:timezone":"Africa/Conakry",
    "iso:country":"GN",
    "wof:name":"Boula Kouninka",
    "wof:placetype":"locality"
},
  "geometry": {"coordinates":[-9.10556,8.98194],"type":"Point"}
}