{
  "type": "Feature",
  "properties": {
    "gn:admin1_code":"F",
    "gn:admin2_code":"09",
    "gn:asciiname":"Kondeboun Karfa",
    "gn:country_code":"GN",
    "gn:dem":447,
    "gn:feature_class":"P",
    "gn:feature_code":"PPL",
    "gn:name":"Kond\u00e9boun Karfa",
    "gn:population":0,
    "gn:timezone":"Africa/Conakry",
    "iso:country":"GN",
    "wof:name":"Kondeboun Karfa",
    "wof:placetype":"locality"
},
  "geometry": {"coordinates":[-10.78333,10.06667],"type":"Point"}
}