{
  "type": "Feature",
  "properties": {
    "gn:admin1_code":"F",
    "gn:admin2_code":"17",
    "gn:asciiname":"Toli",
    "gn:country_code":"GN",
    "gn:dem":476,
    "gn:feature_class":"P",
    "gn:feature_code":"PPL",
    "gn:name":"Toli",
    "gn:population":0,
    "gn:timezone":"Africa/Conakry",
    "iso:country":"GN",
    "name:ceb_x_preferred":[
        "Toli"
    ],
    "name:deu_x_preferred":[
        "Toli"
    ],
    "name:fra_x_preferred":[
        "Toli"
    ],
    "name:swe_x_preferred":[
        "Toli"
    ],
    "wof:name":"Toli",
    "wof:placetype":"locality"
},
  "geometry": {"coordinates":[-9.98333,8.86667],"type":"Point"}
}