{
  "type": "Feature",
  "properties": {
    "gn:admin1_code":"F",
    "gn:admin2_code":"07",
    "gn:asciiname":"Sobeyabe",
    "gn:country_code":"GN",
    "gn:dem":736,
    "gn:feature_class":"P",
    "gn:feature_code":"PPL",
    "gn:name":"Sob\u00e9yab\u00e9",
    "gn:population":0,
    "gn:timezone":"Africa/Conakry",
    "iso:country":"GN",
    "wof:name":"Sobeyabe",
    "wof:placetype":"locality"
},
  "geometry": {"coordinates":[-10.61667,11.41667],"type":"Point"}
}