{
  "type": "Feature",
  "properties": {
    "gn:admin1_code":"K",
    "gn:admin2_code":"39",
    "gn:asciiname":"Siniandala",
    "gn:country_code":"GN",
    "gn:dem":405,
    "gn:feature_class":"P",
    "gn:feature_code":"PPL",
    "gn:name":"Siniandala",
    "gn:population":0,
    "gn:timezone":"Africa/Conakry",
    "iso:country":"GN",
    "wof:name":"Siniandala",
    "wof:placetype":"locality"
},
  "geometry": {"coordinates":[-9.63333,11.05],"type":"Point"}
}