{
  "type": "Feature",
  "properties": {
    "gn:admin1_code":"D",
    "gn:admin2_code":"16",
    "gn:asciiname":"Molokhoure",
    "gn:country_code":"GN",
    "gn:dem":391,
    "gn:feature_class":"P",
    "gn:feature_code":"PPL",
    "gn:name":"Molokhour\u00e9",
    "gn:population":0,
    "gn:timezone":"Africa/Conakry",
    "iso:country":"GN",
    "wof:name":"Molokhoure",
    "wof:placetype":"locality"
},
  "geometry": {"coordinates":[-13.07889,9.81611],"type":"Point"}
}