{
  "type": "Feature",
  "properties": {
    "gn:admin1_code":"B",
    "gn:admin2_code":"18",
    "gn:asciiname":"Diamel",
    "gn:country_code":"GN",
    "gn:dem":56,
    "gn:feature_class":"P",
    "gn:feature_code":"PPL",
    "gn:name":"Diamel",
    "gn:population":0,
    "gn:timezone":"Africa/Conakry",
    "iso:country":"GN",
    "wof:name":"Diamel",
    "wof:placetype":"locality"
},
  "geometry": {"coordinates":[-13.33333,12.48333],"type":"Point"}
}