{
  "type": "Feature",
  "properties": {
    "gn:admin1_code":"F",
    "gn:admin2_code":"17",
    "gn:asciiname":"Fermessadou",
    "gn:cc2":"GN",
    "gn:country_code":"GN",
    "gn:dem":538,
    "gn:feature_class":"P",
    "gn:feature_code":"PPL",
    "gn:name":"Fermessadou",
    "gn:population":0,
    "gn:timezone":"Africa/Conakry",
    "iso:country":"GN",
    "name:und_x_variant":[
        "Farmassadou",
        "Fermessadou"
    ],
    "wof:name":"Fermessadou",
    "wof:placetype":"locality"
},
  "geometry": {"coordinates":[-10.15,9.13333],"type":"Point"}
}