{
  "type": "Feature",
  "properties": {
    "gn:admin1_code":"F",
    "gn:admin2_code":"09",
    "gn:asciiname":"Kendemele",
    "gn:country_code":"GN",
    "gn:dem":659,
    "gn:feature_class":"P",
    "gn:feature_code":"PPL",
    "gn:name":"Kend\u00e9m\u00e9l\u00e9",
    "gn:population":0,
    "gn:timezone":"Africa/Conakry",
    "iso:country":"GN",
    "wof:name":"Kendemele",
    "wof:placetype":"locality"
},
  "geometry": {"coordinates":[-10.58333,9.11667],"type":"Point"}
}