{
  "type": "Feature",
  "properties": {
    "gn:admin1_code":"D",
    "gn:admin2_code":"10",
    "gn:asciiname":"Konta",
    "gn:cc2":"GN",
    "gn:country_code":"GN",
    "gn:dem":10,
    "gn:feature_class":"P",
    "gn:feature_code":"PPL",
    "gn:name":"Konta",
    "gn:population":0,
    "gn:timezone":"Africa/Conakry",
    "iso:country":"GN",
    "name:und_x_variant":[
        "Conta",
        "Konfa",
        "Confa",
        "Konta"
    ],
    "wof:name":"Konta",
    "wof:placetype":"locality"
},
  "geometry": {"coordinates":[-13.14583,9.17694],"type":"Point"}
}