{
  "type": "Feature",
  "properties": {
    "gn:admin1_code":"N",
    "gn:admin2_code":"29",
    "gn:asciiname":"Galagbaye",
    "gn:cc2":"GN",
    "gn:country_code":"GN",
    "gn:dem":292,
    "gn:feature_class":"P",
    "gn:feature_code":"PPL",
    "gn:name":"Galagbaye",
    "gn:population":0,
    "gn:timezone":"Africa/Conakry",
    "iso:country":"GN",
    "name:und_x_variant":[
        "Galapa\u00ef",
        "Galakpay",
        "Galagbaye"
    ],
    "wof:name":"Galagbaye",
    "wof:placetype":"locality"
},
  "geometry": {"coordinates":[-9.155,7.34917],"type":"Point"}
}