{
  "type": "Feature",
  "properties": {
    "gn:admin1_code":"B",
    "gn:admin2_code":"02",
    "gn:asciiname":"Bakiya",
    "gn:country_code":"GN",
    "gn:dem":21,
    "gn:feature_class":"P",
    "gn:feature_code":"PPL",
    "gn:name":"Bakiya",
    "gn:population":0,
    "gn:timezone":"Africa/Conakry",
    "iso:country":"GN",
    "wof:name":"Bakiya",
    "wof:placetype":"locality"
},
  "geometry": {"coordinates":[-13.81833,9.92889],"type":"Point"}
}