{
  "type": "Feature",
  "properties": {
    "gn:admin1_code":"N",
    "gn:admin2_code":"21",
    "gn:asciiname":"Soukoulala",
    "gn:cc2":"GN",
    "gn:country_code":"GN",
    "gn:dem":597,
    "gn:feature_class":"P",
    "gn:feature_code":"PPL",
    "gn:name":"Soukoulala",
    "gn:population":0,
    "gn:timezone":"Africa/Conakry",
    "iso:country":"GN",
    "name:und_x_variant":[
        "Soukourala",
        "Soukoulala"
    ],
    "wof:name":"Soukoulala",
    "wof:placetype":"locality"
},
  "geometry": {"coordinates":[-9.45417,8.78222],"type":"Point"}
}