{
  "type": "Feature",
  "properties": {
    "gn:admin1_code":"N",
    "gn:admin2_code":"21",
    "gn:asciiname":"Koromai",
    "gn:cc2":"GN",
    "gn:country_code":"GN",
    "gn:dem":641,
    "gn:feature_class":"P",
    "gn:feature_code":"PPL",
    "gn:name":"Koromai",
    "gn:population":0,
    "gn:timezone":"Africa/Conakry",
    "iso:country":"GN",
    "name:und_x_variant":[
        "Kooma\u00ef",
        "Koma\u00ef",
        "Koromai"
    ],
    "wof:name":"Koromai",
    "wof:placetype":"locality"
},
  "geometry": {"coordinates":[-9.6125,8.78722],"type":"Point"}
}