{
  "type": "Feature",
  "properties": {
    "gn:admin1_code":"N",
    "gn:admin2_code":"01",
    "gn:asciiname":"Koyamorodougou",
    "gn:country_code":"GN",
    "gn:dem":549,
    "gn:feature_class":"P",
    "gn:feature_code":"PPL",
    "gn:name":"Koyamorodougou",
    "gn:population":0,
    "gn:timezone":"Africa/Conakry",
    "iso:country":"GN",
    "wof:name":"Koyamorodougou",
    "wof:placetype":"locality"
},
  "geometry": {"coordinates":[-8.23333,8.41667],"type":"Point"}
}