{
  "type": "Feature",
  "properties": {
    "gn:admin1_code":"L",
    "gn:admin2_code":"34",
    "gn:asciiname":"Vendou Feto",
    "gn:country_code":"GN",
    "gn:dem":931,
    "gn:feature_class":"P",
    "gn:feature_code":"PPL",
    "gn:name":"Vendou F\u00e9to",
    "gn:population":0,
    "gn:timezone":"Africa/Conakry",
    "iso:country":"GN",
    "wof:name":"Vendou Feto",
    "wof:placetype":"locality"
},
  "geometry": {"coordinates":[-12.85,11.13333],"type":"Point"}
}