{
  "type": "Feature",
  "properties": {
    "gn:admin1_code":"K",
    "gn:admin2_code":"19",
    "gn:asciiname":"Kelou Kelou Foula",
    "gn:country_code":"GN",
    "gn:dem":384,
    "gn:feature_class":"P",
    "gn:feature_code":"PPL",
    "gn:name":"K\u00e9lou K\u00e9lou Foula",
    "gn:population":0,
    "gn:timezone":"Africa/Conakry",
    "iso:country":"GN",
    "wof:name":"Kelou Kelou Foula",
    "wof:placetype":"locality"
},
  "geometry": {"coordinates":[-10.56667,11.11667],"type":"Point"}
}