{
  "type": "Feature",
  "properties": {
    "gn:admin1_code":"D",
    "gn:admin2_code":"16",
    "gn:asciiname":"Naigaya",
    "gn:cc2":"GN",
    "gn:country_code":"GN",
    "gn:dem":410,
    "gn:feature_class":"P",
    "gn:feature_code":"PPL",
    "gn:name":"Naigaya",
    "gn:population":0,
    "gn:timezone":"Africa/Conakry",
    "iso:country":"GN",
    "name:und_x_variant":[
        "Niagaia",
        "Naigaya"
    ],
    "wof:name":"Naigaya",
    "wof:placetype":"locality"
},
  "geometry": {"coordinates":[-12.28333,9.95],"type":"Point"}
}