{
  "type": "Feature",
  "properties": {
    "gn:admin1_code":"B",
    "gn:admin2_code":"03",
    "gn:asciiname":"Bel-Air",
    "gn:cc2":"GN",
    "gn:country_code":"GN",
    "gn:dem":2,
    "gn:feature_class":"P",
    "gn:feature_code":"PPL",
    "gn:name":"Bel-Air",
    "gn:population":0,
    "gn:timezone":"Africa/Conakry",
    "iso:country":"GN",
    "name:und_x_variant":[
        "Katoukouma",
        "Bel-Air"
    ],
    "wof:name":"Bel-Air",
    "wof:placetype":"locality"
},
  "geometry": {"coordinates":[-14.45,10.88333],"type":"Point"}
}