{
  "type": "Feature",
  "properties": {
    "gn:admin1_code":"K",
    "gn:admin2_code":"39",
    "gn:asciiname":"Goueninko",
    "gn:country_code":"GN",
    "gn:dem":383,
    "gn:feature_class":"P",
    "gn:feature_code":"PPL",
    "gn:name":"Gou\u00e9ninko",
    "gn:population":0,
    "gn:timezone":"Africa/Conakry",
    "iso:country":"GN",
    "wof:name":"Goueninko",
    "wof:placetype":"locality"
},
  "geometry": {"coordinates":[-9.58333,11.45],"type":"Point"}
}