{
  "type": "Feature",
  "properties": {
    "gn:admin1_code":"K",
    "gn:admin2_code":"19",
    "gn:asciiname":"Diala",
    "gn:country_code":"GN",
    "gn:dem":387,
    "gn:feature_class":"P",
    "gn:feature_code":"PPL",
    "gn:name":"Diala",
    "gn:population":0,
    "gn:timezone":"Africa/Conakry",
    "iso:country":"GN",
    "name:ceb_x_preferred":[
        "Diala"
    ],
    "name:swe_x_preferred":[
        "Diala"
    ],
    "name:vie_x_preferred":[
        "Diala"
    ],
    "name:war_x_preferred":[
        "Diala"
    ],
    "name:zho_x_preferred":[
        "\u5929\u87ba\u5c5e"
    ],
    "wof:name":"Diala",
    "wof:placetype":"locality"
},
  "geometry": {"coordinates":[-10.23333,11.16667],"type":"Point"}
}