{
  "type": "Feature",
  "properties": {
    "gn:admin1_code":"F",
    "gn:admin2_code":"09",
    "gn:asciiname":"Gania",
    "gn:country_code":"GN",
    "gn:dem":426,
    "gn:feature_class":"P",
    "gn:feature_code":"PPL",
    "gn:name":"Gania",
    "gn:population":0,
    "gn:timezone":"Africa/Conakry",
    "iso:country":"GN",
    "wof:name":"Gania",
    "wof:placetype":"locality"
},
  "geometry": {"coordinates":[-10.71667,10.56667],"type":"Point"}
}