{
  "type": "Feature",
  "properties": {
    "gn:admin1_code":"D",
    "gn:admin2_code":"16",
    "gn:asciiname":"Tambikhoure",
    "gn:cc2":"GN",
    "gn:country_code":"GN",
    "gn:dem":217,
    "gn:feature_class":"P",
    "gn:feature_code":"PPL",
    "gn:name":"Tambikhour\u00e9",
    "gn:population":0,
    "gn:timezone":"Africa/Conakry",
    "iso:country":"GN",
    "name:und_x_variant":[
        "Tambikour\u00e9",
        "Tambikhour\u00e9"
    ],
    "wof:name":"Tambikhoure",
    "wof:placetype":"locality"
},
  "geometry": {"coordinates":[-13.06667,10.36667],"type":"Point"}
}