{
  "type": "Feature",
  "properties": {
    "gn:admin1_code":"K",
    "gn:admin2_code":"37",
    "gn:asciiname":"Sirimana",
    "gn:country_code":"GN",
    "gn:dem":384,
    "gn:feature_class":"P",
    "gn:feature_code":"PPL",
    "gn:name":"Sirimana",
    "gn:population":0,
    "gn:timezone":"Africa/Conakry",
    "iso:country":"GN",
    "wof:name":"Sirimana",
    "wof:placetype":"locality"
},
  "geometry": {"coordinates":[-8.56667,11.23333],"type":"Point"}
}