{
  "type": "Feature",
  "properties": {
    "gn:admin1_code":"M",
    "gn:admin2_code":"23",
    "gn:asciiname":"Fonio Konkov",
    "gn:cc2":"GN",
    "gn:country_code":"GN",
    "gn:dem":587,
    "gn:feature_class":"P",
    "gn:feature_code":"PPL",
    "gn:name":"Fonio Konkov",
    "gn:population":0,
    "gn:timezone":"Africa/Conakry",
    "iso:country":"GN",
    "name:und_x_variant":[
        "Foniokonko",
        "Fonio Konkov"
    ],
    "wof:name":"Fonio Konkov",
    "wof:placetype":"locality"
},
  "geometry": {"coordinates":[-11.23333,11.08333],"type":"Point"}
}