{
  "type": "Feature",
  "properties": {
    "gn:admin1_code":"K",
    "gn:admin2_code":"39",
    "gn:asciiname":"Madenta",
    "gn:country_code":"GN",
    "gn:dem":401,
    "gn:feature_class":"P",
    "gn:feature_code":"PPL",
    "gn:name":"Madenta",
    "gn:population":0,
    "gn:timezone":"Africa/Conakry",
    "iso:country":"GN",
    "wof:name":"Madenta",
    "wof:placetype":"locality"
},
  "geometry": {"coordinates":[-9.71667,11.36667],"type":"Point"}
}