{
  "type": "Feature",
  "properties": {
    "gn:admin1_code":"B",
    "gn:admin2_code":"02",
    "gn:asciiname":"Wendi",
    "gn:cc2":"GN",
    "gn:country_code":"GN",
    "gn:dem":-1,
    "gn:feature_class":"P",
    "gn:feature_code":"PPL",
    "gn:name":"Wendi",
    "gn:population":0,
    "gn:timezone":"Africa/Conakry",
    "iso:country":"GN",
    "name:deu_x_preferred":[
        "Wendi"
    ],
    "name:fra_x_preferred":[
        "Wendi"
    ],
    "name:ita_x_preferred":[
        "Wendi"
    ],
    "name:pol_x_preferred":[
        "Wendi"
    ],
    "name:und_x_variant":[
        "Ouendi",
        "Wendi"
    ],
    "wof:name":"Wendi",
    "wof:placetype":"locality"
},
  "geometry": {"coordinates":[-13.88694,9.9225],"type":"Point"}
}