{
  "type": "Feature",
  "properties": {
    "gn:admin1_code":"M",
    "gn:admin2_code":"23",
    "gn:asciiname":"Sareboval",
    "gn:country_code":"GN",
    "gn:dem":710,
    "gn:feature_class":"P",
    "gn:feature_code":"PPL",
    "gn:name":"Sar\u00e9boval",
    "gn:population":0,
    "gn:timezone":"Africa/Conakry",
    "iso:country":"GN",
    "wof:name":"Sareboval",
    "wof:placetype":"locality"
},
  "geometry": {"coordinates":[-11.68333,10.66667],"type":"Point"}
}