{
  "type": "Feature",
  "properties": {
    "gn:admin1_code":"F",
    "gn:admin2_code":"07",
    "gn:asciiname":"Fadougou",
    "gn:country_code":"GN",
    "gn:dem":192,
    "gn:feature_class":"P",
    "gn:feature_code":"PPL",
    "gn:name":"Fadougou",
    "gn:population":0,
    "gn:timezone":"Africa/Conakry",
    "iso:country":"GN",
    "wof:name":"Fadougou",
    "wof:placetype":"locality"
},
  "geometry": {"coordinates":[-11.05242,12.11469],"type":"Point"}
}