{
  "type": "Feature",
  "properties": {
    "gn:admin1_code":"L",
    "gn:admin2_code":"33",
    "gn:asciiname":"Tingueladji",
    "gn:country_code":"GN",
    "gn:dem":446,
    "gn:feature_class":"P",
    "gn:feature_code":"PPL",
    "gn:name":"Tingu\u00e9ladji",
    "gn:population":0,
    "gn:timezone":"Africa/Conakry",
    "iso:country":"GN",
    "wof:name":"Tingueladji",
    "wof:placetype":"locality"
},
  "geometry": {"coordinates":[-11.4902,12.12639],"type":"Point"}
}