{
  "type": "Feature",
  "properties": {
    "gn:admin1_code":"N",
    "gn:admin2_code":"29",
    "gn:asciiname":"Diecke",
    "gn:cc2":"GN",
    "gn:country_code":"GN",
    "gn:dem":295,
    "gn:feature_class":"P",
    "gn:feature_code":"PPL",
    "gn:name":"Diecke",
    "gn:population":0,
    "gn:timezone":"Africa/Conakry",
    "iso:country":"GN",
    "name:msa_x_preferred":[
        "Di\u00e9k\u00e9"
    ],
    "name:und_x_variant":[
        "Li\u00e9k\u00e9",
        "Dyeck\u00e9",
        "Dy\u00e9k\u00e9",
        "Dyeckh\u00e9",
        "Diecke"
    ],
    "wof:name":"Diecke",
    "wof:placetype":"locality"
},
  "geometry": {"coordinates":[-8.95417,7.34833],"type":"Point"}
}