{
  "type": "Feature",
  "properties": {
    "gn:admin1_code":"L",
    "gn:admin2_code":"22",
    "gn:asciiname":"Lanbawol",
    "gn:country_code":"GN",
    "gn:dem":763,
    "gn:feature_class":"P",
    "gn:feature_code":"PPL",
    "gn:name":"Lanbawol",
    "gn:population":0,
    "gn:timezone":"Africa/Conakry",
    "iso:country":"GN",
    "wof:name":"Lanbawol",
    "wof:placetype":"locality"
},
  "geometry": {"coordinates":[-12.508,12.0761],"type":"Point"}
}