{
  "type": "Feature",
  "properties": {
    "gn:admin1_code":"B",
    "gn:admin2_code":"18",
    "gn:asciiname":"Banbanguilare",
    "gn:country_code":"GN",
    "gn:dem":142,
    "gn:feature_class":"P",
    "gn:feature_code":"PPL",
    "gn:name":"Banbanguilare",
    "gn:population":0,
    "gn:timezone":"Africa/Conakry",
    "iso:country":"GN",
    "wof:name":"Banbanguilare",
    "wof:placetype":"locality"
},
  "geometry": {"coordinates":[-13.03333,12.03333],"type":"Point"}
}