{
  "type": "Feature",
  "properties": {
    "gn:admin1_code":"M",
    "gn:admin2_code":"07",
    "gn:asciiname":"Kourousansan",
    "gn:country_code":"GN",
    "gn:dem":592,
    "gn:feature_class":"P",
    "gn:feature_code":"PPL",
    "gn:name":"Kourousansan",
    "gn:population":0,
    "gn:timezone":"Africa/Conakry",
    "iso:country":"GN",
    "wof:name":"Kourousansan",
    "wof:placetype":"locality"
},
  "geometry": {"coordinates":[-11.31667,11.05],"type":"Point"}
}