{
  "type": "Feature",
  "properties": {
    "gn:admin1_code":"L",
    "gn:admin2_code":"35",
    "gn:asciiname":"Keneri",
    "gn:country_code":"GN",
    "gn:dem":987,
    "gn:feature_class":"P",
    "gn:feature_code":"PPL",
    "gn:name":"K\u00e9n\u00e9ri",
    "gn:population":0,
    "gn:timezone":"Africa/Conakry",
    "iso:country":"GN",
    "wof:name":"Keneri",
    "wof:placetype":"locality"
},
  "geometry": {"coordinates":[-12.71667,11.43333],"type":"Point"}
}