{
  "type": "Feature",
  "properties": {
    "gn:admin1_code":"B",
    "gn:admin2_code":"02",
    "gn:asciiname":"Katende",
    "gn:cc2":"GN",
    "gn:country_code":"GN",
    "gn:dem":0,
    "gn:feature_class":"P",
    "gn:feature_code":"PPL",
    "gn:name":"Katend\u00e9",
    "gn:population":0,
    "gn:timezone":"Africa/Conakry",
    "iso:country":"GN",
    "name:und_x_variant":[
        "Catea",
        "Katand\u00e9",
        "Catande",
        "Katend\u00e9"
    ],
    "wof:name":"Katende",
    "wof:placetype":"locality"
},
  "geometry": {"coordinates":[-13.93333,10.01667],"type":"Point"}
}