{
  "type": "Feature",
  "properties": {
    "gn:admin1_code":"N",
    "gn:admin2_code":"13",
    "gn:asciiname":"Baoua",
    "gn:country_code":"GN",
    "gn:dem":385,
    "gn:feature_class":"P",
    "gn:feature_code":"PPL",
    "gn:name":"Baoua",
    "gn:population":0,
    "gn:timezone":"Africa/Conakry",
    "iso:country":"GN",
    "wof:name":"Baoua",
    "wof:placetype":"locality"
},
  "geometry": {"coordinates":[-10.43167,8.45],"type":"Point"}
}