{
  "type": "Feature",
  "properties": {
    "gn:admin1_code":"L",
    "gn:admin2_code":"22",
    "gn:asciiname":"Toulelniama",
    "gn:country_code":"GN",
    "gn:dem":905,
    "gn:feature_class":"P",
    "gn:feature_code":"PPL",
    "gn:name":"Toulelniama",
    "gn:population":0,
    "gn:timezone":"Africa/Conakry",
    "iso:country":"GN",
    "wof:name":"Toulelniama",
    "wof:placetype":"locality"
},
  "geometry": {"coordinates":[-12.2352,12.0062],"type":"Point"}
}