{
  "type": "Feature",
  "properties": {
    "gn:admin1_code":"N",
    "gn:admin2_code":"13",
    "gn:asciiname":"Youmale",
    "gn:country_code":"GN",
    "gn:dem":473,
    "gn:feature_class":"P",
    "gn:feature_code":"PPL",
    "gn:name":"Youmal\u00e9",
    "gn:population":0,
    "gn:timezone":"Africa/Conakry",
    "iso:country":"GN",
    "name:eng_x_preferred":[
        "Youmal\u00e9"
    ],
    "wof:name":"Youmale",
    "wof:placetype":"locality"
},
  "geometry": {"coordinates":[-10.55,8.81667],"type":"Point"}
}