{
  "type": "Feature",
  "properties": {
    "gn:admin1_code":"N",
    "gn:admin2_code":"01",
    "gn:asciiname":"Koni",
    "gn:country_code":"GN",
    "gn:dem":567,
    "gn:feature_class":"P",
    "gn:feature_code":"PPL",
    "gn:name":"Koni",
    "gn:population":0,
    "gn:timezone":"Africa/Conakry",
    "iso:country":"GN",
    "wof:name":"Koni",
    "wof:placetype":"locality"
},
  "geometry": {"coordinates":[-8.91667,8.21667],"type":"Point"}
}