{
  "type": "Feature",
  "properties": {
    "gn:admin1_code":"N",
    "gn:admin2_code":"01",
    "gn:asciiname":"Koni",
    "gn:country_code":"GN",
    "gn:dem":567,
    "gn:feature_class":"P",
    "gn:feature_code":"PPL",
    "gn:name":"Koni",
    "gn:population":0,
    "gn:timezone":"Africa/Conakry",
    "iso:country":"GN",
    "name:aka_x_preferred":[
        "Koni"
    ],
    "name:ceb_x_preferred":[
        "Koni"
    ],
    "name:deu_x_preferred":[
        "Koni"
    ],
    "name:est_x_preferred":[
        "Koni"
    ],
    "name:fra_x_preferred":[
        "Koni"
    ],
    "name:kat_x_preferred":[
        "\u10d9\u10dd\u10dc\u10d8"
    ],
    "name:rus_x_preferred":[
        "\u041a\u043e\u043d\u0438"
    ],
    "name:srp_x_preferred":[
        "\u041a\u043e\u043d\u0438"
    ],
    "name:swe_x_preferred":[
        "Koni"
    ],
    "wof:name":"Koni",
    "wof:placetype":"locality"
},
  "geometry": {"coordinates":[-8.91667,8.21667],"type":"Point"}
}