{
  "type": "Feature",
  "properties": {
    "gn:admin1_code":"F",
    "gn:admin2_code":"17",
    "gn:asciiname":"Beledou Kamadou",
    "gn:country_code":"GN",
    "gn:dem":521,
    "gn:feature_class":"P",
    "gn:feature_code":"PPL",
    "gn:name":"B\u00e9l\u00e9dou Kamadou",
    "gn:population":0,
    "gn:timezone":"Africa/Conakry",
    "iso:country":"GN",
    "wof:name":"Beledou Kamadou",
    "wof:placetype":"locality"
},
  "geometry": {"coordinates":[-9.88333,9.28333],"type":"Point"}
}