{
  "type": "Feature",
  "properties": {
    "gn:admin1_code":"F",
    "gn:admin2_code":"07",
    "gn:asciiname":"Douga",
    "gn:country_code":"GN",
    "gn:dem":628,
    "gn:feature_class":"P",
    "gn:feature_code":"PPL",
    "gn:name":"Douga",
    "gn:population":0,
    "gn:timezone":"Africa/Conakry",
    "iso:country":"GN",
    "wof:name":"Douga",
    "wof:placetype":"locality"
},
  "geometry": {"coordinates":[-10.25,12.03333],"type":"Point"}
}