{
  "type": "Feature",
  "properties": {
    "gn:admin1_code":"N",
    "gn:admin2_code":"21",
    "gn:asciiname":"Ndeleou",
    "gn:cc2":"GN",
    "gn:country_code":"GN",
    "gn:dem":576,
    "gn:feature_class":"P",
    "gn:feature_code":"PPL",
    "gn:name":"Nd\u00e9l\u00e9ou",
    "gn:population":0,
    "gn:timezone":"Africa/Conakry",
    "iso:country":"GN",
    "name:und_x_variant":[
        "N\u2019D\u00e9r\u00e9ou",
        "Nd\u00e9l\u00e9ou"
    ],
    "wof:name":"Ndeleou",
    "wof:placetype":"locality"
},
  "geometry": {"coordinates":[-9.69667,8.505],"type":"Point"}
}