{
  "type": "Feature",
  "properties": {
    "gn:admin1_code":"F",
    "gn:admin2_code":"07",
    "gn:asciiname":"Pelloye",
    "gn:country_code":"GN",
    "gn:dem":435,
    "gn:feature_class":"P",
    "gn:feature_code":"PPL",
    "gn:name":"Pelloye",
    "gn:population":0,
    "gn:timezone":"Africa/Conakry",
    "iso:country":"GN",
    "wof:name":"Pelloye",
    "wof:placetype":"locality"
},
  "geometry": {"coordinates":[-10.85,11.28333],"type":"Point"}
}