{
  "type": "Feature",
  "properties": {
    "gn:admin1_code":"F",
    "gn:admin2_code":"09",
    "gn:asciiname":"Gbiri Doula",
    "gn:country_code":"GN",
    "gn:dem":454,
    "gn:feature_class":"P",
    "gn:feature_code":"PPL",
    "gn:name":"Gbiri Doula",
    "gn:population":0,
    "gn:timezone":"Africa/Conakry",
    "iso:country":"GN",
    "wof:name":"Gbiri Doula",
    "wof:placetype":"locality"
},
  "geometry": {"coordinates":[-10.91667,9.86667],"type":"Point"}
}