{
  "type": "Feature",
  "properties": {
    "gn:admin1_code":"B",
    "gn:admin2_code":"03",
    "gn:asciiname":"Katongourou",
    "gn:cc2":"GN",
    "gn:country_code":"GN",
    "gn:dem":10,
    "gn:feature_class":"P",
    "gn:feature_code":"PPL",
    "gn:name":"Katongourou",
    "gn:population":0,
    "gn:timezone":"Africa/Conakry",
    "iso:country":"GN",
    "name:und_x_variant":[
        "Katongu\u00e9ron",
        "Katongu\u00e9ro",
        "Katongoro",
        "Katongourou"
    ],
    "wof:name":"Katongourou",
    "wof:placetype":"locality"
},
  "geometry": {"coordinates":[-14.48333,10.66667],"type":"Point"}
}