{
  "type": "Feature",
  "properties": {
    "gn:admin1_code":"F",
    "gn:admin2_code":"17",
    "gn:asciiname":"Kongodou",
    "gn:country_code":"GN",
    "gn:dem":546,
    "gn:feature_class":"P",
    "gn:feature_code":"PPL",
    "gn:name":"Kongodou",
    "gn:population":0,
    "gn:timezone":"Africa/Conakry",
    "iso:country":"GN",
    "wof:name":"Kongodou",
    "wof:placetype":"locality"
},
  "geometry": {"coordinates":[-10.06667,8.95],"type":"Point"}
}