{
  "type": "Feature",
  "properties": {
    "gn:admin1_code":"N",
    "gn:admin2_code":"38",
    "gn:asciiname":"Kouenala",
    "gn:country_code":"GN",
    "gn:dem":467,
    "gn:feature_class":"P",
    "gn:feature_code":"PPL",
    "gn:name":"Kouenala",
    "gn:population":0,
    "gn:timezone":"Africa/Conakry",
    "iso:country":"GN",
    "name:und_x_variant":[
        "Kon\u00e9ba",
        "Konala",
        "Kouenala"
    ],
    "wof:name":"Kouenala",
    "wof:placetype":"locality"
},
  "geometry": {"coordinates":[-8.91778,7.79056],"type":"Point"}
}