{
  "type": "Feature",
  "properties": {
    "gn:admin1_code":"N",
    "gn:admin2_code":"13",
    "gn:asciiname":"Kendou",
    "gn:country_code":"GN",
    "gn:dem":359,
    "gn:feature_class":"P",
    "gn:feature_code":"PPL",
    "gn:name":"Kendou",
    "gn:population":0,
    "gn:timezone":"Africa/Conakry",
    "iso:country":"GN",
    "wof:name":"Kendou",
    "wof:placetype":"locality"
},
  "geometry": {"coordinates":[-10.36667,8.53333],"type":"Point"}
}