{
  "type": "Feature",
  "properties": {
    "gn:admin1_code":"K",
    "gn:admin2_code":"37",
    "gn:asciiname":"Kama",
    "gn:country_code":"GN",
    "gn:dem":351,
    "gn:feature_class":"P",
    "gn:feature_code":"PPL",
    "gn:name":"Kama",
    "gn:population":0,
    "gn:timezone":"Africa/Conakry",
    "iso:country":"GN",
    "name:und_x_variant":[
        "Kamaro",
        "Kama"
    ],
    "wof:name":"Kama",
    "wof:placetype":"locality"
},
  "geometry": {"coordinates":[-8.56667,11.18333],"type":"Point"}
}