{
  "type": "Feature",
  "properties": {
    "gn:admin1_code":"L",
    "gn:admin2_code":"22",
    "gn:asciiname":"Touba",
    "gn:country_code":"GN",
    "gn:dem":139,
    "gn:feature_class":"P",
    "gn:feature_code":"PPL",
    "gn:name":"Touba",
    "gn:population":0,
    "gn:timezone":"Africa/Conakry",
    "iso:country":"GN",
    "wof:name":"Touba",
    "wof:placetype":"locality"
},
  "geometry": {"coordinates":[-12.6588,12.186],"type":"Point"}
}