{
  "type": "Feature",
  "properties": {
    "gn:admin1_code":"K",
    "gn:admin2_code":"15",
    "gn:asciiname":"Forono",
    "gn:country_code":"GN",
    "gn:dem":612,
    "gn:feature_class":"P",
    "gn:feature_code":"PPL",
    "gn:name":"Forono",
    "gn:population":0,
    "gn:timezone":"Africa/Conakry",
    "iso:country":"GN",
    "name:und_x_variant":[
        "Farano",
        "Forono"
    ],
    "wof:name":"Forono",
    "wof:placetype":"locality"
},
  "geometry": {"coordinates":[-8.68333,9.43333],"type":"Point"}
}