{
  "type": "Feature",
  "properties": {
    "gn:admin1_code":"N",
    "gn:admin2_code":"13",
    "gn:asciiname":"Kongoffi",
    "gn:country_code":"GN",
    "gn:dem":525,
    "gn:feature_class":"P",
    "gn:feature_code":"PPL",
    "gn:name":"Kongoffi",
    "gn:population":0,
    "gn:timezone":"Africa/Conakry",
    "iso:country":"GN",
    "wof:name":"Kongoffi",
    "wof:placetype":"locality"
},
  "geometry": {"coordinates":[-10.24778,8.84417],"type":"Point"}
}