{
  "type": "Feature",
  "properties": {
    "gn:admin1_code":"B",
    "gn:admin2_code":"02",
    "gn:asciiname":"Yaraya",
    "gn:country_code":"GN",
    "gn:dem":19,
    "gn:feature_class":"P",
    "gn:feature_code":"PPL",
    "gn:name":"Yaraya",
    "gn:population":0,
    "gn:timezone":"Africa/Conakry",
    "iso:country":"GN",
    "wof:name":"Yaraya",
    "wof:placetype":"locality"
},
  "geometry": {"coordinates":[-13.83083,9.95222],"type":"Point"}
}