{
  "type": "Feature",
  "properties": {
    "gn:admin1_code":"N",
    "gn:admin2_code":"01",
    "gn:asciiname":"Dialakoro",
    "gn:country_code":"GN",
    "gn:dem":654,
    "gn:feature_class":"P",
    "gn:feature_code":"PPL",
    "gn:name":"Dialakoro",
    "gn:population":0,
    "gn:timezone":"Africa/Conakry",
    "iso:country":"GN",
    "name:fra_x_preferred":[
        "Dialakoro"
    ],
    "name:ita_x_preferred":[
        "Dialakoro"
    ],
    "name:spa_x_preferred":[
        "Dialakoro"
    ],
    "wof:name":"Dialakoro",
    "wof:placetype":"locality"
},
  "geometry": {"coordinates":[-8.48333,8.46667],"type":"Point"}
}