{
  "type": "Feature",
  "properties": {
    "gn:admin1_code":"F",
    "gn:admin2_code":"17",
    "gn:asciiname":"Konda",
    "gn:country_code":"GN",
    "gn:dem":497,
    "gn:feature_class":"P",
    "gn:feature_code":"PPL",
    "gn:name":"Konda",
    "gn:population":0,
    "gn:timezone":"Africa/Conakry",
    "iso:country":"GN",
    "name:ceb_x_preferred":[
        "Konda"
    ],
    "name:deu_x_preferred":[
        "Konda"
    ],
    "name:fra_x_preferred":[
        "Konda"
    ],
    "name:ita_x_preferred":[
        "Konda"
    ],
    "name:swe_x_preferred":[
        "Konda"
    ],
    "wof:name":"Konda",
    "wof:placetype":"locality"
},
  "geometry": {"coordinates":[-9.93917,8.92528],"type":"Point"}
}