{
  "type": "Feature",
  "properties": {
    "gn:admin1_code":"F",
    "gn:admin2_code":"17",
    "gn:asciiname":"Yalankie",
    "gn:country_code":"GN",
    "gn:dem":508,
    "gn:feature_class":"P",
    "gn:feature_code":"PPL",
    "gn:name":"Yalanki\u00e9",
    "gn:population":0,
    "gn:timezone":"Africa/Conakry",
    "iso:country":"GN",
    "wof:name":"Yalankie",
    "wof:placetype":"locality"
},
  "geometry": {"coordinates":[-9.91667,9.23333],"type":"Point"}
}