{
  "type": "Feature",
  "properties": {
    "gn:admin1_code":"F",
    "gn:admin2_code":"09",
    "gn:asciiname":"Balandougou",
    "gn:country_code":"GN",
    "gn:dem":419,
    "gn:feature_class":"P",
    "gn:feature_code":"PPL",
    "gn:name":"Balandougou",
    "gn:population":0,
    "gn:timezone":"Africa/Conakry",
    "iso:country":"GN",
    "wof:name":"Balandougou",
    "wof:placetype":"locality"
},
  "geometry": {"coordinates":[-10.76667,10.26667],"type":"Point"}
}