{
  "type": "Feature",
  "properties": {
    "gn:admin1_code":"N",
    "gn:admin2_code":"21",
    "gn:asciiname":"Simbessou",
    "gn:country_code":"GN",
    "gn:dem":549,
    "gn:feature_class":"P",
    "gn:feature_code":"PPL",
    "gn:name":"Simbessou",
    "gn:population":0,
    "gn:timezone":"Africa/Conakry",
    "iso:country":"GN",
    "wof:name":"Simbessou",
    "wof:placetype":"locality"
},
  "geometry": {"coordinates":[-9.86667,8.66667],"type":"Point"}
}