{
  "type": "Feature",
  "properties": {
    "gn:admin1_code":"N",
    "gn:admin2_code":"13",
    "gn:asciiname":"Boumou",
    "gn:country_code":"GN",
    "gn:dem":503,
    "gn:feature_class":"P",
    "gn:feature_code":"PPL",
    "gn:name":"Boumou",
    "gn:population":0,
    "gn:timezone":"Africa/Conakry",
    "iso:country":"GN",
    "wof:name":"Boumou",
    "wof:placetype":"locality"
},
  "geometry": {"coordinates":[-9.99056,8.65833],"type":"Point"}
}