{
  "type": "Feature",
  "properties": {
    "gn:admin1_code":"K",
    "gn:admin2_code":"17",
    "gn:asciiname":"Soiououleya",
    "gn:country_code":"GN",
    "gn:dem":737,
    "gn:feature_class":"P",
    "gn:feature_code":"PPL",
    "gn:name":"Soiououl\u00e9ya",
    "gn:population":0,
    "gn:timezone":"Africa/Conakry",
    "iso:country":"GN",
    "name:und_x_variant":[
        "Solououl\u00e9ya",
        "Soiououl\u00e9ya"
    ],
    "wof:name":"Soiououleya",
    "wof:placetype":"locality"
},
  "geometry": {"coordinates":[-9.56306,8.8725],"type":"Point"}
}