{
  "type": "Feature",
  "properties": {
    "gn:admin1_code":"L",
    "gn:admin2_code":"22",
    "gn:asciiname":"Bourou",
    "gn:country_code":"GN",
    "gn:dem":785,
    "gn:feature_class":"P",
    "gn:feature_code":"PPL",
    "gn:name":"Bourou",
    "gn:population":0,
    "gn:timezone":"Africa/Conakry",
    "iso:country":"GN",
    "name:azb_x_preferred":[
        "\u0628\u0648\u0631\u0648"
    ],
    "name:ceb_x_preferred":[
        "Bourou"
    ],
    "name:fas_x_preferred":[
        "\u0628\u0648\u0631\u0648"
    ],
    "name:fra_x_preferred":[
        "Bourou"
    ],
    "name:ita_x_preferred":[
        "Bourou"
    ],
    "name:swe_x_preferred":[
        "Bourou"
    ],
    "wof:name":"Bourou",
    "wof:placetype":"locality"
},
  "geometry": {"coordinates":[-12.5553,12.0681],"type":"Point"}
}