{
  "type": "Feature",
  "properties": {
    "gn:admin1_code":"L",
    "gn:admin2_code":"22",
    "gn:asciiname":"Tountoue",
    "gn:country_code":"GN",
    "gn:dem":1219,
    "gn:feature_class":"P",
    "gn:feature_code":"PPL",
    "gn:name":"Tountou\u00e9",
    "gn:population":0,
    "gn:timezone":"Africa/Conakry",
    "iso:country":"GN",
    "wof:name":"Tountoue",
    "wof:placetype":"locality"
},
  "geometry": {"coordinates":[-12.2816,12.0164],"type":"Point"}
}