{
  "type": "Feature",
  "properties": {
    "gn:admin1_code":"D",
    "gn:admin2_code":"10",
    "gn:asciiname":"Sinaya",
    "gn:country_code":"GN",
    "gn:dem":71,
    "gn:feature_class":"P",
    "gn:feature_code":"PPL",
    "gn:name":"Sinaya",
    "gn:population":0,
    "gn:timezone":"Africa/Conakry",
    "iso:country":"GN",
    "wof:name":"Sinaya",
    "wof:placetype":"locality"
},
  "geometry": {"coordinates":[-12.68333,9.48333],"type":"Point"}
}