{
  "type": "Feature",
  "properties": {
    "gn:admin1_code":"K",
    "gn:admin2_code":"19",
    "gn:asciiname":"Soronkoni",
    "gn:country_code":"GN",
    "gn:dem":413,
    "gn:feature_class":"P",
    "gn:feature_code":"PPL",
    "gn:name":"Soronkoni",
    "gn:population":0,
    "gn:timezone":"Africa/Conakry",
    "iso:country":"GN",
    "wof:name":"Soronkoni",
    "wof:placetype":"locality"
},
  "geometry": {"coordinates":[-9.63333,10.53333],"type":"Point"}
}