{
  "type": "Feature",
  "properties": {
    "gn:admin1_code":"M",
    "gn:admin2_code":"25",
    "gn:asciiname":"Mango",
    "gn:country_code":"GN",
    "gn:dem":855,
    "gn:feature_class":"P",
    "gn:feature_code":"PPL",
    "gn:name":"Mango",
    "gn:population":0,
    "gn:timezone":"Africa/Conakry",
    "iso:country":"GN",
    "wof:name":"Mango",
    "wof:placetype":"locality"
},
  "geometry": {"coordinates":[-12.55,10.98333],"type":"Point"}
}