{
  "type": "Feature",
  "properties": {
    "gn:admin1_code":"K",
    "gn:admin2_code":"19",
    "gn:asciiname":"Bogo Oule",
    "gn:country_code":"GN",
    "gn:dem":430,
    "gn:feature_class":"P",
    "gn:feature_code":"PPL",
    "gn:name":"Bogo Oul\u00e9",
    "gn:population":0,
    "gn:timezone":"Africa/Conakry",
    "iso:country":"GN",
    "wof:name":"Bogo Oule",
    "wof:placetype":"locality"
},
  "geometry": {"coordinates":[-9.95,11.03333],"type":"Point"}
}