{
  "type": "Feature",
  "properties": {
    "gn:admin1_code":"M",
    "gn:admin2_code":"06",
    "gn:asciiname":"Pennou",
    "gn:cc2":"GN",
    "gn:country_code":"GN",
    "gn:dem":746,
    "gn:feature_class":"P",
    "gn:feature_code":"PPL",
    "gn:name":"Pennou",
    "gn:population":0,
    "gn:timezone":"Africa/Conakry",
    "iso:country":"GN",
    "name:und_x_variant":[
        "Penoux",
        "Penou",
        "Pennou"
    ],
    "wof:name":"Pennou",
    "wof:placetype":"locality"
},
  "geometry": {"coordinates":[-11.81667,10.95],"type":"Point"}
}