{
  "type": "Feature",
  "properties": {
    "gn:admin1_code":"B",
    "gn:admin2_code":"12",
    "gn:asciiname":"Nialama",
    "gn:country_code":"GN",
    "gn:dem":215,
    "gn:feature_class":"P",
    "gn:feature_code":"PPL",
    "gn:name":"Nialama",
    "gn:population":0,
    "gn:timezone":"Africa/Conakry",
    "iso:country":"GN",
    "wof:name":"Nialama",
    "wof:placetype":"locality"
},
  "geometry": {"coordinates":[-12.78333,11.85],"type":"Point"}
}