{
  "type": "Feature",
  "properties": {
    "gn:admin1_code":"K",
    "gn:admin2_code":"07",
    "gn:asciiname":"Tomba",
    "gn:country_code":"GN",
    "gn:dem":386,
    "gn:feature_class":"P",
    "gn:feature_code":"PPL",
    "gn:name":"Tomba",
    "gn:population":0,
    "gn:timezone":"Africa/Conakry",
    "iso:country":"GN",
    "name:cat_x_preferred":[
        "Tomba"
    ],
    "name:ceb_x_preferred":[
        "Tomba"
    ],
    "name:ces_x_preferred":[
        "Tomba"
    ],
    "name:eng_x_preferred":[
        "Tomba Kobila"
    ],
    "name:eng_x_variant":[
        "Tomba"
    ],
    "name:fin_x_preferred":[
        "Tomba"
    ],
    "name:fra_x_preferred":[
        "Tomba"
    ],
    "name:ita_x_preferred":[
        "Tomba"
    ],
    "name:jpn_x_preferred":[
        "\u30c8\u30f3\u30d0"
    ],
    "name:por_x_preferred":[
        "Tomba"
    ],
    "name:ron_x_preferred":[
        "Tomba"
    ],
    "name:srp_x_preferred":[
        "Tomba"
    ],
    "name:swe_x_preferred":[
        "Tomba"
    ],
    "wof:name":"Tomba Kobila",
    "wof:placetype":"locality"
},
  "geometry": {"coordinates":[-10.21667,11.73333],"type":"Point"}
}