{
  "type": "Feature",
  "properties": {
    "gn:admin1_code":"L",
    "gn:admin2_code":"34",
    "gn:asciiname":"Gouba",
    "gn:country_code":"GN",
    "gn:dem":818,
    "gn:feature_class":"P",
    "gn:feature_code":"PPL",
    "gn:name":"Gouba",
    "gn:population":0,
    "gn:timezone":"Africa/Conakry",
    "iso:country":"GN",
    "wof:name":"Gouba",
    "wof:placetype":"locality"
},
  "geometry": {"coordinates":[-12.21667,11.45],"type":"Point"}
}