{
  "type": "Feature",
  "properties": {
    "gn:admin1_code":"D",
    "gn:admin2_code":"16",
    "gn:asciiname":"Kante",
    "gn:country_code":"GN",
    "gn:dem":365,
    "gn:feature_class":"P",
    "gn:feature_code":"PPL",
    "gn:name":"Kant\u00e9",
    "gn:population":0,
    "gn:timezone":"Africa/Conakry",
    "iso:country":"GN",
    "name:ceb_x_preferred":[
        "Kante"
    ],
    "name:deu_x_preferred":[
        "Kante"
    ],
    "name:nds_x_preferred":[
        "Kante"
    ],
    "name:rus_x_preferred":[
        "\u041a\u0430\u043d\u0442\u0435"
    ],
    "name:swe_x_preferred":[
        "Kante"
    ],
    "name:ukr_x_preferred":[
        "\u041a\u0430\u043d\u0442\u0435"
    ],
    "wof:name":"Kante",
    "wof:placetype":"locality"
},
  "geometry": {"coordinates":[-13.05,10.01667],"type":"Point"}
}