{
  "type": "Feature",
  "properties": {
    "gn:admin1_code":"K",
    "gn:admin2_code":"15",
    "gn:asciiname":"Diraya",
    "gn:cc2":"GN",
    "gn:country_code":"GN",
    "gn:dem":541,
    "gn:feature_class":"P",
    "gn:feature_code":"PPL",
    "gn:name":"Diraya",
    "gn:population":0,
    "gn:timezone":"Africa/Conakry",
    "iso:country":"GN",
    "name:und_x_variant":[
        "Yradou",
        "Diraya"
    ],
    "wof:name":"Diraya",
    "wof:placetype":"locality"
},
  "geometry": {"coordinates":[-9.28333,9.41667],"type":"Point"}
}