{
  "type": "Feature",
  "properties": {
    "gn:admin1_code":"N",
    "gn:admin2_code":"13",
    "gn:asciiname":"Ouamandou",
    "gn:country_code":"GN",
    "gn:dem":353,
    "gn:feature_class":"P",
    "gn:feature_code":"PPL",
    "gn:name":"Ouamandou",
    "gn:population":0,
    "gn:timezone":"Africa/Conakry",
    "iso:country":"GN",
    "wof:name":"Ouamandou",
    "wof:placetype":"locality"
},
  "geometry": {"coordinates":[-10.47083,8.48528],"type":"Point"}
}