{
  "type": "Feature",
  "properties": {
    "gn:admin1_code":"N",
    "gn:admin2_code":"13",
    "gn:asciiname":"Douboudou",
    "gn:country_code":"GN",
    "gn:dem":500,
    "gn:feature_class":"P",
    "gn:feature_code":"PPL",
    "gn:name":"Douboudou",
    "gn:population":0,
    "gn:timezone":"Africa/Conakry",
    "iso:country":"GN",
    "wof:name":"Douboudou",
    "wof:placetype":"locality"
},
  "geometry": {"coordinates":[-10.26972,8.89056],"type":"Point"}
}