{
  "type": "Feature",
  "properties": {
    "gn:admin1_code":"D",
    "gn:admin2_code":"16",
    "gn:asciiname":"Bolonta",
    "gn:country_code":"GN",
    "gn:dem":101,
    "gn:feature_class":"P",
    "gn:feature_code":"PPL",
    "gn:name":"Bolonta",
    "gn:population":0,
    "gn:timezone":"Africa/Conakry",
    "iso:country":"GN",
    "wof:name":"Bolonta",
    "wof:placetype":"locality"
},
  "geometry": {"coordinates":[-13.20556,9.87028],"type":"Point"}
}