{
  "type": "Feature",
  "properties": {
    "gn:admin1_code":"K",
    "gn:admin2_code":"19",
    "gn:asciiname":"Dakamangui",
    "gn:country_code":"GN",
    "gn:dem":414,
    "gn:feature_class":"P",
    "gn:feature_code":"PPL",
    "gn:name":"Dakamangui",
    "gn:population":0,
    "gn:timezone":"Africa/Conakry",
    "iso:country":"GN",
    "wof:name":"Dakamangui",
    "wof:placetype":"locality"
},
  "geometry": {"coordinates":[-10.46667,11.11667],"type":"Point"}
}