{
  "type": "Feature",
  "properties": {
    "gn:admin1_code":"B",
    "gn:admin2_code":"03",
    "gn:asciiname":"Kanouba",
    "gn:country_code":"GN",
    "gn:dem":20,
    "gn:feature_class":"P",
    "gn:feature_code":"PPL",
    "gn:name":"Kanouba",
    "gn:population":0,
    "gn:timezone":"Africa/Conakry",
    "iso:country":"GN",
    "wof:name":"Kanouba",
    "wof:placetype":"locality"
},
  "geometry": {"coordinates":[-14.78333,10.95],"type":"Point"}
}