{
  "type": "Feature",
  "properties": {
    "gn:admin1_code":"D",
    "gn:admin2_code":"16",
    "gn:asciiname":"Sireya",
    "gn:cc2":"GN",
    "gn:country_code":"GN",
    "gn:dem":341,
    "gn:feature_class":"P",
    "gn:feature_code":"PPL",
    "gn:name":"Sireya",
    "gn:population":0,
    "gn:timezone":"Africa/Conakry",
    "iso:country":"GN",
    "name:und_x_variant":[
        "Sir\u00e9\u00efa",
        "Sireya"
    ],
    "wof:name":"Sireya",
    "wof:placetype":"locality"
},
  "geometry": {"coordinates":[-12.26667,10.11667],"type":"Point"}
}