{
  "type": "Feature",
  "properties": {
    "gn:admin1_code":"N",
    "gn:admin2_code":"29",
    "gn:asciiname":"Beley",
    "gn:country_code":"GN",
    "gn:dem":401,
    "gn:feature_class":"P",
    "gn:feature_code":"PPL",
    "gn:name":"Beley",
    "gn:population":0,
    "gn:timezone":"Africa/Conakry",
    "iso:country":"GN",
    "wof:name":"Beley",
    "wof:placetype":"locality"
},
  "geometry": {"coordinates":[-8.81417,7.56722],"type":"Point"}
}