{
  "type": "Feature",
  "properties": {
    "gn:admin1_code":"D",
    "gn:admin2_code":"11",
    "gn:asciiname":"Gonga Khimbeli",
    "gn:country_code":"GN",
    "gn:dem":337,
    "gn:feature_class":"P",
    "gn:feature_code":"PPL",
    "gn:name":"Gonga Khimb\u00e9li",
    "gn:population":0,
    "gn:timezone":"Africa/Conakry",
    "iso:country":"GN",
    "name:und_x_variant":[
        "Gonga",
        "Gonga Khimb\u00e9li"
    ],
    "wof:name":"Gonga Khimbeli",
    "wof:placetype":"locality"
},
  "geometry": {"coordinates":[-13.45,10.38333],"type":"Point"}
}