{
  "type": "Feature",
  "properties": {
    "gn:admin1_code":"F",
    "gn:admin2_code":"17",
    "gn:asciiname":"Mamouria",
    "gn:country_code":"GN",
    "gn:dem":635,
    "gn:feature_class":"P",
    "gn:feature_code":"PPL",
    "gn:name":"Mamouria",
    "gn:population":0,
    "gn:timezone":"Africa/Conakry",
    "iso:country":"GN",
    "wof:name":"Mamouria",
    "wof:placetype":"locality"
},
  "geometry": {"coordinates":[-9.68611,8.93333],"type":"Point"}
}