{
  "type": "Feature",
  "properties": {
    "gn:admin1_code":"K",
    "gn:admin2_code":"32",
    "gn:asciiname":"Farabana",
    "gn:country_code":"GN",
    "gn:dem":539,
    "gn:feature_class":"P",
    "gn:feature_code":"PPL",
    "gn:name":"Farabana",
    "gn:population":0,
    "gn:timezone":"Africa/Conakry",
    "iso:country":"GN",
    "wof:name":"Farabana",
    "wof:placetype":"locality"
},
  "geometry": {"coordinates":[-9.28333,9.51667],"type":"Point"}
}