{
  "type": "Feature",
  "properties": {
    "gn:admin1_code":"K",
    "gn:admin2_code":"19",
    "gn:asciiname":"Belinkoro",
    "gn:cc2":"GN",
    "gn:country_code":"GN",
    "gn:dem":404,
    "gn:feature_class":"P",
    "gn:feature_code":"PPL",
    "gn:name":"B\u00e9linkoro",
    "gn:population":0,
    "gn:timezone":"Africa/Conakry",
    "iso:country":"GN",
    "name:und_x_variant":[
        "Bilinkoro",
        "B\u00e9linkoro"
    ],
    "wof:name":"Belinkoro",
    "wof:placetype":"locality"
},
  "geometry": {"coordinates":[-10.23333,10.15],"type":"Point"}
}