{
  "type": "Feature",
  "properties": {
    "gn:admin1_code":"M",
    "gn:admin2_code":"23",
    "gn:asciiname":"Mooria",
    "gn:country_code":"GN",
    "gn:dem":867,
    "gn:feature_class":"P",
    "gn:feature_code":"PPL",
    "gn:name":"Mooria",
    "gn:population":0,
    "gn:timezone":"Africa/Conakry",
    "iso:country":"GN",
    "wof:name":"Mooria",
    "wof:placetype":"locality"
},
  "geometry": {"coordinates":[-11.56667,10.45],"type":"Point"}
}