{
  "type": "Feature",
  "properties": {
    "gn:admin1_code":"B",
    "gn:admin2_code":"03",
    "gn:asciiname":"Taidi",
    "gn:cc2":"GN",
    "gn:country_code":"GN",
    "gn:dem":4,
    "gn:feature_class":"P",
    "gn:feature_code":"PPL",
    "gn:name":"Ta\u00efdi",
    "gn:population":0,
    "gn:timezone":"Africa/Conakry",
    "iso:country":"GN",
    "name:und_x_variant":[
        "Petit Talibonche",
        "Tabuctane",
        "Tailbounsou",
        "Ta\u00efdi"
    ],
    "wof:name":"Taidi",
    "wof:placetype":"locality"
},
  "geometry": {"coordinates":[-14.65,10.68333],"type":"Point"}
}