{
  "type": "Feature",
  "properties": {
    "gn:admin1_code":"B",
    "gn:admin2_code":"02",
    "gn:asciiname":"Bakou",
    "gn:cc2":"GN",
    "gn:country_code":"GN",
    "gn:dem":49,
    "gn:feature_class":"P",
    "gn:feature_code":"PPL",
    "gn:name":"Bakou",
    "gn:population":0,
    "gn:timezone":"Africa/Conakry",
    "iso:country":"GN",
    "name:und_x_variant":[
        "Bako",
        "Bakou"
    ],
    "wof:name":"Bakou",
    "wof:placetype":"locality"
},
  "geometry": {"coordinates":[-14.33333,10.33333],"type":"Point"}
}