{
  "type": "Feature",
  "properties": {
    "gn:admin1_code":"D",
    "gn:admin2_code":"10",
    "gn:asciiname":"Guemeyire",
    "gn:country_code":"GN",
    "gn:dem":8,
    "gn:feature_class":"P",
    "gn:feature_code":"PPL",
    "gn:name":"Gu\u00e8m\u00e8yir\u00e9",
    "gn:population":0,
    "gn:timezone":"Africa/Conakry",
    "iso:country":"GN",
    "wof:name":"Guemeyire",
    "wof:placetype":"locality"
},
  "geometry": {"coordinates":[-13.43972,9.4125],"type":"Point"}
}