{
  "type": "Feature",
  "properties": {
    "gn:admin1_code":"M",
    "gn:admin2_code":"25",
    "gn:asciiname":"Dalao",
    "gn:country_code":"GN",
    "gn:dem":1051,
    "gn:feature_class":"P",
    "gn:feature_code":"PPL",
    "gn:name":"Dalao",
    "gn:population":0,
    "gn:timezone":"Africa/Conakry",
    "iso:country":"GN",
    "wof:name":"Dalao",
    "wof:placetype":"locality"
},
  "geometry": {"coordinates":[-12.68333,10.96667],"type":"Point"}
}