{
  "type": "Feature",
  "properties": {
    "gn:admin1_code":"N",
    "gn:admin2_code":"29",
    "gn:asciiname":"Bamakanja",
    "gn:cc2":"GN",
    "gn:country_code":"GN",
    "gn:dem":412,
    "gn:feature_class":"P",
    "gn:feature_code":"PPL",
    "gn:name":"Bamakanja",
    "gn:population":0,
    "gn:timezone":"Africa/Conakry",
    "iso:country":"GN",
    "name:und_x_variant":[
        "Bamakaman",
        "Bamakama",
        "Bamakanja"
    ],
    "wof:name":"Bamakanja",
    "wof:placetype":"locality"
},
  "geometry": {"coordinates":[-9.26861,7.71639],"type":"Point"}
}