{
  "type": "Feature",
  "properties": {
    "gn:admin1_code":"B",
    "gn:admin2_code":"12",
    "gn:asciiname":"Kampounding",
    "gn:country_code":"GN",
    "gn:dem":191,
    "gn:feature_class":"P",
    "gn:feature_code":"PPL",
    "gn:name":"Kampounding",
    "gn:population":0,
    "gn:timezone":"Africa/Conakry",
    "iso:country":"GN",
    "wof:name":"Kampounding",
    "wof:placetype":"locality"
},
  "geometry": {"coordinates":[-13.68333,11.76667],"type":"Point"}
}