{
  "type": "Feature",
  "properties": {
    "gn:admin1_code":"F",
    "gn:admin2_code":"17",
    "gn:asciiname":"Kossa",
    "gn:country_code":"GN",
    "gn:dem":606,
    "gn:feature_class":"P",
    "gn:feature_code":"PPL",
    "gn:name":"Kossa",
    "gn:population":0,
    "gn:timezone":"Africa/Conakry",
    "iso:country":"GN",
    "name:ceb_x_preferred":[
        "Kossa"
    ],
    "name:deu_x_preferred":[
        "Kossa"
    ],
    "name:swe_x_preferred":[
        "Kossa"
    ],
    "wof:name":"Kossa",
    "wof:placetype":"locality"
},
  "geometry": {"coordinates":[-10.07472,8.955],"type":"Point"}
}