{
  "type": "Feature",
  "properties": {
    "gn:admin1_code":"N",
    "gn:admin2_code":"21",
    "gn:asciiname":"Loo",
    "gn:country_code":"GN",
    "gn:dem":460,
    "gn:feature_class":"P",
    "gn:feature_code":"PPL",
    "gn:name":"Loo",
    "gn:population":0,
    "gn:timezone":"Africa/Conakry",
    "iso:country":"GN",
    "name:bih_x_preferred":[
        "\u0932\u0942\u0939\u093f"
    ],
    "name:ceb_x_preferred":[
        "Loo"
    ],
    "name:ces_x_preferred":[
        "Loo"
    ],
    "name:cym_x_preferred":[
        "Loo"
    ],
    "name:deu_x_preferred":[
        "Loo"
    ],
    "name:fra_x_preferred":[
        "Loo"
    ],
    "name:spa_x_preferred":[
        "Loo"
    ],
    "name:swe_x_preferred":[
        "Loo"
    ],
    "wof:name":"Loo",
    "wof:placetype":"locality"
},
  "geometry": {"coordinates":[-9.28333,7.85861],"type":"Point"}
}