{
  "type": "Feature",
  "properties": {
    "gn:admin1_code":"N",
    "gn:admin2_code":"13",
    "gn:asciiname":"Falanko",
    "gn:country_code":"GN",
    "gn:dem":418,
    "gn:feature_class":"P",
    "gn:feature_code":"PPL",
    "gn:name":"Falanko",
    "gn:population":0,
    "gn:timezone":"Africa/Conakry",
    "iso:country":"GN",
    "wof:name":"Falanko",
    "wof:placetype":"locality"
},
  "geometry": {"coordinates":[-10.33583,8.52472],"type":"Point"}
}