{
  "type": "Feature",
  "properties": {
    "gn:admin1_code":"F",
    "gn:admin2_code":"09",
    "gn:asciiname":"Sandankoro",
    "gn:country_code":"GN",
    "gn:dem":608,
    "gn:feature_class":"P",
    "gn:feature_code":"PPL",
    "gn:name":"Sandankoro",
    "gn:population":0,
    "gn:timezone":"Africa/Conakry",
    "iso:country":"GN",
    "wof:name":"Sandankoro",
    "wof:placetype":"locality"
},
  "geometry": {"coordinates":[-10.55,9.33333],"type":"Point"}
}