{
  "type": "Feature",
  "properties": {
    "gn:admin1_code":"F",
    "gn:admin2_code":"07",
    "gn:asciiname":"Nimalo Konsolon",
    "gn:cc2":"GN",
    "gn:country_code":"GN",
    "gn:dem":400,
    "gn:feature_class":"P",
    "gn:feature_code":"PPL",
    "gn:name":"Nimalo Konsolon",
    "gn:population":0,
    "gn:timezone":"Africa/Conakry",
    "iso:country":"GN",
    "name:und_x_variant":[
        "Ilimalo-Konsolon",
        "Nimalo Konsolon"
    ],
    "wof:name":"Nimalo Konsolon",
    "wof:placetype":"locality"
},
  "geometry": {"coordinates":[-10.35,11.78333],"type":"Point"}
}