{
  "type": "Feature",
  "properties": {
    "gn:admin1_code":"F",
    "gn:admin2_code":"17",
    "gn:asciiname":"Kongola",
    "gn:country_code":"GN",
    "gn:dem":661,
    "gn:feature_class":"P",
    "gn:feature_code":"PPL",
    "gn:name":"Kongola",
    "gn:population":0,
    "gn:timezone":"Africa/Conakry",
    "iso:country":"GN",
    "name:deu_x_preferred":[
        "Kongola"
    ],
    "wof:name":"Kongola",
    "wof:placetype":"locality"
},
  "geometry": {"coordinates":[-10.36667,9.15],"type":"Point"}
}