{
  "type": "Feature",
  "properties": {
    "gn:admin1_code":"04",
    "gn:asciiname":"Tamatara",
    "gn:country_code":"GN",
    "gn:dem":23,
    "gn:feature_class":"P",
    "gn:feature_code":"PPL",
    "gn:name":"Tamatara",
    "gn:population":0,
    "gn:timezone":"Africa/Conakry",
    "iso:country":"GN",
    "wof:name":"Tamatara",
    "wof:placetype":"locality"
},
  "geometry": {"coordinates":[-13.5575,9.69722],"type":"Point"}
}