{
  "type": "Feature",
  "properties": {
    "gn:admin1_code":"D",
    "gn:admin2_code":"16",
    "gn:asciiname":"Guiemembo",
    "gn:cc2":"GN",
    "gn:country_code":"GN",
    "gn:dem":121,
    "gn:feature_class":"P",
    "gn:feature_code":"PPL",
    "gn:name":"Gui\u00e9membo",
    "gn:population":0,
    "gn:timezone":"Africa/Conakry",
    "iso:country":"GN",
    "name:und_x_variant":[
        "Gui\u00e9memo",
        "Gui\u00e9membo"
    ],
    "wof:name":"Guiemembo",
    "wof:placetype":"locality"
},
  "geometry": {"coordinates":[-13.16583,9.78944],"type":"Point"}
}