{
  "type": "Feature",
  "properties": {
    "gn:admin1_code":"N",
    "gn:admin2_code":"29",
    "gn:asciiname":"Koepa",
    "gn:country_code":"GN",
    "gn:dem":405,
    "gn:feature_class":"P",
    "gn:feature_code":"PPL",
    "gn:name":"Koepa",
    "gn:population":0,
    "gn:timezone":"Africa/Conakry",
    "iso:country":"GN",
    "wof:name":"Koepa",
    "wof:placetype":"locality"
},
  "geometry": {"coordinates":[-8.76722,7.50806],"type":"Point"}
}