{
  "type": "Feature",
  "properties": {
    "gn:admin1_code":"N",
    "gn:admin2_code":"13",
    "gn:asciiname":"Tiecoulo",
    "gn:country_code":"GN",
    "gn:dem":529,
    "gn:feature_class":"P",
    "gn:feature_code":"PPL",
    "gn:name":"Ti\u00e9coulo",
    "gn:population":0,
    "gn:timezone":"Africa/Conakry",
    "iso:country":"GN",
    "wof:name":"Tiecoulo",
    "wof:placetype":"locality"
},
  "geometry": {"coordinates":[-9.95694,8.54806],"type":"Point"}
}