{
  "type": "Feature",
  "properties": {
    "gn:admin1_code":"D",
    "gn:admin2_code":"31",
    "gn:asciiname":"Kalekhoure",
    "gn:country_code":"GN",
    "gn:dem":16,
    "gn:feature_class":"P",
    "gn:feature_code":"PPL",
    "gn:name":"Kal\u00e9khour\u00e9",
    "gn:population":0,
    "gn:timezone":"Africa/Conakry",
    "iso:country":"GN",
    "name:und_x_variant":[
        "Kal\u00e9kour\u00e9",
        "Kal\u00e9khour\u00e9"
    ],
    "wof:name":"Kalekhoure",
    "wof:placetype":"locality"
},
  "geometry": {"coordinates":[-13.52333,9.84778],"type":"Point"}
}