{
  "type": "Feature",
  "properties": {
    "gn:admin1_code":"F",
    "gn:admin2_code":"17",
    "gn:asciiname":"Dingue",
    "gn:cc2":"GN",
    "gn:country_code":"GN",
    "gn:dem":557,
    "gn:feature_class":"P",
    "gn:feature_code":"PPL",
    "gn:name":"Dingu\u00e9",
    "gn:population":0,
    "gn:timezone":"Africa/Conakry",
    "iso:country":"GN",
    "name:und_x_variant":[
        "Dink\u00e9",
        "Dingu\u00e9"
    ],
    "wof:name":"Dingue",
    "wof:placetype":"locality"
},
  "geometry": {"coordinates":[-10.21667,9.11667],"type":"Point"}
}