{
  "type": "Feature",
  "properties": {
    "gn:admin1_code":"D",
    "gn:admin2_code":"31",
    "gn:asciiname":"Souguebunyi",
    "gn:country_code":"GN",
    "gn:dem":29,
    "gn:feature_class":"P",
    "gn:feature_code":"PPL",
    "gn:name":"Sougu\u00e9bunyi",
    "gn:population":0,
    "gn:timezone":"Africa/Conakry",
    "iso:country":"GN",
    "wof:name":"Souguebunyi",
    "wof:placetype":"locality"
},
  "geometry": {"coordinates":[-13.64194,9.95778],"type":"Point"}
}