{
  "type": "Feature",
  "properties": {
    "gn:admin1_code":"B",
    "gn:admin2_code":"02",
    "gn:asciiname":"Katere",
    "gn:country_code":"GN",
    "gn:dem":12,
    "gn:feature_class":"P",
    "gn:feature_code":"PPL",
    "gn:name":"Kat\u00e9r\u00e9",
    "gn:population":0,
    "gn:timezone":"Africa/Conakry",
    "iso:country":"GN",
    "wof:name":"Katere",
    "wof:placetype":"locality"
},
  "geometry": {"coordinates":[-13.83639,9.93472],"type":"Point"}
}