{
  "type": "Feature",
  "properties": {
    "gn:admin1_code":"N",
    "gn:admin2_code":"29",
    "gn:asciiname":"Diapele",
    "gn:country_code":"GN",
    "gn:dem":442,
    "gn:feature_class":"P",
    "gn:feature_code":"PPL",
    "gn:name":"Diap\u00e9l\u00e9",
    "gn:population":0,
    "gn:timezone":"Africa/Conakry",
    "iso:country":"GN",
    "wof:name":"Diapele",
    "wof:placetype":"locality"
},
  "geometry": {"coordinates":[-8.72056,7.51778],"type":"Point"}
}