{
  "type": "Feature",
  "properties": {
    "gn:admin1_code":"M",
    "gn:admin2_code":"23",
    "gn:asciiname":"Sitakoto",
    "gn:country_code":"GN",
    "gn:dem":419,
    "gn:feature_class":"P",
    "gn:feature_code":"PPL",
    "gn:name":"Sitakoto",
    "gn:population":0,
    "gn:timezone":"Africa/Conakry",
    "iso:country":"GN",
    "wof:name":"Sitakoto",
    "wof:placetype":"locality"
},
  "geometry": {"coordinates":[-11.71667,10.05],"type":"Point"}
}