{
  "type": "Feature",
  "properties": {
    "gn:admin1_code":"K",
    "gn:admin2_code":"19",
    "gn:asciiname":"Sansan",
    "gn:country_code":"GN",
    "gn:dem":393,
    "gn:feature_class":"P",
    "gn:feature_code":"PPL",
    "gn:name":"Sansan",
    "gn:population":0,
    "gn:timezone":"Africa/Conakry",
    "iso:country":"GN",
    "name:bar_x_preferred":[
        "Sansan"
    ],
    "name:ceb_x_preferred":[
        "Sansan"
    ],
    "name:deu_x_preferred":[
        "Sansan"
    ],
    "name:pol_x_preferred":[
        "Sansan"
    ],
    "name:swe_x_preferred":[
        "Sansan"
    ],
    "wof:name":"Sansan",
    "wof:placetype":"locality"
},
  "geometry": {"coordinates":[-10.35,11.05],"type":"Point"}
}