{
  "type": "Feature",
  "properties": {
    "gn:admin1_code":"L",
    "gn:admin2_code":"22",
    "gn:asciiname":"Dira",
    "gn:country_code":"GN",
    "gn:dem":409,
    "gn:feature_class":"P",
    "gn:feature_code":"PPL",
    "gn:name":"Dira",
    "gn:population":0,
    "gn:timezone":"Africa/Conakry",
    "iso:country":"GN",
    "name:azb_x_preferred":[
        "\u062f\u06cc\u0631\u0627"
    ],
    "name:ceb_x_preferred":[
        "Dira"
    ],
    "name:fas_x_preferred":[
        "\u062f\u06cc\u0631\u0627"
    ],
    "name:fra_x_preferred":[
        "Dira"
    ],
    "name:lat_x_preferred":[
        "Dira"
    ],
    "name:swe_x_preferred":[
        "Dira"
    ],
    "wof:name":"Dira",
    "wof:placetype":"locality"
},
  "geometry": {"coordinates":[-12.3542,12.1806],"type":"Point"}
}