{
  "type": "Feature",
  "properties": {
    "gn:admin1_code":"F",
    "gn:admin2_code":"07",
    "gn:asciiname":"Diarinde",
    "gn:country_code":"GN",
    "gn:dem":541,
    "gn:feature_class":"P",
    "gn:feature_code":"PPL",
    "gn:name":"Diarind\u00e9",
    "gn:population":0,
    "gn:timezone":"Africa/Conakry",
    "iso:country":"GN",
    "wof:name":"Diarinde",
    "wof:placetype":"locality"
},
  "geometry": {"coordinates":[-10.26667,12.05],"type":"Point"}
}