{
  "type": "Feature",
  "properties": {
    "gn:admin1_code":"F",
    "gn:admin2_code":"07",
    "gn:asciiname":"Hellaya",
    "gn:country_code":"GN",
    "gn:dem":738,
    "gn:feature_class":"P",
    "gn:feature_code":"PPL",
    "gn:name":"Hellaya",
    "gn:population":0,
    "gn:timezone":"Africa/Conakry",
    "iso:country":"GN",
    "wof:name":"Hellaya",
    "wof:placetype":"locality"
},
  "geometry": {"coordinates":[-10.86667,11.45],"type":"Point"}
}