{
  "type": "Feature",
  "properties": {
    "gn:admin1_code":"K",
    "gn:admin2_code":"37",
    "gn:asciiname":"Mansalako",
    "gn:country_code":"GN",
    "gn:dem":366,
    "gn:feature_class":"P",
    "gn:feature_code":"PPL",
    "gn:name":"Mansalako",
    "gn:population":0,
    "gn:timezone":"Africa/Conakry",
    "iso:country":"GN",
    "name:und_x_variant":[
        "Kini\u00e9ni",
        "Mansalako"
    ],
    "wof:name":"Mansalako",
    "wof:placetype":"locality"
},
  "geometry": {"coordinates":[-8.65,10.93333],"type":"Point"}
}