{
  "type": "Feature",
  "properties": {
    "gn:admin1_code":"N",
    "gn:admin2_code":"21",
    "gn:asciiname":"Kolimai",
    "gn:country_code":"GN",
    "gn:dem":528,
    "gn:feature_class":"P",
    "gn:feature_code":"PPL",
    "gn:name":"Kolima\u00ef",
    "gn:population":0,
    "gn:timezone":"Africa/Conakry",
    "iso:country":"GN",
    "wof:name":"Kolimai",
    "wof:placetype":"locality"
},
  "geometry": {"coordinates":[-9.73333,8.60722],"type":"Point"}
}