{
  "type": "Feature",
  "properties": {
    "gn:admin1_code":"N",
    "gn:admin2_code":"21",
    "gn:asciiname":"Diataidou",
    "gn:country_code":"GN",
    "gn:dem":550,
    "gn:feature_class":"P",
    "gn:feature_code":"PPL",
    "gn:name":"Diata\u00efdou",
    "gn:population":0,
    "gn:timezone":"Africa/Conakry",
    "iso:country":"GN",
    "wof:name":"Diataidou",
    "wof:placetype":"locality"
},
  "geometry": {"coordinates":[-9.60556,8.70389],"type":"Point"}
}