{
  "type": "Feature",
  "properties": {
    "gn:admin1_code":"N",
    "gn:admin2_code":"13",
    "gn:asciiname":"Bili",
    "gn:country_code":"GN",
    "gn:dem":599,
    "gn:feature_class":"P",
    "gn:feature_code":"PPL",
    "gn:name":"Bili",
    "gn:population":0,
    "gn:timezone":"Africa/Conakry",
    "iso:country":"GN",
    "name:bre_x_preferred":[
        "Bili"
    ],
    "name:ceb_x_preferred":[
        "Bili"
    ],
    "name:fra_x_preferred":[
        "Bili"
    ],
    "name:kat_x_preferred":[
        "\u10d1\u10d8\u10da\u10d8"
    ],
    "name:swe_x_preferred":[
        "Bili"
    ],
    "wof:name":"Bili",
    "wof:placetype":"locality"
},
  "geometry": {"coordinates":[-9.98333,8.51667],"type":"Point"}
}