{
  "type": "Feature",
  "properties": {
    "gn:admin1_code":"D",
    "gn:admin2_code":"10",
    "gn:asciiname":"Rofema",
    "gn:country_code":"GN",
    "gn:dem":1,
    "gn:feature_class":"P",
    "gn:feature_code":"PPL",
    "gn:name":"Rof\u00e9ma",
    "gn:population":0,
    "gn:timezone":"Africa/Conakry",
    "iso:country":"GN",
    "wof:name":"Rofema",
    "wof:placetype":"locality"
},
  "geometry": {"coordinates":[-13.13083,9.10139],"type":"Point"}
}