{
  "type": "Feature",
  "properties": {
    "gn:admin1_code":"B",
    "gn:admin2_code":"18",
    "gn:asciiname":"Mbanb",
    "gn:country_code":"GN",
    "gn:dem":155,
    "gn:feature_class":"P",
    "gn:feature_code":"PPL",
    "gn:name":"Mbanb",
    "gn:population":0,
    "gn:timezone":"Africa/Conakry",
    "iso:country":"GN",
    "wof:name":"Mbanb",
    "wof:placetype":"locality"
},
  "geometry": {"coordinates":[-12.9517,12.3175],"type":"Point"}
}