{
  "type": "Feature",
  "properties": {
    "gn:admin1_code":"N",
    "gn:admin2_code":"36",
    "gn:asciiname":"Gban",
    "gn:country_code":"GN",
    "gn:dem":471,
    "gn:feature_class":"P",
    "gn:feature_code":"PPL",
    "gn:name":"Gban",
    "gn:population":0,
    "gn:timezone":"Africa/Conakry",
    "iso:country":"GN",
    "wof:name":"Gban",
    "wof:placetype":"locality"
},
  "geometry": {"coordinates":[-8.17472,7.80306],"type":"Point"}
}