{
  "type": "Feature",
  "properties": {
    "gn:admin1_code":"K",
    "gn:admin2_code":"19",
    "gn:asciiname":"Karankama",
    "gn:cc2":"GN",
    "gn:country_code":"GN",
    "gn:dem":406,
    "gn:feature_class":"P",
    "gn:feature_code":"PPL",
    "gn:name":"Karankama",
    "gn:population":0,
    "gn:timezone":"Africa/Conakry",
    "iso:country":"GN",
    "name:und_x_variant":[
        "Karankaman",
        "Karankama"
    ],
    "wof:name":"Karankama",
    "wof:placetype":"locality"
},
  "geometry": {"coordinates":[-10.08333,10.93333],"type":"Point"}
}