{
  "type": "Feature",
  "properties": {
    "gn:admin1_code":"D",
    "gn:admin2_code":"27",
    "gn:asciiname":"Maoba Hassana",
    "gn:country_code":"GN",
    "gn:dem":667,
    "gn:feature_class":"P",
    "gn:feature_code":"PPL",
    "gn:name":"Maoba Hassana",
    "gn:population":0,
    "gn:timezone":"Africa/Conakry",
    "iso:country":"GN",
    "wof:name":"Maoba Hassana",
    "wof:placetype":"locality"
},
  "geometry": {"coordinates":[-13.05,10.73333],"type":"Point"}
}