{
  "type": "Feature",
  "properties": {
    "gn:admin1_code":"B",
    "gn:admin2_code":"03",
    "gn:asciiname":"Oundoufere",
    "gn:country_code":"GN",
    "gn:dem":57,
    "gn:feature_class":"P",
    "gn:feature_code":"PPL",
    "gn:name":"Oundouf\u00e9r\u00e9",
    "gn:population":0,
    "gn:timezone":"Africa/Conakry",
    "iso:country":"GN",
    "wof:name":"Oundoufere",
    "wof:placetype":"locality"
},
  "geometry": {"coordinates":[-14.43333,11.31667],"type":"Point"}
}