{
  "type": "Feature",
  "properties": {
    "gn:admin1_code":"K",
    "gn:admin2_code":"21",
    "gn:asciiname":"Boutoudou",
    "gn:country_code":"GN",
    "gn:dem":677,
    "gn:feature_class":"P",
    "gn:feature_code":"PPL",
    "gn:name":"Boutoudou",
    "gn:population":0,
    "gn:timezone":"Africa/Conakry",
    "iso:country":"GN",
    "wof:name":"Boutoudou",
    "wof:placetype":"locality"
},
  "geometry": {"coordinates":[-9.03472,8.89389],"type":"Point"}
}