{
  "type": "Feature",
  "properties": {
    "gn:admin1_code":"N",
    "gn:admin2_code":"13",
    "gn:asciiname":"Koundou",
    "gn:country_code":"GN",
    "gn:dem":420,
    "gn:feature_class":"P",
    "gn:feature_code":"PPL",
    "gn:name":"Koundou",
    "gn:population":0,
    "gn:timezone":"Africa/Conakry",
    "iso:country":"GN",
    "wof:name":"Koundou",
    "wof:placetype":"locality"
},
  "geometry": {"coordinates":[-10.40834,8.63782],"type":"Point"}
}