{
  "type": "Feature",
  "properties": {
    "gn:admin1_code":"N",
    "gn:admin2_code":"13",
    "gn:asciiname":"Kolignindo",
    "gn:cc2":"GN",
    "gn:country_code":"GN",
    "gn:dem":443,
    "gn:feature_class":"P",
    "gn:feature_code":"PPL",
    "gn:name":"Kolignindo",
    "gn:population":0,
    "gn:timezone":"Africa/Conakry",
    "iso:country":"GN",
    "name:und_x_variant":[
        "Kolianindo",
        "Kolignindo"
    ],
    "wof:name":"Kolignindo",
    "wof:placetype":"locality"
},
  "geometry": {"coordinates":[-10.30611,8.60139],"type":"Point"}
}