{
  "type": "Feature",
  "properties": {
    "gn:admin1_code":"N",
    "gn:admin2_code":"21",
    "gn:asciiname":"Serinka",
    "gn:country_code":"GN",
    "gn:dem":662,
    "gn:feature_class":"P",
    "gn:feature_code":"PPL",
    "gn:name":"S\u00e9rinka",
    "gn:population":0,
    "gn:timezone":"Africa/Conakry",
    "iso:country":"GN",
    "wof:name":"Serinka",
    "wof:placetype":"locality"
},
  "geometry": {"coordinates":[-9.65528,8.68722],"type":"Point"}
}