{
  "type": "Feature",
  "properties": {
    "gn:admin1_code":"D",
    "gn:admin2_code":"10",
    "gn:asciiname":"Katabe",
    "gn:cc2":"GN",
    "gn:country_code":"GN",
    "gn:dem":12,
    "gn:feature_class":"P",
    "gn:feature_code":"PPL",
    "gn:name":"Katab\u00e9",
    "gn:population":0,
    "gn:timezone":"Africa/Conakry",
    "iso:country":"GN",
    "name:und_x_variant":[
        "Kabat\u00e9",
        "Katab\u00e9"
    ],
    "wof:name":"Katabe",
    "wof:placetype":"locality"
},
  "geometry": {"coordinates":[-13.15,9.41667],"type":"Point"}
}