{
  "type": "Feature",
  "properties": {
    "gn:admin1_code":"N",
    "gn:admin2_code":"38",
    "gn:asciiname":"Gbouo",
    "gn:country_code":"GN",
    "gn:dem":475,
    "gn:feature_class":"P",
    "gn:feature_code":"PPL",
    "gn:name":"Gbouo",
    "gn:population":0,
    "gn:timezone":"Africa/Conakry",
    "iso:country":"GN",
    "name:und_x_variant":[
        "Boulo",
        "Gbouo"
    ],
    "wof:name":"Gbouo",
    "wof:placetype":"locality"
},
  "geometry": {"coordinates":[-8.69361,7.93528],"type":"Point"}
}