{
  "type": "Feature",
  "properties": {
    "gn:admin1_code":"K",
    "gn:admin2_code":"39",
    "gn:asciiname":"Ouria",
    "gn:country_code":"GN",
    "gn:dem":370,
    "gn:feature_class":"P",
    "gn:feature_code":"PPL",
    "gn:name":"Ouria",
    "gn:population":0,
    "gn:timezone":"Africa/Conakry",
    "iso:country":"GN",
    "wof:name":"Ouria",
    "wof:placetype":"locality"
},
  "geometry": {"coordinates":[-9.31667,11.68333],"type":"Point"}
}