{
  "type": "Feature",
  "properties": {
    "gn:admin1_code":"N",
    "gn:admin2_code":"13",
    "gn:asciiname":"Gbandou",
    "gn:country_code":"GN",
    "gn:dem":450,
    "gn:feature_class":"P",
    "gn:feature_code":"PPL",
    "gn:name":"Gbandou",
    "gn:population":0,
    "gn:timezone":"Africa/Conakry",
    "iso:country":"GN",
    "wof:name":"Gbandou",
    "wof:placetype":"locality"
},
  "geometry": {"coordinates":[-10.28861,8.52667],"type":"Point"}
}