{
  "type": "Feature",
  "properties": {
    "gn:admin1_code":"F",
    "gn:admin2_code":"09",
    "gn:asciiname":"Yatia",
    "gn:cc2":"GN",
    "gn:country_code":"GN",
    "gn:dem":458,
    "gn:feature_class":"P",
    "gn:feature_code":"PPL",
    "gn:name":"Yatia",
    "gn:population":0,
    "gn:timezone":"Africa/Conakry",
    "iso:country":"GN",
    "name:und_x_variant":[
        "Yathia",
        "Yatia"
    ],
    "wof:name":"Yatia",
    "wof:placetype":"locality"
},
  "geometry": {"coordinates":[-10.96667,10.01667],"type":"Point"}
}