{
  "type": "Feature",
  "properties": {
    "gn:admin1_code":"N",
    "gn:admin2_code":"13",
    "gn:asciiname":"Yalamba",
    "gn:country_code":"GN",
    "gn:dem":437,
    "gn:feature_class":"P",
    "gn:feature_code":"PPL",
    "gn:name":"Yalamba",
    "gn:population":0,
    "gn:timezone":"Africa/Conakry",
    "iso:country":"GN",
    "wof:name":"Yalamba",
    "wof:placetype":"locality"
},
  "geometry": {"coordinates":[-10.18333,8.51667],"type":"Point"}
}