{
  "type": "Feature",
  "properties": {
    "gn:admin1_code":"K",
    "gn:admin2_code":"19",
    "gn:asciiname":"Logoronbo",
    "gn:cc2":"GN",
    "gn:country_code":"GN",
    "gn:dem":412,
    "gn:feature_class":"P",
    "gn:feature_code":"PPL",
    "gn:name":"Logoronbo",
    "gn:population":0,
    "gn:timezone":"Africa/Conakry",
    "iso:country":"GN",
    "name:und_x_variant":[
        "Logorombo",
        "Lokoumbo",
        "Logoronbo"
    ],
    "wof:name":"Logoronbo",
    "wof:placetype":"locality"
},
  "geometry": {"coordinates":[-10.66667,10.98333],"type":"Point"}
}