{
  "type": "Feature",
  "properties": {
    "gn:admin1_code":"N",
    "gn:admin2_code":"01",
    "gn:asciiname":"Gouakedougou",
    "gn:country_code":"GN",
    "gn:dem":710,
    "gn:feature_class":"P",
    "gn:feature_code":"PPL",
    "gn:name":"Gouak\u00e9dougou",
    "gn:population":0,
    "gn:timezone":"Africa/Conakry",
    "iso:country":"GN",
    "wof:name":"Gouakedougou",
    "wof:placetype":"locality"
},
  "geometry": {"coordinates":[-8.45,8.75],"type":"Point"}
}