{
  "type": "Feature",
  "properties": {
    "gn:admin1_code":"N",
    "gn:admin2_code":"21",
    "gn:asciiname":"Dieboidou",
    "gn:country_code":"GN",
    "gn:dem":534,
    "gn:feature_class":"P",
    "gn:feature_code":"PPL",
    "gn:name":"Di\u00e9bo\u00efdou",
    "gn:population":0,
    "gn:timezone":"Africa/Conakry",
    "iso:country":"GN",
    "wof:name":"Dieboidou",
    "wof:placetype":"locality"
},
  "geometry": {"coordinates":[-9.06667,8.65],"type":"Point"}
}