{
  "type": "Feature",
  "properties": {
    "gn:admin1_code":"K",
    "gn:admin2_code":"39",
    "gn:asciiname":"Bokofele",
    "gn:country_code":"GN",
    "gn:dem":355,
    "gn:feature_class":"P",
    "gn:feature_code":"PPL",
    "gn:name":"Bokof\u00e9l\u00e9",
    "gn:population":0,
    "gn:timezone":"Africa/Conakry",
    "iso:country":"GN",
    "wof:name":"Bokofele",
    "wof:placetype":"locality"
},
  "geometry": {"coordinates":[-8.91667,12.01667],"type":"Point"}
}