{
  "type": "Feature",
  "properties": {
    "gn:admin1_code":"D",
    "gn:admin2_code":"10",
    "gn:asciiname":"Silemaneya",
    "gn:country_code":"GN",
    "gn:dem":10,
    "gn:feature_class":"P",
    "gn:feature_code":"PPL",
    "gn:name":"Sil\u00e9maneya",
    "gn:population":0,
    "gn:timezone":"Africa/Conakry",
    "iso:country":"GN",
    "wof:name":"Silemaneya",
    "wof:placetype":"locality"
},
  "geometry": {"coordinates":[-13.42444,9.41167],"type":"Point"}
}