{
  "type": "Feature",
  "properties": {
    "gn:admin1_code":"B",
    "gn:admin2_code":"02",
    "gn:asciiname":"Menkine",
    "gn:country_code":"GN",
    "gn:dem":23,
    "gn:feature_class":"P",
    "gn:feature_code":"PPL",
    "gn:name":"Menkin\u00e9",
    "gn:population":0,
    "gn:timezone":"Africa/Conakry",
    "iso:country":"GN",
    "wof:name":"Menkine",
    "wof:placetype":"locality"
},
  "geometry": {"coordinates":[-13.74028,9.92556],"type":"Point"}
}