{
  "type": "Feature",
  "properties": {
    "gn:admin1_code":"N",
    "gn:admin2_code":"13",
    "gn:asciiname":"Koroadou",
    "gn:country_code":"GN",
    "gn:dem":530,
    "gn:feature_class":"P",
    "gn:feature_code":"PPL",
    "gn:name":"Koroadou",
    "gn:population":0,
    "gn:timezone":"Africa/Conakry",
    "iso:country":"GN",
    "wof:name":"Koroadou",
    "wof:placetype":"locality"
},
  "geometry": {"coordinates":[-10.22917,8.92667],"type":"Point"}
}