{
  "type": "Feature",
  "properties": {
    "gn:admin1_code":"D",
    "gn:admin2_code":"10",
    "gn:asciiname":"Fokoufokou",
    "gn:country_code":"GN",
    "gn:dem":9,
    "gn:feature_class":"P",
    "gn:feature_code":"PPL",
    "gn:name":"Fokoufokou",
    "gn:population":0,
    "gn:timezone":"Africa/Conakry",
    "iso:country":"GN",
    "wof:name":"Fokoufokou",
    "wof:placetype":"locality"
},
  "geometry": {"coordinates":[-13.37944,9.50944],"type":"Point"}
}