{
  "type": "Feature",
  "properties": {
    "gn:admin1_code":"N",
    "gn:admin2_code":"21",
    "gn:asciiname":"Assaouma",
    "gn:country_code":"GN",
    "gn:dem":611,
    "gn:feature_class":"P",
    "gn:feature_code":"PPL",
    "gn:name":"Assaouma",
    "gn:population":0,
    "gn:timezone":"Africa/Conakry",
    "iso:country":"GN",
    "wof:name":"Assaouma",
    "wof:placetype":"locality"
},
  "geometry": {"coordinates":[-9.79056,8.64139],"type":"Point"}
}