{
  "type": "Feature",
  "properties": {
    "gn:admin1_code":"K",
    "gn:admin2_code":"32",
    "gn:asciiname":"Kaala",
    "gn:country_code":"GN",
    "gn:dem":502,
    "gn:feature_class":"P",
    "gn:feature_code":"PPL",
    "gn:name":"Kaala",
    "gn:population":0,
    "gn:timezone":"Africa/Conakry",
    "iso:country":"GN",
    "name:und_x_variant":[
        "Kala",
        "Kaala"
    ],
    "wof:name":"Kaala",
    "wof:placetype":"locality"
},
  "geometry": {"coordinates":[-9.23333,9.88333],"type":"Point"}
}