{
  "type": "Feature",
  "properties": {
    "gn:admin1_code":"N",
    "gn:admin2_code":"21",
    "gn:asciiname":"Ouzaroulazou",
    "gn:cc2":"GN",
    "gn:country_code":"GN",
    "gn:dem":553,
    "gn:feature_class":"P",
    "gn:feature_code":"PPL",
    "gn:name":"Ouzaroulazou",
    "gn:population":0,
    "gn:timezone":"Africa/Conakry",
    "iso:country":"GN",
    "name:und_x_variant":[
        "S\u00e9pa",
        "Ouzaourazou",
        "Ouzaourassou",
        "Ouzaroulazou"
    ],
    "wof:name":"Ouzaroulazou",
    "wof:placetype":"locality"
},
  "geometry": {"coordinates":[-9.74944,8.71944],"type":"Point"}
}