{
  "type": "Feature",
  "properties": {
    "gn:admin1_code":"K",
    "gn:admin2_code":"39",
    "gn:asciiname":"Nenea",
    "gn:country_code":"GN",
    "gn:dem":368,
    "gn:feature_class":"P",
    "gn:feature_code":"PPL",
    "gn:name":"N\u00e9n\u00e9a",
    "gn:population":0,
    "gn:timezone":"Africa/Conakry",
    "iso:country":"GN",
    "wof:name":"Nenea",
    "wof:placetype":"locality"
},
  "geometry": {"coordinates":[-9.76667,11.71667],"type":"Point"}
}