{
  "type": "Feature",
  "properties": {
    "gn:admin1_code":"D",
    "gn:admin2_code":"16",
    "gn:asciiname":"Lefure",
    "gn:cc2":"GN",
    "gn:country_code":"GN",
    "gn:dem":347,
    "gn:feature_class":"P",
    "gn:feature_code":"PPL",
    "gn:name":"L\u00e9fur\u00e9",
    "gn:population":0,
    "gn:timezone":"Africa/Conakry",
    "iso:country":"GN",
    "name:und_x_variant":[
        "L\u00e9four\u00e9",
        "L\u00e9fur\u00e9"
    ],
    "wof:name":"Lefure",
    "wof:placetype":"locality"
},
  "geometry": {"coordinates":[-12.65,10.55],"type":"Point"}
}