{
  "type": "Feature",
  "properties": {
    "gn:admin1_code":"K",
    "gn:admin2_code":"37",
    "gn:asciiname":"Faragouekoro",
    "gn:country_code":"GN",
    "gn:dem":349,
    "gn:feature_class":"P",
    "gn:feature_code":"PPL",
    "gn:name":"Faragou\u00e9koro",
    "gn:population":0,
    "gn:timezone":"Africa/Conakry",
    "iso:country":"GN",
    "wof:name":"Faragouekoro",
    "wof:placetype":"locality"
},
  "geometry": {"coordinates":[-8.61667,11.36667],"type":"Point"}
}