{
  "type": "Feature",
  "properties": {
    "gn:admin1_code":"K",
    "gn:admin2_code":"07",
    "gn:asciiname":"Tombaguia Foula",
    "gn:country_code":"GN",
    "gn:dem":438,
    "gn:feature_class":"P",
    "gn:feature_code":"PPL",
    "gn:name":"Tombaguia Foula",
    "gn:population":0,
    "gn:timezone":"Africa/Conakry",
    "iso:country":"GN",
    "wof:name":"Tombaguia Foula",
    "wof:placetype":"locality"
},
  "geometry": {"coordinates":[-10.11667,11.68333],"type":"Point"}
}