{
  "type": "Feature",
  "properties": {
    "gn:admin1_code":"L",
    "gn:admin2_code":"35",
    "gn:asciiname":"Koukama",
    "gn:country_code":"GN",
    "gn:dem":659,
    "gn:feature_class":"P",
    "gn:feature_code":"PPL",
    "gn:name":"Koukama",
    "gn:population":0,
    "gn:timezone":"Africa/Conakry",
    "iso:country":"GN",
    "wof:name":"Koukama",
    "wof:placetype":"locality"
},
  "geometry": {"coordinates":[-12.73333,11.25],"type":"Point"}
}