{
  "type": "Feature",
  "properties": {
    "gn:admin1_code":"F",
    "gn:admin2_code":"17",
    "gn:asciiname":"Kissene",
    "gn:country_code":"GN",
    "gn:dem":486,
    "gn:feature_class":"P",
    "gn:feature_code":"PPL",
    "gn:name":"Kiss\u00e9n\u00e8",
    "gn:population":0,
    "gn:timezone":"Africa/Conakry",
    "iso:country":"GN",
    "wof:name":"Kissene",
    "wof:placetype":"locality"
},
  "geometry": {"coordinates":[-9.98333,8.88333],"type":"Point"}
}