{
  "type": "Feature",
  "properties": {
    "gn:admin1_code":"K",
    "gn:admin2_code":"01",
    "gn:asciiname":"Mathenian Baladou",
    "gn:country_code":"GN",
    "gn:dem":640,
    "gn:feature_class":"P",
    "gn:feature_code":"PPL",
    "gn:name":"Math\u00e9nian Baladou",
    "gn:population":0,
    "gn:timezone":"Africa/Conakry",
    "iso:country":"GN",
    "name:und_x_variant":[
        "Baladou",
        "Math\u00e9nian Baladou"
    ],
    "wof:name":"Mathenian Baladou",
    "wof:placetype":"locality"
},
  "geometry": {"coordinates":[-9.02806,8.92528],"type":"Point"}
}