{
  "type": "Feature",
  "properties": {
    "gn:admin1_code":"M",
    "gn:admin2_code":"25",
    "gn:asciiname":"Brourouve",
    "gn:country_code":"GN",
    "gn:dem":788,
    "gn:feature_class":"P",
    "gn:feature_code":"PPL",
    "gn:name":"Brourouv\u00e9",
    "gn:population":0,
    "gn:timezone":"Africa/Conakry",
    "iso:country":"GN",
    "wof:name":"Brourouve",
    "wof:placetype":"locality"
},
  "geometry": {"coordinates":[-12.71667,11.15],"type":"Point"}
}