{
  "type": "Feature",
  "properties": {
    "gn:admin1_code":"L",
    "gn:admin2_code":"22",
    "gn:asciiname":"Parawol",
    "gn:country_code":"GN",
    "gn:dem":1239,
    "gn:feature_class":"P",
    "gn:feature_code":"PPL",
    "gn:name":"Parawol",
    "gn:population":0,
    "gn:timezone":"Africa/Conakry",
    "iso:country":"GN",
    "name:fra_x_preferred":[
        "Parawol"
    ],
    "name:ita_x_preferred":[
        "Parawol"
    ],
    "name:msa_x_preferred":[
        "Parawol"
    ],
    "name:spa_x_preferred":[
        "Parawol"
    ],
    "wof:name":"Parawol",
    "wof:placetype":"locality"
},
  "geometry": {"coordinates":[-12.3306,12.0844],"type":"Point"}
}