{
  "type": "Feature",
  "properties": {
    "gn:admin1_code":"K",
    "gn:admin2_code":"17",
    "gn:asciiname":"Sibirikoya",
    "gn:country_code":"GN",
    "gn:dem":564,
    "gn:feature_class":"P",
    "gn:feature_code":"PPL",
    "gn:name":"Sibirikoya",
    "gn:population":0,
    "gn:timezone":"Africa/Conakry",
    "iso:country":"GN",
    "wof:name":"Sibirikoya",
    "wof:placetype":"locality"
},
  "geometry": {"coordinates":[-9.61667,9.43333],"type":"Point"}
}