{
  "type": "Feature",
  "properties": {
    "gn:admin1_code":"F",
    "gn:admin2_code":"07",
    "gn:asciiname":"Diafounabe",
    "gn:country_code":"GN",
    "gn:dem":590,
    "gn:feature_class":"P",
    "gn:feature_code":"PPL",
    "gn:name":"Diafounab\u00e9",
    "gn:population":0,
    "gn:timezone":"Africa/Conakry",
    "iso:country":"GN",
    "wof:name":"Diafounabe",
    "wof:placetype":"locality"
},
  "geometry": {"coordinates":[-10.73333,11.33333],"type":"Point"}
}