{
  "type": "Feature",
  "properties": {
    "gn:admin1_code":"K",
    "gn:admin2_code":"19",
    "gn:asciiname":"Sembafagatou",
    "gn:country_code":"GN",
    "gn:dem":426,
    "gn:feature_class":"P",
    "gn:feature_code":"PPL",
    "gn:name":"Sembafagatou",
    "gn:population":0,
    "gn:timezone":"Africa/Conakry",
    "iso:country":"GN",
    "wof:name":"Sembafagatou",
    "wof:placetype":"locality"
},
  "geometry": {"coordinates":[-9.96667,11.05],"type":"Point"}
}