{
  "type": "Feature",
  "properties": {
    "gn:admin1_code":"N",
    "gn:admin2_code":"13",
    "gn:asciiname":"Yomandou",
    "gn:cc2":"GN",
    "gn:country_code":"GN",
    "gn:dem":406,
    "gn:feature_class":"P",
    "gn:feature_code":"PPL",
    "gn:name":"Yomandou",
    "gn:population":0,
    "gn:timezone":"Africa/Conakry",
    "iso:country":"GN",
    "name:und_x_variant":[
        "Yomadou",
        "Yomandou"
    ],
    "wof:name":"Yomandou",
    "wof:placetype":"locality"
},
  "geometry": {"coordinates":[-10.47194,8.94611],"type":"Point"}
}