{
  "type": "Feature",
  "properties": {
    "gn:admin1_code":"K",
    "gn:admin2_code":"07",
    "gn:asciiname":"Bafe",
    "gn:country_code":"GN",
    "gn:dem":406,
    "gn:feature_class":"P",
    "gn:feature_code":"PPL",
    "gn:name":"Baf\u00e9",
    "gn:population":0,
    "gn:timezone":"Africa/Conakry",
    "iso:country":"GN",
    "wof:name":"Bafe",
    "wof:placetype":"locality"
},
  "geometry": {"coordinates":[-10.03333,12.01667],"type":"Point"}
}