{
  "type": "Feature",
  "properties": {
    "gn:admin1_code":"N",
    "gn:admin2_code":"13",
    "gn:asciiname":"Kiessane",
    "gn:country_code":"GN",
    "gn:dem":511,
    "gn:feature_class":"P",
    "gn:feature_code":"PPL",
    "gn:name":"Ki\u00e9ssan\u00e9",
    "gn:population":0,
    "gn:timezone":"Africa/Conakry",
    "iso:country":"GN",
    "wof:name":"Kiessane",
    "wof:placetype":"locality"
},
  "geometry": {"coordinates":[-10.0625,8.75111],"type":"Point"}
}