{
  "type": "Feature",
  "properties": {
    "gn:admin1_code":"K",
    "gn:admin2_code":"39",
    "gn:asciiname":"Soukouraba",
    "gn:country_code":"GN",
    "gn:dem":387,
    "gn:feature_class":"P",
    "gn:feature_code":"PPL",
    "gn:name":"Soukouraba",
    "gn:population":0,
    "gn:timezone":"Africa/Conakry",
    "iso:country":"GN",
    "wof:name":"Soukouraba",
    "wof:placetype":"locality"
},
  "geometry": {"coordinates":[-8.88333,11.15],"type":"Point"}
}