{
  "type": "Feature",
  "properties": {
    "gn:admin1_code":"K",
    "gn:admin2_code":"17",
    "gn:asciiname":"Guibaya",
    "gn:country_code":"GN",
    "gn:dem":799,
    "gn:feature_class":"P",
    "gn:feature_code":"PPL",
    "gn:name":"Guibaya",
    "gn:population":0,
    "gn:timezone":"Africa/Conakry",
    "iso:country":"GN",
    "wof:name":"Guibaya",
    "wof:placetype":"locality"
},
  "geometry": {"coordinates":[-9.46306,8.94722],"type":"Point"}
}