{
  "type": "Feature",
  "properties": {
    "gn:admin1_code":"M",
    "gn:admin2_code":"06",
    "gn:asciiname":"Lele",
    "gn:country_code":"GN",
    "gn:dem":1028,
    "gn:feature_class":"P",
    "gn:feature_code":"PPL",
    "gn:name":"L\u00e9l\u00e9",
    "gn:population":0,
    "gn:timezone":"Africa/Conakry",
    "iso:country":"GN",
    "wof:name":"Lele",
    "wof:placetype":"locality"
},
  "geometry": {"coordinates":[-12.35,10.66667],"type":"Point"}
}