{
  "type": "Feature",
  "properties": {
    "gn:admin1_code":"N",
    "gn:admin2_code":"01",
    "gn:asciiname":"Sekoudougou",
    "gn:country_code":"GN",
    "gn:dem":709,
    "gn:feature_class":"P",
    "gn:feature_code":"PPL",
    "gn:name":"S\u00e9koudougou",
    "gn:population":0,
    "gn:timezone":"Africa/Conakry",
    "iso:country":"GN",
    "wof:name":"Sekoudougou",
    "wof:placetype":"locality"
},
  "geometry": {"coordinates":[-8.41667,8.83333],"type":"Point"}
}