{
  "type": "Feature",
  "properties": {
    "gn:admin1_code":"N",
    "gn:admin2_code":"21",
    "gn:asciiname":"Karapilita",
    "gn:country_code":"GN",
    "gn:dem":534,
    "gn:feature_class":"P",
    "gn:feature_code":"PPL",
    "gn:name":"Karapilita",
    "gn:population":0,
    "gn:timezone":"Africa/Conakry",
    "iso:country":"GN",
    "wof:name":"Karapilita",
    "wof:placetype":"locality"
},
  "geometry": {"coordinates":[-9.07694,8.40167],"type":"Point"}
}