{
  "type": "Feature",
  "properties": {
    "gn:admin1_code":"M",
    "gn:admin2_code":"23",
    "gn:asciiname":"Dantare",
    "gn:country_code":"GN",
    "gn:dem":769,
    "gn:feature_class":"P",
    "gn:feature_code":"PPL",
    "gn:name":"Dantar\u00e9",
    "gn:population":0,
    "gn:timezone":"Africa/Conakry",
    "iso:country":"GN",
    "wof:name":"Dantare",
    "wof:placetype":"locality"
},
  "geometry": {"coordinates":[-12.16667,10.41667],"type":"Point"}
}