{
  "type": "Feature",
  "properties": {
    "gn:admin1_code":"K",
    "gn:admin2_code":"37",
    "gn:asciiname":"Marina",
    "gn:country_code":"GN",
    "gn:dem":381,
    "gn:feature_class":"P",
    "gn:feature_code":"PPL",
    "gn:name":"Marina",
    "gn:population":0,
    "gn:timezone":"Africa/Conakry",
    "iso:country":"GN",
    "name:und_x_variant":[
        "Mar\u00e9na",
        "Marina"
    ],
    "wof:name":"Marina",
    "wof:placetype":"locality"
},
  "geometry": {"coordinates":[-8.83333,10.65],"type":"Point"}
}