{
  "type": "Feature",
  "properties": {
    "gn:admin1_code":"D",
    "gn:admin2_code":"31",
    "gn:asciiname":"Solokhire",
    "gn:country_code":"GN",
    "gn:dem":2,
    "gn:feature_class":"P",
    "gn:feature_code":"PPL",
    "gn:name":"Solokhir\u00e9",
    "gn:population":0,
    "gn:timezone":"Africa/Conakry",
    "iso:country":"GN",
    "wof:name":"Solokhire",
    "wof:placetype":"locality"
},
  "geometry": {"coordinates":[-13.63583,9.81806],"type":"Point"}
}