{
  "type": "Feature",
  "properties": {
    "gn:admin1_code":"N",
    "gn:admin2_code":"21",
    "gn:asciiname":"Baignema",
    "gn:cc2":"GN",
    "gn:country_code":"GN",
    "gn:dem":502,
    "gn:feature_class":"P",
    "gn:feature_code":"PPL",
    "gn:name":"Ba\u00efgnema",
    "gn:population":0,
    "gn:timezone":"Africa/Conakry",
    "iso:country":"GN",
    "name:und_x_variant":[
        "Bagu\u00e9",
        "Ba\u00efgnema"
    ],
    "wof:name":"Baignema",
    "wof:placetype":"locality"
},
  "geometry": {"coordinates":[-9.27111,8.13333],"type":"Point"}
}