{
  "type": "Feature",
  "properties": {
    "gn:admin1_code":"N",
    "gn:admin2_code":"13",
    "gn:asciiname":"Konkesse",
    "gn:country_code":"GN",
    "gn:dem":511,
    "gn:feature_class":"P",
    "gn:feature_code":"PPL",
    "gn:name":"Konk\u00e8sse",
    "gn:population":0,
    "gn:timezone":"Africa/Conakry",
    "iso:country":"GN",
    "wof:name":"Konkesse",
    "wof:placetype":"locality"
},
  "geometry": {"coordinates":[-9.96667,8.71667],"type":"Point"}
}