{
  "type": "Feature",
  "properties": {
    "gn:admin1_code":"N",
    "gn:admin2_code":"13",
    "gn:asciiname":"Poa",
    "gn:country_code":"GN",
    "gn:dem":436,
    "gn:feature_class":"P",
    "gn:feature_code":"PPL",
    "gn:name":"Poa",
    "gn:population":0,
    "gn:timezone":"Africa/Conakry",
    "iso:country":"GN",
    "wof:name":"Poa",
    "wof:placetype":"locality"
},
  "geometry": {"coordinates":[-10.16667,8.53333],"type":"Point"}
}