{
  "type": "Feature",
  "properties": {
    "gn:admin1_code":"K",
    "gn:admin2_code":"37",
    "gn:asciiname":"Denso",
    "gn:country_code":"GN",
    "gn:dem":399,
    "gn:feature_class":"P",
    "gn:feature_code":"PPL",
    "gn:name":"Denso",
    "gn:population":0,
    "gn:timezone":"Africa/Conakry",
    "iso:country":"GN",
    "wof:name":"Denso",
    "wof:placetype":"locality"
},
  "geometry": {"coordinates":[-8.38333,10.96667],"type":"Point"}
}