{
  "type": "Feature",
  "properties": {
    "gn:admin1_code":"K",
    "gn:admin2_code":"37",
    "gn:asciiname":"Denso",
    "gn:country_code":"GN",
    "gn:dem":399,
    "gn:feature_class":"P",
    "gn:feature_code":"PPL",
    "gn:name":"Denso",
    "gn:population":0,
    "gn:timezone":"Africa/Conakry",
    "iso:country":"GN",
    "name:afr_x_preferred":[
        "DENSO Corporation"
    ],
    "name:ara_x_preferred":[
        "\u062f\u0646\u0633\u0648"
    ],
    "name:cat_x_preferred":[
        "Denso Corporation"
    ],
    "name:dan_x_preferred":[
        "Denso"
    ],
    "name:deu_x_preferred":[
        "Denso"
    ],
    "name:fas_x_preferred":[
        "\u062f\u0646\u0633\u0648"
    ],
    "name:fin_x_preferred":[
        "Denso"
    ],
    "name:fra_x_preferred":[
        "Denso Corporation"
    ],
    "name:hun_x_preferred":[
        "Denso"
    ],
    "name:ind_x_preferred":[
        "Denso"
    ],
    "name:ita_x_preferred":[
        "Denso"
    ],
    "name:jpn_x_preferred":[
        "\u30c7\u30f3\u30bd\u30fc"
    ],
    "name:msa_x_preferred":[
        "Denso"
    ],
    "name:nld_x_preferred":[
        "Denso"
    ],
    "name:pol_x_preferred":[
        "Denso"
    ],
    "name:por_x_preferred":[
        "Denso"
    ],
    "name:rus_x_preferred":[
        "Denso"
    ],
    "name:spa_x_preferred":[
        "Denso Corporation"
    ],
    "name:tur_x_preferred":[
        "Denso"
    ],
    "name:ukr_x_preferred":[
        "Denso"
    ],
    "wof:name":"Denso",
    "wof:placetype":"locality"
},
  "geometry": {"coordinates":[-8.38333,10.96667],"type":"Point"}
}