{
  "type": "Feature",
  "properties": {
    "gn:admin1_code":"B",
    "gn:admin2_code":"03",
    "gn:asciiname":"Doumba Diolo",
    "gn:cc2":"GN",
    "gn:country_code":"GN",
    "gn:dem":223,
    "gn:feature_class":"P",
    "gn:feature_code":"PPL",
    "gn:name":"Doumba Diolo",
    "gn:population":0,
    "gn:timezone":"Africa/Conakry",
    "iso:country":"GN",
    "name:und_x_variant":[
        "Bensan\u00e9",
        "B\u00e9nnsan\u00e9",
        "Doumba Diolo"
    ],
    "wof:name":"Doumba Diolo",
    "wof:placetype":"locality"
},
  "geometry": {"coordinates":[-13.95,11.45],"type":"Point"}
}