{
  "type": "Feature",
  "properties": {
    "gn:admin1_code":"K",
    "gn:admin2_code":"39",
    "gn:asciiname":"Bouteda",
    "gn:country_code":"GN",
    "gn:dem":640,
    "gn:feature_class":"P",
    "gn:feature_code":"PPL",
    "gn:name":"Bout\u00e9da",
    "gn:population":0,
    "gn:timezone":"Africa/Conakry",
    "iso:country":"GN",
    "wof:name":"Bouteda",
    "wof:placetype":"locality"
},
  "geometry": {"coordinates":[-9.73333,11.78333],"type":"Point"}
}