{
  "type": "Feature",
  "properties": {
    "gn:admin1_code":"F",
    "gn:admin2_code":"09",
    "gn:asciiname":"Sansanko",
    "gn:country_code":"GN",
    "gn:dem":448,
    "gn:feature_class":"P",
    "gn:feature_code":"PPL",
    "gn:name":"Sansanko",
    "gn:population":0,
    "gn:timezone":"Africa/Conakry",
    "iso:country":"GN",
    "wof:name":"Sansanko",
    "wof:placetype":"locality"
},
  "geometry": {"coordinates":[-10.65,10.26667],"type":"Point"}
}