{
  "type": "Feature",
  "properties": {
    "gn:admin1_code":"B",
    "gn:admin2_code":"03",
    "gn:asciiname":"Guebeya",
    "gn:cc2":"GN",
    "gn:country_code":"GN",
    "gn:dem":35,
    "gn:feature_class":"P",
    "gn:feature_code":"PPL",
    "gn:name":"Gu\u00e9b\u00e9ya",
    "gn:population":0,
    "gn:timezone":"Africa/Conakry",
    "iso:country":"GN",
    "name:und_x_variant":[
        "Guibia",
        "Gu\u00e9b\u00e9ya"
    ],
    "wof:name":"Guebeya",
    "wof:placetype":"locality"
},
  "geometry": {"coordinates":[-14.36667,10.65],"type":"Point"}
}