{
  "type": "Feature",
  "properties": {
    "gn:admin1_code":"B",
    "gn:admin2_code":"02",
    "gn:asciiname":"Koundinde",
    "gn:cc2":"GN",
    "gn:country_code":"GN",
    "gn:dem":1,
    "gn:feature_class":"P",
    "gn:feature_code":"PPL",
    "gn:name":"Koundind\u00e9",
    "gn:population":0,
    "gn:timezone":"Africa/Conakry",
    "iso:country":"GN",
    "name:und_x_variant":[
        "Koudind\u00e9",
        "Koundind\u00e9"
    ],
    "wof:name":"Koundinde",
    "wof:placetype":"locality"
},
  "geometry": {"coordinates":[-14.45,10.23333],"type":"Point"}
}