{
  "type": "Feature",
  "properties": {
    "gn:admin1_code":"L",
    "gn:admin2_code":"28",
    "gn:asciiname":"Kouratongo",
    "gn:country_code":"GN",
    "gn:dem":844,
    "gn:feature_class":"P",
    "gn:feature_code":"PPL",
    "gn:name":"Kouratongo",
    "gn:population":0,
    "gn:timezone":"Africa/Conakry",
    "iso:country":"GN",
    "wof:name":"Kouratongo",
    "wof:placetype":"locality"
},
  "geometry": {"coordinates":[-11.48333,11.63333],"type":"Point"}
}