{
  "type": "Feature",
  "properties": {
    "gn:admin1_code":"K",
    "gn:admin2_code":"37",
    "gn:asciiname":"Tindila",
    "gn:country_code":"GN",
    "gn:dem":405,
    "gn:feature_class":"P",
    "gn:feature_code":"PPL",
    "gn:name":"Tindila",
    "gn:population":0,
    "gn:timezone":"Africa/Conakry",
    "iso:country":"GN",
    "name:und_x_variant":[
        "Tindilla",
        "Tinila",
        "Tindila"
    ],
    "wof:name":"Tindila",
    "wof:placetype":"locality"
},
  "geometry": {"coordinates":[-8.25,10.26667],"type":"Point"}
}