{
  "type": "Feature",
  "properties": {
    "gn:admin1_code":"D",
    "gn:admin2_code":"10",
    "gn:asciiname":"Douadou",
    "gn:country_code":"GN",
    "gn:dem":37,
    "gn:feature_class":"P",
    "gn:feature_code":"PPL",
    "gn:name":"Douadou",
    "gn:population":0,
    "gn:timezone":"Africa/Conakry",
    "iso:country":"GN",
    "wof:name":"Douadou",
    "wof:placetype":"locality"
},
  "geometry": {"coordinates":[-13.08056,9.25667],"type":"Point"}
}