{
  "type": "Feature",
  "properties": {
    "gn:admin1_code":"F",
    "gn:admin2_code":"07",
    "gn:asciiname":"Maria",
    "gn:country_code":"GN",
    "gn:dem":431,
    "gn:feature_class":"P",
    "gn:feature_code":"PPL",
    "gn:name":"Maria",
    "gn:population":0,
    "gn:timezone":"Africa/Conakry",
    "iso:country":"GN",
    "wof:name":"Maria",
    "wof:placetype":"locality"
},
  "geometry": {"coordinates":[-10.83333,11.28333],"type":"Point"}
}