{
  "type": "Feature",
  "properties": {
    "gn:admin1_code":"N",
    "gn:admin2_code":"38",
    "gn:asciiname":"Niaragbaleye",
    "gn:country_code":"GN",
    "gn:dem":464,
    "gn:feature_class":"P",
    "gn:feature_code":"PPL",
    "gn:name":"Niaragbaleye",
    "gn:population":0,
    "gn:timezone":"Africa/Conakry",
    "iso:country":"GN",
    "wof:name":"Niaragbaleye",
    "wof:placetype":"locality"
},
  "geometry": {"coordinates":[-8.91667,8.01667],"type":"Point"}
}