{
  "type": "Feature",
  "properties": {
    "gn:admin1_code":"D",
    "gn:admin2_code":"30",
    "gn:asciiname":"Youmaya",
    "gn:country_code":"GN",
    "gn:dem":47,
    "gn:feature_class":"P",
    "gn:feature_code":"PPL",
    "gn:name":"Youmaya",
    "gn:population":0,
    "gn:timezone":"Africa/Conakry",
    "iso:country":"GN",
    "wof:name":"Youmaya",
    "wof:placetype":"locality"
},
  "geometry": {"coordinates":[-13.47694,9.85333],"type":"Point"}
}