{
  "type": "Feature",
  "properties": {
    "gn:admin1_code":"N",
    "gn:admin2_code":"13",
    "gn:asciiname":"Temessadou Toli",
    "gn:country_code":"GN",
    "gn:dem":410,
    "gn:feature_class":"P",
    "gn:feature_code":"PPL",
    "gn:name":"T\u00e9messadou Toli",
    "gn:population":0,
    "gn:timezone":"Africa/Conakry",
    "iso:country":"GN",
    "wof:name":"Temessadou Toli",
    "wof:placetype":"locality"
},
  "geometry": {"coordinates":[-10.30972,8.66556],"type":"Point"}
}