{
  "type": "Feature",
  "properties": {
    "gn:admin1_code":"N",
    "gn:admin2_code":"13",
    "gn:asciiname":"Yakadou",
    "gn:country_code":"GN",
    "gn:dem":546,
    "gn:feature_class":"P",
    "gn:feature_code":"PPL",
    "gn:name":"Yakadou",
    "gn:population":0,
    "gn:timezone":"Africa/Conakry",
    "iso:country":"GN",
    "wof:name":"Yakadou",
    "wof:placetype":"locality"
},
  "geometry": {"coordinates":[-9.95,8.76667],"type":"Point"}
}