{
  "type": "Feature",
  "properties": {
    "gn:admin1_code":"N",
    "gn:admin2_code":"01",
    "gn:asciiname":"Sanofilala",
    "gn:country_code":"GN",
    "gn:dem":712,
    "gn:feature_class":"P",
    "gn:feature_code":"PPL",
    "gn:name":"Sanofilala",
    "gn:population":0,
    "gn:timezone":"Africa/Conakry",
    "iso:country":"GN",
    "wof:name":"Sanofilala",
    "wof:placetype":"locality"
},
  "geometry": {"coordinates":[-8.38333,8.95],"type":"Point"}
}