{
  "type": "Feature",
  "properties": {
    "gn:admin1_code":"B",
    "gn:admin2_code":"03",
    "gn:asciiname":"Katchek",
    "gn:cc2":"GN",
    "gn:country_code":"GN",
    "gn:dem":12,
    "gn:feature_class":"P",
    "gn:feature_code":"PPL",
    "gn:name":"Katchek",
    "gn:population":0,
    "gn:timezone":"Africa/Conakry",
    "iso:country":"GN",
    "name:und_x_variant":[
        "Catchek",
        "Franceville",
        "Kakich",
        "Katchek"
    ],
    "wof:name":"Katchek",
    "wof:placetype":"locality"
},
  "geometry": {"coordinates":[-15.06667,10.88333],"type":"Point"}
}