{
  "type": "Feature",
  "properties": {
    "gn:admin1_code":"F",
    "gn:admin2_code":"09",
    "gn:asciiname":"Kamere Kounia",
    "gn:country_code":"GN",
    "gn:dem":494,
    "gn:feature_class":"P",
    "gn:feature_code":"PPL",
    "gn:name":"Kam\u00e9r\u00e9 Kounia",
    "gn:population":0,
    "gn:timezone":"Africa/Conakry",
    "iso:country":"GN",
    "wof:name":"Kamere Kounia",
    "wof:placetype":"locality"
},
  "geometry": {"coordinates":[-10.58333,10.01667],"type":"Point"}
}