{
  "type": "Feature",
  "properties": {
    "gn:admin1_code":"K",
    "gn:admin2_code":"37",
    "gn:asciiname":"Noumoudjiguila",
    "gn:country_code":"GN",
    "gn:dem":439,
    "gn:feature_class":"P",
    "gn:feature_code":"PPL",
    "gn:name":"Noumoudjiguila",
    "gn:population":0,
    "gn:timezone":"Africa/Conakry",
    "iso:country":"GN",
    "wof:name":"Noumoudjiguila",
    "wof:placetype":"locality"
},
  "geometry": {"coordinates":[-8.05,10.11667],"type":"Point"}
}