{
  "type": "Feature",
  "properties": {
    "gn:admin1_code":"L",
    "gn:admin2_code":"22",
    "gn:asciiname":"Kanso",
    "gn:country_code":"GN",
    "gn:dem":842,
    "gn:feature_class":"P",
    "gn:feature_code":"PPL",
    "gn:name":"Kanso",
    "gn:population":0,
    "gn:timezone":"Africa/Conakry",
    "iso:country":"GN",
    "wof:name":"Kanso",
    "wof:placetype":"locality"
},
  "geometry": {"coordinates":[-12.4058,12.0459],"type":"Point"}
}