{
  "type": "Feature",
  "properties": {
    "gn:admin1_code":"K",
    "gn:admin2_code":"37",
    "gn:asciiname":"Tassilima",
    "gn:country_code":"GN",
    "gn:dem":357,
    "gn:feature_class":"P",
    "gn:feature_code":"PPL",
    "gn:name":"Tassilima",
    "gn:population":0,
    "gn:timezone":"Africa/Conakry",
    "iso:country":"GN",
    "name:und_x_variant":[
        "Tassilman",
        "Tassiliman",
        "Tassilima"
    ],
    "wof:name":"Tassilima",
    "wof:placetype":"locality"
},
  "geometry": {"coordinates":[-9.21667,10.78333],"type":"Point"}
}