{
  "type": "Feature",
  "properties": {
    "gn:admin1_code":"K",
    "gn:admin2_code":"32",
    "gn:asciiname":"Farala",
    "gn:country_code":"GN",
    "gn:dem":411,
    "gn:feature_class":"P",
    "gn:feature_code":"PPL",
    "gn:name":"Farala",
    "gn:population":0,
    "gn:timezone":"Africa/Conakry",
    "iso:country":"GN",
    "wof:name":"Farala",
    "wof:placetype":"locality"
},
  "geometry": {"coordinates":[-8.55,9.88333],"type":"Point"}
}