{
  "type": "Feature",
  "properties": {
    "gn:admin1_code":"D",
    "gn:admin2_code":"10",
    "gn:asciiname":"Kompaya",
    "gn:country_code":"GN",
    "gn:dem":15,
    "gn:feature_class":"P",
    "gn:feature_code":"PPL",
    "gn:name":"Kompaya",
    "gn:population":0,
    "gn:timezone":"Africa/Conakry",
    "iso:country":"GN",
    "wof:name":"Kompaya",
    "wof:placetype":"locality"
},
  "geometry": {"coordinates":[-13.18583,9.28528],"type":"Point"}
}