{
  "type": "Feature",
  "properties": {
    "gn:admin1_code":"F",
    "gn:admin2_code":"17",
    "gn:asciiname":"Firaoua",
    "gn:country_code":"GN",
    "gn:dem":617,
    "gn:feature_class":"P",
    "gn:feature_code":"PPL",
    "gn:name":"Firaoua",
    "gn:population":0,
    "gn:timezone":"Africa/Conakry",
    "iso:country":"GN",
    "wof:name":"Firaoua",
    "wof:placetype":"locality"
},
  "geometry": {"coordinates":[-9.95,8.96667],"type":"Point"}
}