{
  "type": "Feature",
  "properties": {
    "gn:admin1_code":"K",
    "gn:admin2_code":"19",
    "gn:asciiname":"Koubi",
    "gn:country_code":"GN",
    "gn:dem":413,
    "gn:feature_class":"P",
    "gn:feature_code":"PPL",
    "gn:name":"Koubi",
    "gn:population":0,
    "gn:timezone":"Africa/Conakry",
    "iso:country":"GN",
    "wof:name":"Koubi",
    "wof:placetype":"locality"
},
  "geometry": {"coordinates":[-10.48333,11.13333],"type":"Point"}
}