{
  "type": "Feature",
  "properties": {
    "gn:admin1_code":"N",
    "gn:admin2_code":"13",
    "gn:asciiname":"Nioumatanga",
    "gn:country_code":"GN",
    "gn:dem":483,
    "gn:feature_class":"P",
    "gn:feature_code":"PPL",
    "gn:name":"Nioumatanga",
    "gn:population":0,
    "gn:timezone":"Africa/Conakry",
    "iso:country":"GN",
    "wof:name":"Nioumatanga",
    "wof:placetype":"locality"
},
  "geometry": {"coordinates":[-10.15694,8.74028],"type":"Point"}
}