{
  "type": "Feature",
  "properties": {
    "gn:admin1_code":"B",
    "gn:admin2_code":"18",
    "gn:asciiname":"Sarebodio",
    "gn:country_code":"GN",
    "gn:dem":87,
    "gn:feature_class":"P",
    "gn:feature_code":"PPL",
    "gn:name":"Sarebodio",
    "gn:population":0,
    "gn:timezone":"Africa/Conakry",
    "iso:country":"GN",
    "wof:name":"Sarebodio",
    "wof:placetype":"locality"
},
  "geometry": {"coordinates":[-13.52606,12.40397],"type":"Point"}
}