{
  "type": "Feature",
  "properties": {
    "gn:admin1_code":"L",
    "gn:admin2_code":"22",
    "gn:asciiname":"Rounde-Here",
    "gn:country_code":"GN",
    "gn:dem":604,
    "gn:feature_class":"P",
    "gn:feature_code":"PPL",
    "gn:name":"Round\u00e9-H\u00e9r\u00e9",
    "gn:population":0,
    "gn:timezone":"Africa/Conakry",
    "iso:country":"GN",
    "wof:name":"Rounde-Here",
    "wof:placetype":"locality"
},
  "geometry": {"coordinates":[-12.4164,12.0959],"type":"Point"}
}