{
  "type": "Feature",
  "properties": {
    "gn:admin1_code":"D",
    "gn:admin2_code":"16",
    "gn:asciiname":"Linsan",
    "gn:cc2":"GN",
    "gn:country_code":"GN",
    "gn:dem":419,
    "gn:feature_class":"P",
    "gn:feature_code":"PPL",
    "gn:name":"Linsan",
    "gn:population":0,
    "gn:timezone":"Africa/Conakry",
    "iso:country":"GN",
    "name:und_x_variant":[
        "La Linsan",
        "Linsan"
    ],
    "wof:name":"Linsan",
    "wof:placetype":"locality"
},
  "geometry": {"coordinates":[-12.43333,10.28333],"type":"Point"}
}