{
  "type": "Feature",
  "properties": {
    "gn:admin1_code":"N",
    "gn:admin2_code":"21",
    "gn:asciiname":"Bokoezia",
    "gn:country_code":"GN",
    "gn:dem":641,
    "gn:feature_class":"P",
    "gn:feature_code":"PPL",
    "gn:name":"Boko\u00e9zia",
    "gn:population":0,
    "gn:timezone":"Africa/Conakry",
    "iso:country":"GN",
    "wof:name":"Bokoezia",
    "wof:placetype":"locality"
},
  "geometry": {"coordinates":[-9.76667,8.78333],"type":"Point"}
}