{
  "type": "Feature",
  "properties": {
    "gn:admin1_code":"N",
    "gn:admin2_code":"21",
    "gn:asciiname":"Koelazou",
    "gn:country_code":"GN",
    "gn:dem":625,
    "gn:feature_class":"P",
    "gn:feature_code":"PPL",
    "gn:name":"Ko\u00e8lazou",
    "gn:population":0,
    "gn:timezone":"Africa/Conakry",
    "iso:country":"GN",
    "wof:name":"Koelazou",
    "wof:placetype":"locality"
},
  "geometry": {"coordinates":[-9.77278,8.79389],"type":"Point"}
}