{
  "type": "Feature",
  "properties": {
    "gn:admin1_code":"D",
    "gn:admin2_code":"10",
    "gn:asciiname":"Timboima",
    "gn:country_code":"GN",
    "gn:dem":2,
    "gn:feature_class":"P",
    "gn:feature_code":"PPL",
    "gn:name":"Timbo\u00efma",
    "gn:population":0,
    "gn:timezone":"Africa/Conakry",
    "iso:country":"GN",
    "wof:name":"Timboima",
    "wof:placetype":"locality"
},
  "geometry": {"coordinates":[-13.45833,9.43972],"type":"Point"}
}