{
  "type": "Feature",
  "properties": {
    "gn:admin1_code":"K",
    "gn:admin2_code":"01",
    "gn:asciiname":"Biramadougou",
    "gn:country_code":"GN",
    "gn:dem":375,
    "gn:feature_class":"P",
    "gn:feature_code":"PPL",
    "gn:name":"Biramadougou",
    "gn:population":0,
    "gn:timezone":"Africa/Conakry",
    "iso:country":"GN",
    "wof:name":"Biramadougou",
    "wof:placetype":"locality"
},
  "geometry": {"coordinates":[-8.16667,12.03333],"type":"Point"}
}