{
  "type": "Feature",
  "properties": {
    "gn:admin1_code":"K",
    "gn:admin2_code":"15",
    "gn:asciiname":"Tieoulindougou",
    "gn:country_code":"GN",
    "gn:dem":537,
    "gn:feature_class":"P",
    "gn:feature_code":"PPL",
    "gn:name":"Ti\u00e9oulindougou",
    "gn:population":0,
    "gn:timezone":"Africa/Conakry",
    "iso:country":"GN",
    "wof:name":"Tieoulindougou",
    "wof:placetype":"locality"
},
  "geometry": {"coordinates":[-8.96667,9.43333],"type":"Point"}
}