{
  "type": "Feature",
  "properties": {
    "gn:admin1_code":"K",
    "gn:admin2_code":"07",
    "gn:asciiname":"Niougourou",
    "gn:country_code":"GN",
    "gn:dem":439,
    "gn:feature_class":"P",
    "gn:feature_code":"PPL",
    "gn:name":"Niougourou",
    "gn:population":0,
    "gn:timezone":"Africa/Conakry",
    "iso:country":"GN",
    "wof:name":"Niougourou",
    "wof:placetype":"locality"
},
  "geometry": {"coordinates":[-10.08333,12.08333],"type":"Point"}
}