{
  "type": "Feature",
  "properties": {
    "gn:admin1_code":"N",
    "gn:admin2_code":"21",
    "gn:asciiname":"Sassama",
    "gn:country_code":"GN",
    "gn:dem":602,
    "gn:feature_class":"P",
    "gn:feature_code":"PPL",
    "gn:name":"Sassama",
    "gn:population":0,
    "gn:timezone":"Africa/Conakry",
    "iso:country":"GN",
    "wof:name":"Sassama",
    "wof:placetype":"locality"
},
  "geometry": {"coordinates":[-9.46194,8.6725],"type":"Point"}
}