{
  "type": "Feature",
  "properties": {
    "gn:admin1_code":"D",
    "gn:admin2_code":"16",
    "gn:asciiname":"Karimouya",
    "gn:country_code":"GN",
    "gn:dem":646,
    "gn:feature_class":"P",
    "gn:feature_code":"PPL",
    "gn:name":"Karimouya",
    "gn:population":0,
    "gn:timezone":"Africa/Conakry",
    "iso:country":"GN",
    "wof:name":"Karimouya",
    "wof:placetype":"locality"
},
  "geometry": {"coordinates":[-12.26667,10.03333],"type":"Point"}
}