{
  "type": "Feature",
  "properties": {
    "gn:admin1_code":"L",
    "gn:admin2_code":"22",
    "gn:asciiname":"Linsan",
    "gn:country_code":"GN",
    "gn:dem":465,
    "gn:feature_class":"P",
    "gn:feature_code":"PPL",
    "gn:name":"Linsan",
    "gn:population":0,
    "gn:timezone":"Africa/Conakry",
    "iso:country":"GN",
    "wof:name":"Linsan",
    "wof:placetype":"locality"
},
  "geometry": {"coordinates":[-12.68333,11.76667],"type":"Point"}
}