{
  "type": "Feature",
  "properties": {
    "gn:admin1_code":"K",
    "gn:admin2_code":"39",
    "gn:asciiname":"Togui Oule",
    "gn:country_code":"GN",
    "gn:dem":347,
    "gn:feature_class":"P",
    "gn:feature_code":"PPL",
    "gn:name":"Togui Oul\u00e9",
    "gn:population":0,
    "gn:timezone":"Africa/Conakry",
    "iso:country":"GN",
    "name:und_x_variant":[
        "Togui",
        "Togui Oul\u00e9"
    ],
    "wof:name":"Togui Oule",
    "wof:placetype":"locality"
},
  "geometry": {"coordinates":[-9.16667,11.33333],"type":"Point"}
}