{
  "type": "Feature",
  "properties": {
    "gn:admin1_code":"N",
    "gn:admin2_code":"38",
    "gn:asciiname":"Din",
    "gn:country_code":"GN",
    "gn:dem":526,
    "gn:feature_class":"P",
    "gn:feature_code":"PPL",
    "gn:name":"Din",
    "gn:population":0,
    "gn:timezone":"Africa/Conakry",
    "iso:country":"GN",
    "name:ara_x_preferred":[
        "\u062f\u064a\u0646"
    ],
    "name:cat_x_preferred":[
        "Din"
    ],
    "name:dan_x_preferred":[
        "Din"
    ],
    "name:deu_x_preferred":[
        "Din"
    ],
    "name:est_x_preferred":[
        "DIN"
    ],
    "name:lav_x_preferred":[
        "Dins"
    ],
    "name:nor_x_preferred":[
        "Din"
    ],
    "name:spa_x_preferred":[
        "Din"
    ],
    "wof:name":"Din",
    "wof:placetype":"locality"
},
  "geometry": {"coordinates":[-8.51667,8.06667],"type":"Point"}
}