{
  "type": "Feature",
  "properties": {
    "gn:admin1_code":"F",
    "gn:admin2_code":"17",
    "gn:asciiname":"Telebodou",
    "gn:cc2":"GN",
    "gn:country_code":"GN",
    "gn:dem":620,
    "gn:feature_class":"P",
    "gn:feature_code":"PPL",
    "gn:name":"T\u00e9l\u00e9bodou",
    "gn:population":0,
    "gn:timezone":"Africa/Conakry",
    "iso:country":"GN",
    "name:und_x_variant":[
        "Telebadou",
        "T\u00e9l\u00e9bodou"
    ],
    "wof:name":"Telebodou",
    "wof:placetype":"locality"
},
  "geometry": {"coordinates":[-9.75,9.11667],"type":"Point"}
}