{
  "type": "Feature",
  "properties": {
    "gn:admin1_code":"N",
    "gn:admin2_code":"13",
    "gn:asciiname":"Dandou",
    "gn:cc2":"GN",
    "gn:country_code":"GN",
    "gn:dem":468,
    "gn:feature_class":"P",
    "gn:feature_code":"PPL",
    "gn:name":"Dandou",
    "gn:population":0,
    "gn:timezone":"Africa/Conakry",
    "iso:country":"GN",
    "name:und_x_variant":[
        "Daendou",
        "Dandou"
    ],
    "wof:name":"Dandou",
    "wof:placetype":"locality"
},
  "geometry": {"coordinates":[-10.07611,8.66083],"type":"Point"}
}