{
  "type": "Feature",
  "properties": {
    "gn:admin1_code":"K",
    "gn:admin2_code":"17",
    "gn:asciiname":"Tizinko",
    "gn:country_code":"GN",
    "gn:dem":704,
    "gn:feature_class":"P",
    "gn:feature_code":"PPL",
    "gn:name":"Tizinko",
    "gn:population":0,
    "gn:timezone":"Africa/Conakry",
    "iso:country":"GN",
    "wof:name":"Tizinko",
    "wof:placetype":"locality"
},
  "geometry": {"coordinates":[-9.35,9.25],"type":"Point"}
}