{
  "type": "Feature",
  "properties": {
    "gn:admin1_code":"N",
    "gn:admin2_code":"21",
    "gn:asciiname":"Ourouezou",
    "gn:cc2":"GN",
    "gn:country_code":"GN",
    "gn:dem":619,
    "gn:feature_class":"P",
    "gn:feature_code":"PPL",
    "gn:name":"Ourou\u00e9zou",
    "gn:population":0,
    "gn:timezone":"Africa/Conakry",
    "iso:country":"GN",
    "name:und_x_variant":[
        "Ouzou\u00e9zou",
        "Ourou\u00e9zou"
    ],
    "wof:name":"Ourouezou",
    "wof:placetype":"locality"
},
  "geometry": {"coordinates":[-9.72611,8.57778],"type":"Point"}
}