{
  "type": "Feature",
  "properties": {
    "gn:admin1_code":"N",
    "gn:admin2_code":"01",
    "gn:asciiname":"Toubakouno",
    "gn:country_code":"GN",
    "gn:dem":602,
    "gn:feature_class":"P",
    "gn:feature_code":"PPL",
    "gn:name":"Toubakouno",
    "gn:population":0,
    "gn:timezone":"Africa/Conakry",
    "iso:country":"GN",
    "wof:name":"Toubakouno",
    "wof:placetype":"locality"
},
  "geometry": {"coordinates":[-8.28333,8.51667],"type":"Point"}
}