{
  "type": "Feature",
  "properties": {
    "gn:admin1_code":"F",
    "gn:admin2_code":"05",
    "gn:asciiname":"Sembakounian",
    "gn:cc2":"GN",
    "gn:country_code":"GN",
    "gn:dem":457,
    "gn:feature_class":"P",
    "gn:feature_code":"PPL",
    "gn:name":"Sembakounian",
    "gn:population":0,
    "gn:timezone":"Africa/Conakry",
    "iso:country":"GN",
    "name:und_x_variant":[
        "Simbakounian",
        "Simbacounian",
        "Sambakounian",
        "Sambakougnan",
        "Sambakougnao",
        "Sembakounian"
    ],
    "wof:name":"Sembakounian",
    "wof:placetype":"locality"
},
  "geometry": {"coordinates":[-11.05,10.55],"type":"Point"}
}