{
  "type": "Feature",
  "properties": {
    "gn:admin1_code":"D",
    "gn:admin2_code":"30",
    "gn:asciiname":"Kanderiya",
    "gn:country_code":"GN",
    "gn:dem":27,
    "gn:feature_class":"P",
    "gn:feature_code":"PPL",
    "gn:name":"Kand\u00e9riya",
    "gn:population":0,
    "gn:timezone":"Africa/Conakry",
    "iso:country":"GN",
    "name:und_x_variant":[
        "Kand\u00e9ria",
        "Kand\u00e9riya"
    ],
    "wof:name":"Kanderiya",
    "wof:placetype":"locality"
},
  "geometry": {"coordinates":[-13.26667,9.63333],"type":"Point"}
}