{
  "type": "Feature",
  "properties": {
    "gn:admin1_code":"N",
    "gn:admin2_code":"21",
    "gn:asciiname":"Fassablema",
    "gn:country_code":"GN",
    "gn:dem":717,
    "gn:feature_class":"P",
    "gn:feature_code":"PPL",
    "gn:name":"Fassabl\u00e9ma",
    "gn:population":0,
    "gn:timezone":"Africa/Conakry",
    "iso:country":"GN",
    "wof:name":"Fassablema",
    "wof:placetype":"locality"
},
  "geometry": {"coordinates":[-9.93139,8.66667],"type":"Point"}
}