{
  "type": "Feature",
  "properties": {
    "gn:admin1_code":"N",
    "gn:admin2_code":"01",
    "gn:asciiname":"Kaniangoro",
    "gn:country_code":"GN",
    "gn:dem":640,
    "gn:feature_class":"P",
    "gn:feature_code":"PPL",
    "gn:name":"Kaniangoro",
    "gn:population":0,
    "gn:timezone":"Africa/Conakry",
    "iso:country":"GN",
    "wof:name":"Kaniangoro",
    "wof:placetype":"locality"
},
  "geometry": {"coordinates":[-8.38333,8.51667],"type":"Point"}
}