{
  "type": "Feature",
  "properties": {
    "gn:admin1_code":"D",
    "gn:admin2_code":"31",
    "gn:asciiname":"Bagueya",
    "gn:country_code":"GN",
    "gn:dem":18,
    "gn:feature_class":"P",
    "gn:feature_code":"PPL",
    "gn:name":"Bagu\u00e9ya",
    "gn:population":0,
    "gn:timezone":"Africa/Conakry",
    "iso:country":"GN",
    "name:und_x_variant":[
        "Baqu\u00e9ya",
        "Bagu\u00e9ya"
    ],
    "wof:name":"Bagueya",
    "wof:placetype":"locality"
},
  "geometry": {"coordinates":[-13.57833,9.83861],"type":"Point"}
}