{
  "type": "Feature",
  "properties": {
    "gn:admin1_code":"K",
    "gn:admin2_code":"37",
    "gn:asciiname":"Bambadinga",
    "gn:country_code":"GN",
    "gn:dem":365,
    "gn:feature_class":"P",
    "gn:feature_code":"PPL",
    "gn:name":"Bambadinga",
    "gn:population":0,
    "gn:timezone":"Africa/Conakry",
    "iso:country":"GN",
    "wof:name":"Bambadinga",
    "wof:placetype":"locality"
},
  "geometry": {"coordinates":[-8.55,11.36667],"type":"Point"}
}