{
  "type": "Feature",
  "properties": {
    "gn:admin1_code":"N",
    "gn:admin2_code":"01",
    "gn:asciiname":"Tiekorodougou",
    "gn:country_code":"GN",
    "gn:dem":725,
    "gn:feature_class":"P",
    "gn:feature_code":"PPL",
    "gn:name":"Ti\u00e9korodougou",
    "gn:population":0,
    "gn:timezone":"Africa/Conakry",
    "iso:country":"GN",
    "wof:name":"Tiekorodougou",
    "wof:placetype":"locality"
},
  "geometry": {"coordinates":[-8.41667,8.81667],"type":"Point"}
}