{
  "type": "Feature",
  "properties": {
    "gn:admin1_code":"B",
    "gn:admin2_code":"02",
    "gn:asciiname":"Doniya",
    "gn:country_code":"GN",
    "gn:dem":26,
    "gn:feature_class":"P",
    "gn:feature_code":"PPL",
    "gn:name":"Doniya",
    "gn:population":0,
    "gn:timezone":"Africa/Conakry",
    "iso:country":"GN",
    "wof:name":"Doniya",
    "wof:placetype":"locality"
},
  "geometry": {"coordinates":[-13.73722,9.89806],"type":"Point"}
}