{
  "type": "Feature",
  "properties": {
    "gn:admin1_code":"K",
    "gn:admin2_code":"37",
    "gn:asciiname":"Toumba",
    "gn:country_code":"GN",
    "gn:dem":380,
    "gn:feature_class":"P",
    "gn:feature_code":"PPL",
    "gn:name":"Toumba",
    "gn:population":0,
    "gn:timezone":"Africa/Conakry",
    "iso:country":"GN",
    "name:deu_x_preferred":[
        "Toumba"
    ],
    "name:ell_x_preferred":[
        "\u039c\u03b1\u03b3\u03bf\u03cd\u03bb\u03b1"
    ],
    "wof:name":"Toumba",
    "wof:placetype":"locality"
},
  "geometry": {"coordinates":[-8.65,11.28333],"type":"Point"}
}