{
  "type": "Feature",
  "properties": {
    "gn:admin1_code":"D",
    "gn:admin2_code":"31",
    "gn:asciiname":"Kambamaleya",
    "gn:country_code":"GN",
    "gn:dem":344,
    "gn:feature_class":"P",
    "gn:feature_code":"PPL",
    "gn:name":"Kambamal\u00e9ya",
    "gn:population":0,
    "gn:timezone":"Africa/Conakry",
    "iso:country":"GN",
    "name:und_x_variant":[
        "Kamba",
        "Kambamal\u00e9ya"
    ],
    "wof:name":"Kambamaleya",
    "wof:placetype":"locality"
},
  "geometry": {"coordinates":[-13.33333,10.28333],"type":"Point"}
}