{
  "type": "Feature",
  "properties": {
    "gn:admin1_code":"K",
    "gn:admin2_code":"15",
    "gn:asciiname":"Niantoumandou",
    "gn:country_code":"GN",
    "gn:dem":551,
    "gn:feature_class":"P",
    "gn:feature_code":"PPL",
    "gn:name":"Niantoumandou",
    "gn:population":0,
    "gn:timezone":"Africa/Conakry",
    "iso:country":"GN",
    "wof:name":"Niantoumandou",
    "wof:placetype":"locality"
},
  "geometry": {"coordinates":[-9.08333,9.11667],"type":"Point"}
}