{
  "type": "Feature",
  "properties": {
    "gn:admin1_code":"B",
    "gn:admin2_code":"12",
    "gn:asciiname":"Kambala",
    "gn:country_code":"GN",
    "gn:dem":105,
    "gn:feature_class":"P",
    "gn:feature_code":"PPL",
    "gn:name":"Kambala",
    "gn:population":0,
    "gn:timezone":"Africa/Conakry",
    "iso:country":"GN",
    "name:kan_x_preferred":[
        "\u0c95\u0c82\u0cac\u0cb3"
    ],
    "name:mal_x_preferred":[
        "\u0d15\u0d02\u0d2c\u0d33"
    ],
    "name:tam_x_preferred":[
        "\u0b95\u0bae\u0bcd\u0baa\u0bb3\u0bbe"
    ],
    "name:tcy_x_preferred":[
        "\u0c95\u0c82\u0cac\u0cc1\u0cb2"
    ],
    "wof:name":"Kambala",
    "wof:placetype":"locality"
},
  "geometry": {"coordinates":[-13.46667,11.93333],"type":"Point"}
}