{
  "type": "Feature",
  "properties": {
    "gn:admin1_code":"L",
    "gn:admin2_code":"22",
    "gn:asciiname":"Boundoukoura",
    "gn:country_code":"GN",
    "gn:dem":1154,
    "gn:feature_class":"P",
    "gn:feature_code":"PPL",
    "gn:name":"Boundoukoura",
    "gn:population":0,
    "gn:timezone":"Africa/Conakry",
    "iso:country":"GN",
    "wof:name":"Boundoukoura",
    "wof:placetype":"locality"
},
  "geometry": {"coordinates":[-12.3658,12.0078],"type":"Point"}
}