{
  "type": "Feature",
  "properties": {
    "gn:admin1_code":"N",
    "gn:admin2_code":"13",
    "gn:asciiname":"Daoua",
    "gn:country_code":"GN",
    "gn:dem":479,
    "gn:feature_class":"P",
    "gn:feature_code":"PPL",
    "gn:name":"Daoua",
    "gn:population":0,
    "gn:timezone":"Africa/Conakry",
    "iso:country":"GN",
    "wof:name":"Daoua",
    "wof:placetype":"locality"
},
  "geometry": {"coordinates":[-10.0375,8.67],"type":"Point"}
}