{
  "type": "Feature",
  "properties": {
    "gn:admin1_code":"N",
    "gn:admin2_code":"13",
    "gn:asciiname":"Tangolo",
    "gn:cc2":"GN",
    "gn:country_code":"GN",
    "gn:dem":414,
    "gn:feature_class":"P",
    "gn:feature_code":"PPL",
    "gn:name":"Tangolo",
    "gn:population":0,
    "gn:timezone":"Africa/Conakry",
    "iso:country":"GN",
    "name:und_x_variant":[
        "Tangola",
        "Tangolo"
    ],
    "wof:name":"Tangolo",
    "wof:placetype":"locality"
},
  "geometry": {"coordinates":[-10.46111,8.555],"type":"Point"}
}